Workbook
Name hr_ini: #REF!
Name hr_ini: #REF!
Name hr_ini: #REF!
Name hr_ini: #REF!
Name hr_ini: #REF!
Name hr_ini: #REF!
Name hr_ini: #REF!
Name hr_ini: #REF!
Name hr_ini: #REF!
Name hr_ini: #REF!
Name hr_ini: #REF!
Name hr_ini: #REF!
Name hr_ini: #REF!
Name hr_ini: #REF!
Name hr_ini: #REF!
Name hr_limite: #REF!
Name hr_limite: #REF!
Name hr_limite: #REF!
Name hr_limite: #REF!
Name hr_limite: #REF!
Name hr_limite: #REF!
Name hr_limite: #REF!
Name hr_limite: #REF!
Name hr_limite: #REF!
Name hr_limite: #REF!
Name hr_limite: #REF!
Name hr_limite: #REF!
Name hr_limite: #REF!
Name hr_limite: #REF!
Name hr_limite: #REF!
Name lista_causa: [5]!causa_raiz[Causa Raiz]
Name lista_causa: [5]!causa_raiz[Causa Raiz]
Name lista_causa: [5]!causa_raiz[Causa Raiz]
Name lista_causa: [5]!causa_raiz[Causa Raiz]
Name lista_causa: [5]!causa_raiz[Causa Raiz]
Name lista_causa: [5]!causa_raiz[Causa Raiz]
Name lista_causa: [5]!causa_raiz[Causa Raiz]
Name lista_causa: [5]!causa_raiz[Causa Raiz]
Name lista_causa: #REF!
Name lista_causa: [5]!causa_raiz[Causa Raiz]
Name lista_causa: [5]!causa_raiz[Causa Raiz]
Name lista_causa: [5]!causa_raiz[Causa Raiz]
Name lista_causa: #REF!
Name lista_causa: [5]!causa_raiz[Causa Raiz]
Name lista_causa: [5]!causa_raiz[Causa Raiz]
Name lista_causa: [5]!causa_raiz[Causa Raiz]
Name lista_causa: [5]!causa_raiz[Causa Raiz]
Name lista_causa: #REF!
Name lista_causa: #REF!
Name lista_causa: #REF!
Name lista_causa: #REF!
Name logo: #REF!
Name logo: #REF!
Name logo: #REF!
Name logo: #REF!
Name logo: #REF!
Name logo: #REF!
Name logo: #REF!
Name logo: #REF!
Name logo: #REF!

Sheet TEMPOS
B2: DURAÇÃO DAS AULAS | R2: =D4+H4+L4+P4+T4+X4 -> 0.16538194
B4: 0. COMECE POR AQUI | D4: =D6+D8+D10+D12+D14+D16+D18 -> 0.020196759 | F4: 1. ESTRATÉGICO | H4: =H6+H8+H10+H12+H14+H16+H18 -> 0.041851852 | J4: 2. MARKETING | L4: =L6+L8+L10+L12+L14+L16+L18 -> 0.020659722 | N4: 3. VENDAS | P4: =P6+P8+P10+P12+P14+P16+P18 -> 0.029097222 | R4: 4. PESSOAS | T4: =T6+T8+T10+T12+T14+T16+T18 -> 0.032291667 | V4: 5. FINANCEIRO | X4: =X6+X8+X10+X12+X14+X16+X18+X24 -> 0.021284722
B6: MAPA DA METODOLOGIA | F6: MISSÃO, VISÃO E VALORES | H6: 0.0049768519 | J6: RAIO-X DO CLIENTE DOS SONHOS | L6: 0.0030555556 | N6: AMPULHETA DE VENDAS | P6: 0.0066203704 | R6: RECRUTAMENTO E SELEÇÃO | T6: 0.007025463 | V6: GESTÃO MATRICIAL DE DESPESAS | X6: 0.0074884259
B8: AULA INAUGURAL | D8: 0.0054861111 | F8: MAPA DE CARGOS E FUNÇÕES | H8: 0.0044675926 | J8: CRIAÇÃO DE CONTEÚDOS VIRAIS | L8: 0.0075578704 | N8: GESTÃO DA BASE DE CLIENTES | P8: 0.0034953704 | R8: TREINAMENTO COM FLUXOGRAMA | T8: 0.0051967593 | V8: GESTÃO MATRICIAL DE RECEITAS | X8: 0.0083217593
B10: TESTE DE NIVELAMENTO + EVOLUÇÃO POR PILAR + PPE | D10: 0.0076157407 | F10: REGULAMENTO INTERNO | H10: 0.0036921296 | J10: SOCIAL SELLER | L10: 0.010046296 | N10: SCRIPT DE ATENDIMENTO IDEAL | P10: 0.0034606481 | R10: PRODUTIVIDADE X OCIOSIDADE | T10: 0.0035648148 | V10: GESTÃO DO FLUXO DE CAIXA | X10: 0.005474537
B12: CONTROLE DE METAS + FOTOGRAFIA DA EMPRESA | D12: 0.0070949074 | F12: DESDOBRAMENTO DE METAS | H12: 0.0071875 | N12: QUEBRA DE OBJEÇÕES | P12: 0.0058912037 | R12: FEEDBACKS 1 X 1 COM SEU TIME | T12: 0.0054050926
F14: REUNIÃO NOTA 10 (DIÁRIA) | H14: 0.0032986111 | N14: GATILHOS MENTAIS | P14: 0.0096296296 | R14: TREINAMENTO DAS LIDERANÇAS | T14: 0.0048958333
F16: ANÁLISE DE RESULTADOS DO MÊS | H16: 0.010694444 | R16: PESQUISA DE CLIMA NA EMPRESA | T16: 0.0030439815
F18: CRIAÇÃO DE CULTURA FORTE | H18: 0.0075347222 | R18: ENTREVISTA DE DESLIGAMENTO | T18: 0.0031597222
B20: EXPERTS CONVIDADOS | R20: =D22+H22+L22+P22+T22+X22 -> 0.10606481
F22: 1. ESTRATÉGICO | H22: =H24+H26+H28+H30+H32+H34+H36 -> 0.033275463 | J22: 2. MARKETING | L22: =L24+L26+L28+L30+L32+L34+L36 -> 0.020127315 | N22: 3. VENDAS | P22: =P24+P26+P28+P30+P32+P34+P36 -> 0.052662037 | R22: 4. PESSOAS | T22: =T24+T26+T28+T30+T32+T34+T36+T43 -> 0 | V22: 5. FINANCEIRO | X22: =X24+X26+X28+X30+X32+X34+X36+X43 -> 0
F24: REMUNERAÇÃO VARIÁVEL (TIAGO GUEDES) | H24: 0.033275463 | J24: LIVES SHOP (JULIANA TURMINA) | L24: 0.020127315 | N24: AUTOMAÇÃO E IA PRA VENDAS (ERIC LUCIANO) | P24: 0.052662037 | R24: COMO CRIAR UMA EQUIPE EXCEPCIONAL (2 NO VAREJO)

Sheet PAINEL
A1: SCRIPT DE ATENDIMENTO
B2: DASHBOARD DA MENTORIA | R2: > CLIQUE NAS CÉLULAS PARA ACESSAR O CONTEÚDO < | AB2: LEGENDA
AB3: ✓
B4: 0. COMECE POR AQUI | D4: STATUS | F4: 1. ESTRATÉGICO | H4: STATUS | J4: 2. MARKETING | L4: STATUS | N4: 3. VENDAS | P4: STATUS | R4: 4. PESSOAS | T4: STATUS | V4: 5. FINANCEIRO | X4: STATUS | AB4: X
B6: TESTE DE NIVELAMENTO | D6: ✓ | F6: MISSÃO, VISÃO E VALORES | H6: X | J6: RAIO-X DO CLIENTE DOS SONHOS | L6: X | N6: AMPULHETA DE VENDAS | P6: X | R6: RECRUTAMENTO E SELEÇÃO | T6: X | V6: GESTÃO MATRICIAL DE DESPESAS | X6: X
B8: EVOLUÇÃO POR PILAR | D8: ✓ | F8: MAPA DE CARGOS E FUNÇÕES | H8: X | J8: CRIAÇÃO DE CONTEÚDOS VIRAIS | L8: X | N8: GESTÃO DA BASE DE CLIENTES | P8: X | R8: TREINAMENTO COM FLUXOGRAMA | T8: X | V8: GESTÃO MATRICIAL DE RECEITAS | X8: X
B10: PPE (PLANO DE PRIORIDADES DA EMPRESA) | D10: ✓ | F10: REGULAMENTO INTERNO | H10: X | J10: SOCIAL SELLER | L10: X | N10: SCRIPT DE ATENDIMENTO IDEAL | P10: X | R10: PRODUTIVIDADE X OCIOSIDADE | T10: X | V10: GESTÃO DO FLUXO DE CAIXA | X10: X
B12: CONTROLE DE METAS | D12: X | F12: DESDOBRAMENTO DE METAS | H12: X | J12: LIVES SHOP | L12: X | N12: QUEBRA DE OBJEÇÕES | P12: X | R12: FEEDBACKS 1 X 1 COM SEU TIME | T12: X
B14: FOTOGRAFIA DA EMPRESA | D14: ✓ | F14: REUNIÃO NOTA 10 (DIÁRIA) | H14: X | N14: GATILHOS MENTAIS | P14: X | R14: TREINAMENTO DAS LIDERANÇAS | T14: X
F16: ANÁLISE DE RESULTADOS DO MÊS | H16: X | R16: PESQUISA DE CLIMA NA EMPRESA | T16: X
F18: CRIAÇÃO DE CULTURA FORTE | H18: X | R18: ENTREVISTA DE DESLIGAMENTO | T18: X
F20: REMUNERAÇÃO VARIÁVEL | H20: X

Sheet 0.1
B2: < CLIQUE AQUI E VOLTE AO PAINEL INICIAL | C2: CADEIA DE VALOR
B4: PILAR ESTRATÉGICO | F4: PILAR DE MARKETING | J4: PILAR VENDAS | N4: PILAR DE PESSOAS | R4: PILAR FINANCEIRO | W4: SOCIAL MEDIA | AA4: CAPTAÇÃO DE CONTEÚDOS/EDIÇÃO DE VÍDEOS | AE4: TRÁFEGO PAGO | AI4: SUCESSO DO CLIENTE (CS) | AM4: DESIGN
B6: NATASHA E BRUNO | F6: NATASHA E BRUNO | J6: NATASHA E BRUNO | N6: NATASHA E BRUNO | R6: NATASHA E BRUNO | W6: NATASHA E BRUNO | AA6: NATASHA E BRUNO | AE6: BRUNO | AI6: NATASHA E BRUNO | AM6: NATASHA
B8: ROTINAS DO PILAR | C8: NÍVEL CRÍTICO | D8: NOTA ATUAL | F8: ROTINAS DO PILAR | G8: NÍVEL CRÍTICO | H8: NOTA ATUAL | J8: ROTINAS DO PILAR | K8: NÍVEL CRÍTICO | L8: NOTA ATUAL | N8: ROTINAS DO PILAR | O8: NÍVEL CRÍTICO | P8: NOTA ATUAL | R8: ROTINAS DO PILAR | S8: NÍVEL CRÍTICO | T8: NOTA ATUAL | W8: ROTINAS DO PILAR | X8: NÍVEL CRÍTICO | Y8: NOTA ATUAL | AA8: ROTINAS DO PILAR | AB8: NÍVEL CRÍTICO | AC8: NOTA ATUAL | AE8: ROTINAS DO PILAR | AF8: NÍVEL CRÍTICO | AG8: NOTA ATUAL | AI8: ROTINAS DO PILAR | AJ8: NÍVEL CRÍTICO | AK8: NOTA ATUAL | AM8: ROTINAS DO PILAR | AN8: NÍVEL CRÍTICO | AO8: NOTA ATUAL
B10: DEFINIÇÃO E ALINHAMENTO COM O TIME DE MISSÃO, VISÃO E VALORES (DO CEO ATÉ A OPERAÇÃO) | C10: ALTO | D10: 0 | F10: RAIO-X DO CLIENTE DOS SONHOS, ANÁLISE DA CONCORRÊNCIA E ESTUDO DE MERCADO | G10: ALTO | H10: 0 | J10: EXECUÇÃO DIÁRIA DA AMPULHETA DE VENDAS (DA PROSPECÇÃO ATÉ A VENDA E INDICAÇÕES) | K10: ALTO | L10: 2 | N10: ROTINAS DE RECRUTAMENTO E SELEÇÃO DE NOVOS COLABORADORES | O10: ALTO | P10: 3 | R10: ROTINAS DE CONTAS A PAGAR (GESTÃO DE MULTAS E JUROS EM DIA) | S10: ALTO | T10: 10 | W10: ROTINA DE REUNIÃO DE BRIEFING E DEFINIÇÃO DAS ESTRATÉGICAS DO CLIENTE | X10: ALTO | Y10: 8 | AA10: ROTINA DE REUNIÃO DE BRIEFING E DEFINIÇÃO DAS ESTRATÉGICAS COM O TIME DE SOCIAL MEDIA | AB10: ALTO | AC10: 10 | AE10: ROTINA DE REUNIÃO DE BRIEFING E DEFINIÇÃO DAS ESTRATÉGICAS DO CLIENTE | AF10: ALTO | AG10: 7 | AI10: ROTINA DE REUNIÕES DE BOAS-VINDAS E ALINHAMENTO COM O CLIENTE | AJ10: ALTO | AK10: 8 | AM10: ROTINA DE REUNIÃO DE BRIEFING E DEFINIÇÃO DAS ESTRATÉGICAS COM O SOCIAL MEDIA, TRÁFEGO E CAPTAÇÃO DE CONTEÚDO | AN10: ALTO | AO10: 3
B11: GESTÃO DO ORGANOGRAMA DA EMPRESA E MAPEAMENTO DOS CARGOS E FUNÇÕES | C11: ALTO | D11: 2 | F11: GESTÃO DE PÁGINAS, SITES, GOOGLE MEU NEGÓCIO | G11: ALTO | H11: 0 | J11: GESTÃO CONTÍNUA DA BASE DE CLIENTES (ATIVOS E INATIVOS) | K11: ALTO | L11: 0 | N11: TREINAMENTO INTRODUTÓRIO NA CULTURA E REG. INTERNO PARA NOVOS FUNCIONÁRIOS | O11: ALTO | P11: 2 | R11: ROTINAS DE CONTAS A RECEBER (GESTÃO DA CONSTRUÇÃO DE UM CAIXA FORTE) | S11: ALTO | T11: 5 | W11: ROTINA DE CRIAÇÃO DE PLANEJAMENTO DIÁRIOS, SEMANAIS E MENSAIS DE CONTEÚDO | X11: ALTO | Y11: 8 | AA11: GESTÃO DO CALENDÁRIOS E DE ROTAS DAS VISITAS PARA CAPTAÇÃO DE CONTEÚDO | AB11: ALTO | AC11: 8 | AE11: ROTINA DE DEFINIÇÃO DE METAS DE CAMPANHA (ALCANCE, CLIQUES, LEADS, CONVERSÃO...) | AF11: ALTO | AG11: 5 | AI11: ROTINA DE ATENDIMENTO AO CLIENTE DIÁRIO E SEMANAL (MODO BABÁ) | AJ11: ALTO | AK11: 1 | AM11: GESTÃO DE PRIORIZAÇÃO DAS PRODUÇÕES DE CONTEÚDO (AGENDA DE POSTAGEM) | AN11: ALTO | AO11: 3
B12: ELABORAÇÃO E APRESENTAÇÃO DO REGULAMENTO INTERNO PARA GARANTIR REGRAS E PADRÕES DA EMPRESA | C12: ALTO | D12: 2 | F12: GESTÃO DAS REDES SOCIAIS E CRIAÇÃO DE CONTEÚDOS ORGÂNICOS/VIRAIS | G12: ALTO | H12: 0 | J12: ROTINA/SCRIPT DE ATENDIMENTO AO LEAD/CLIENTE | K12: ALTO | L12: 0 | N12: TREINAMENTO E CAPACITAÇÃO DE COLABORADORES NAS SUAS FUNÇÕES (COM FLUXOGRAMAS) | O12: ALTO | P12: 0 | R12: GESTÃO DO FLUXO DE CAIXA (GESTÃO DA PREVISIBILIDADE DA EMPRESA MÊS A MÊS E PRÓ LABORE DOS SÓCIOS) | S12: ALTO | T12: 2 | W12: ROTINA DE PROGRAMAÇÃO DE POSTAGENS NAS PLATAFORMAS DO CLIENTE | X12: MÉDIO | Y12: 8 | AA12: ROTINA DE VERIFICAÇÃO/CHECKLIST DOS MATERIAIS NECESSÁRIOS PARA A VISITA (MICROFONE, CAMERA, LUZ...) | AB12: MÉDIO | AC12: 8 | AE12: ROTINA DE CRIAÇÃO DA CAMPANHAS, CONJUNTOS DE ANÚNCIOS E CRIATIVOS | AF12: MÉDIO | AG12: 8 | AI12: ROTINA DE COLETA DE FEEDBACKS DOS CLIENTES E COMUNICAÇÃO COM O TIME INTERNO | AJ12: ALTO | AK12: 0 | AM12: ROTINA DE PRODUÇÃO E EDIÇÃO DE CONTEÚDOS (POSTS ESTÁTICOS/ARTES) | AN12: ALTO | AO12: 3
B13: DEFINIÇÃO DE METAS ANUAIS E DESDOBRAMENTO DE METAS MÊS A MÊS | C13: ALTO | D13: 0 | F13: ROTINAS DE SOCIAL SELLER (PROSPECÇÃO ATIVA NAS REDES SOCIAIS) | G13: MÉDIO | H13: 5 | J13: DIAGNÓSTICO DO CLIENTE E MAPEAMENTO DAS NECESSIDADES (AMPULHETA DE VENDAS) | K13: ALTO | L13: 1 | N13: AVALIAÇÃO DE DESEMPENHO DOS FUNCIONÁRIOS | O13: ALTO | P13: 2 | R13: FECHAMENTO MENSAL DOS RESULTADOS E ANÁLISE DA DRE DA EMPRESA | S13: ALTO | T13: 0 | W13: ROTINA DE ROTEIRIZAÇÃO E PRODUÇÃO DE LEGENDAS E COPYS | X13: MÉDIO | Y13: 10 | AA13: ROTINA DA REALIZAÇÃO DA VISITA NAS EMPRESAS (ATENDIMENTO E EXPLICAÇÃO DO SERVIÇO PARA O CLIENTE) | AB13: ALTO | AC13: 10 | AE13: ROTINA DE MONITORAMENTO DE DESEMPENHO DA CAMPANHAS E ANÚNCIOS | AF13: ALTO | AG13: 5 | AI13: GESTÃO DE RISCOS DOS CLIENTES (RECLAMAÇÕES E QUEDA DE ENGAJAMENTO) | AJ13: ALTO | AK13: 0 | AM13: ROTINA DE REVISÃO DOS MATERIAIS PRODUZIDOS (CHECKLIST ANTES DO ENVIO PARA CS) | AN13: MÉDIO | AO13: 3
B14: ROTINA DE REUNIÃO MENSAL: PARA ANÁLISE DOS RESULTADOS (POR ÁREA E INDICADOR) | C14: ALTO | D14: 0 | F14: GESTÃO DE TRÁFEGO PAGO/ANÚNCIOS ONLINE | G14: ALTO | H14: 0 | J14: ROTINA DE COLETA E DIVULGAÇÃO DE PROVAS SOCIAIS | K14: ALTO | L14: 0 | N14: ROTINA DE FEEDBACKS COM FUNCIONÁRIOS (1 A 1) LÍDERES E LIDERADOS | O14: ALTO | P14: 0 | R14: ROTINAS DE PRECIFICAÇÃO E ANÁLISE DAS MARGENS DE LUCRO | S14: ALTO | T14: 3 | W14: ROTINA DE REVISÃO E APROVAÇÃO DE CONTEÚDOS (TEXTO, ESTÉTICA, COERÊNCIA...) | X14: ALTO | Y14: 8 | AA14: ROTINA DE CAPTAÇÃO DAS IMAGENS | AB14: ALTO | AC14: 8 | AE14: ROTINA DE PRODUÇÃO DE RELATÓRIOS SEMANAIS E QUINZENAIS COM DADOS DE DESEMPENHO | AF14: ALTO | AG14: 1 | AI14: GESTÃO DE CALENDÁRIO/AGENDA/ROTA INTERNA DA EQUIPE E CEOs | AJ14: ALTO | AK14: 5 | AM14: ROTINA DE ORGANIZAÇÃO E ATUALIZAÇÃO DE ARQUIVOS E REFERÊNCIAS DAS ARTES (CATÁLOGO) | AN14: MÉDIO | AO14: 0
B15: ROTINA DE REUNIÃO SEMANAL: PARA ALINHAMENTO 1 A 1 (COM LÍDERES DE CADA ÁREA) | C15: ALTO | D15: 0 | F15: PARCERIAS COM EMPRESAS E NEGÓCIOS ESTRATÉGICOS | G15: MÉDIO | H15: 5 | J15: ROTINA DE FOLLOWUP DE PROPOSTAS EM ABERTO PARA CLIENTES | K15: ALTO | L15: 0 | N15: ROTINAS TREINAMENTO E CAPACITAÇÃO DAS LIDERANÇAS DA EMPRESA | O15: MÉDIO | P15: 8 | R15: GESTÃO MATRICIAL DE CUSTOS E DESPESAS (CONTROLE LINHA A LINHA DE TODOS OS GASTOS) | S15: ALTO | T15: 0 | W15: ROTINA DE PRODUÇÃO E EDIÇÃO DE CONTEÚDOS (FOTOS, REELS, STORIES E VÍDEOS) | X15: ALTO | Y15: 8 | AA15: ROTINA DE ENVIO DOS MATERIAIS COLETADOS NA VISITA REALIZADA (DRIVE, TELEGRAM, WHATSAPP, EMAIL...) | AB15: ALTO | AC15: 5 | AE15: ROTINA DE REUNIÃO DE ALINHAMENTO COM O CLIENTE (APRESENTAÇÃO, FEEDBACKS, COLETA DE INFORMAÇÕES...) | AF15: ALTO | AG15: 5 | AI15: ROTINA DE ALINHAMENTO COM TIME INTERNO DA EMPRESA (REUNIÕES, WHATSAPP...) | AJ15: ALTO | AK15: 8
B16: ROTINA DE REUNIÃO DIÁRIA: PARA ALINHAMENTO DO TIME (FOCO NAS ROTINAS E PADRÕES) | C16: ALTO | D16: 0 | F16: GESTÃO DE GRUPO VIP NO WHATSAPP/MENSAGENS VIA LISTA DE TRANSMISSÃO | G16: MÉDIO | H16: NA | J16: ELABORAÇÃO E CONSTRUÇÃO DE ORÇAMENTOS PARA O CLIENTE | K16: MÉDIO | L16: 6 | N16: GESTÃO DA FOLHA DE PAGAMENTO E DA REMUNERAÇÃO VARIÁVEL (SE HOUVER) | O16: MÉDIO | P16: 10 | R16: GESTÃO MATRICIAL DE RECEITAS E VENDAS (CONTROLE DE VOLUME E LUCRO) | S16: ALTO | T16: 5 | W16: GESTÃO DE ANÁLISE DE RESULTADOS (INDICADORES) DOS POSTS PARA PADRONIZAÇÃO DE BOAS PRÁTICAS E AÇÕES CORRETIVAS | X16: ALTO | Y16: 1 | AA16: ROTINA DE EDIÇÃO E PRODUÇÃO DOS MATERIAIS COLETADOS | AB16: ALTO | AC16: 6 | AE16: ROTINA DE ALINHAMENTO COM TIME INTERNO DA EMPRESA (REUNIÕES, WHATSAPP...) | AF16: ALTO | AG16: 5 | AI16: ROTINA DE ENVIO DE MATERIAIS PARA APROVAÇÃO DO CLIENTE (RECEBIDO PELO TIME INTERNO) | AJ16: ALTO | AK16: 5
B17: ROTINA DE TREINAMENTO E FORMAÇÃO DE NOVAS LIDERANÇAS PARA AS POSIÇÕES CRÍTICAS | C17: MÉDIO | D17: 5 | F17: ROTINA DE LIVES SHOP PARA DIVULGAÇÃO DE PRODUTOS/OFERTAS ESPECIAIS | G17: MÉDIO | H17: NA | J17: ROTINA DE QUEBRA DE OBJEÇÕES E USO DE GATILHOS MENTAIS | K17: MÉDIO | L17: 7 | N17: AÇÕES DE PREMIAÇÃO, BONIFICAÇÃO E DE PROMOÇÃO DA MERITOCRACIA | O17: MÉDIO | P17: 0 | R17: ROTINA DE EMISSÃO DE NOTAS FISCAIS | S17: MÉDIO | T17: 10 | W17: ROTINA DE REUNIÃO DE ALINHAMENTO COM O CLIENTE (APRESENTAÇÃO, FEEDBACKS, COLETA DE INFORMAÇÕES...) | X17: ALTO | Y17: 5 | AI17: ROTINA DE ATUALIZAÇÃO E GESTÃO DO CATÁLOGO DE TRABALHOS REALIZADOS (DRIVE DOS CLIENTES) | AJ17: MÉDIO | AK17: 0
B18: AÇÕES DE DESENVOLVIMENTO E FORTALECIMANTO DA CULTURA ORGANIZACIONAL | C18: BAIXO | D18: 0 | F18: PARCERIAS COM INFLUENCERS E PROFISSIONAIS DO NICHO | G18: BAIXO | H18: 0 | J18: ROTINA DE UPSELL, DOWNSELL, CROSSELL E COMBOS NAS NEGOCIAÇÕES | K18: MÉDIO | L18: 5 | N18: PESQUISA DE CLIMA ORGANIZACIONAL PARA PADRONIZAÇÃO DE BOAS PRÁTICAS E AÇÕES CORRETIVAS | O18: MÉDIO | P18: 0 | R18: GESTÃO DE INADIMPLENTES | S18: MÉDIO | T18: 10 | W18: ROTINA DE ALINHAMENTO COM TIME INTERNO DA EMPRESA (REUNIÕES, WHATSAPP...) | X18: ALTO | Y18: 1
B19: ROTINA DE ANÁLISE DE CONCORRENTES E TENDÊNCIAS DE MERCADO PARA O SETOR (RISCOS E OPORTUNIDADES) | C19: BAIXO | D19: 0 | F19: ELABORAÇÃO DE MATERIAIS, FOLDERS, PANFLETOS INSTITUCIONAIS, CARTAZES, ETC | G19: BAIXO | H19: 0 | J19: GESTÃO DE FERRAMENTAS DE AUTOMAÇÃO E I.A. (INTELIGÊNCIA ARTIFICIAL) | K19: BAIXO | L19: 5 | N19: ROTINAS DE PROCESSO DEMISSIONAL E ENTREVISTA DE DESLIGAMENTO (SE APLICÁVEL) | O19: BAIXO | P19: 0 | R19: GESTÃO DO FUNDO DE RESERVA E PRÓ-LABORE DOS SÓCIOS | S19: BAIXO | T19: 0
B21: MÉDIA DO PILAR | D21: =AVERAGE(D10:D19) -> 0.9 | F21: MÉDIA DO PILAR | H21: =AVERAGE(H10:H19) -> 1.25 | J21: MÉDIA DO PILAR | L21: =AVERAGE(L10:L19) -> 2.6 | N21: MÉDIA DO PILAR | P21: =AVERAGE(P10:P19) -> 2.5 | R21: MÉDIA DO PILAR | T21: =AVERAGE(T10:T19) -> 4.5 | W21: MÉDIA DO PILAR | Y21: =AVERAGE(Y10:Y19) -> 6.3333333 | AA21: MÉDIA DO PILAR | AC21: =AVERAGE(AC10:AC19) -> 7.8571429 | AE21: MÉDIA DO PILAR | AG21: =AVERAGE(AG10:AG19) -> 5.1428571 | AI21: MÉDIA DO PILAR | AK21: =AVERAGE(AK10:AK19) -> 3.375 | AM21: MÉDIA DO PILAR | AO21: =AVERAGE(AO10:AO19) -> 2.4

Sheet 0.2
B2: < CLIQUE AQUI E VOLTE AO PAINEL INICIAL | C2: AVALIAÇÃO DOS PILARES EMPRESARIAIS (EVOLUÇÃO TRIMESTRAL)
B4: PILARES DO TESTE DE NIVELAMENTO EMPRESARIAL | C4: Coluna preenchida de forma automática | D4: Preencher a data do onboarding e colcar valores nas datas | E4: AVALIAÇÃO 1 (90 dias após o onboarding) | F4: AVALIAÇÃO 2 (180 dias após a Avaliação 1) | G4: AVALIAÇÃO 3 (270 dias após a Avaliação 2)
C5: =TODAY() -> 45951 | D5: 45938 | E5: =D5+90 -> 46028 | F5: =E5+90 -> 46118 | G5: =F5+90 -> 46208
B6: ESTRATÉGICO | C6: ='0.1'!D21 -> 0.9 | D6: =C6 -> 0.9
B7: MARKETING | C7: ='0.1'!H21 -> 1.25 | D7: =C7 -> 1.25
B8: VENDAS | C8: ='0.1'!L21 -> 2.6 | D8: =C8 -> 2.6
B9: PESSOAS | C9: ='0.1'!P21 -> 2.5 | D9: =C9 -> 2.5
B10: FINANCEIRO | C10: ='0.1'!T21 -> 4.5 | D10: =C10 -> 4.5
B11: SOCIAL MEDIA | C11: ='0.1'!Y21 -> 6.3333333 | D11: 6.3
B12: CAPTAÇÃO DE CONTEÚDOS | C12: ='0.1'!AC21 -> 7.8571429 | D12: 7.9
B13: TRÁFEGO PAGO | C13: ='0.1'!AG21 -> 5.1428571 | D13: 5.1
B14: SUCESSO DO CLIENTE | C14: ='0.1'!AK21 -> 3.375 | D14: 3.4
B15: DESIGN | C15: ='0.1'!AO21 -> 2.4 | D15: 2.4
B16: TOTAL | C16: =AVERAGE(C6:C15) -> 3.6858333 | D16: 3.7
D17: =SUM(D6:D16) -> 40.55
B18: LEGENDA DO GRÁFICO | E18: ABAIXO DE 6 | F18: ENTRE 6,1 E 8 | G18: ENTRE 8,1 E 10

Sheet 0.3
D2: < CLIQUE AQUI E VOLTE AO PAINEL INICIAL | E2: PLANO DE PRIORIDADES DA EMPRESA
C4: # | D4: PILAR | E4: ROTINA | F4: NÍVEL CRÍTICO | G4: NOTA ATUAL | H4: AÇÃO CORRETIVA | I4: QUEM | J4: PRAZO | K4: STATUS | M4: LEGENDA
C6: 1 | D6: ESTRATÉGICO | E6: DEFINIÇÃO E ALINHAMENTO COM O TIME DE MISSÃO, VISÃO E VALORES (DO CEO ATÉ A OPERAÇÃO) | F6: ALTO | G6: 0 | H6: 1. ASSISTIR A AULA DE MISSÃO, VISÃO E VALORES PARA DEFINIR ESSES PILARES NA EMPRESA (USAR PLANILHA 1.1) 2. REALIZAR REUNIÃO DE ALINHAMENTO COM O TIME PARA INFORMAR A TODOS ESSES 3 PRINCÍPIOS | I6: BRUNO | J6: 46028 | K6: EM ANDAMENTO | M6: A INICIAR
C7: =C6+1 -> 2 | D7: ESTRATÉGICO | E7: GESTÃO DO ORGANOGRAMA DA EMPRESA E MAPEAMENTO DOS CARGOS E FUNÇÕES | F7: ALTO | G7: 2 | H7: 1. ASSISTIR A AULA DE CARGOS E FUNÇÕES PARA DEFINIR AS EXPECTATIVAS E ATIVIDADE DE CADA CARGO (USAR PLANILHA 1.2) 2. REALIZAR REUNIÃO DE ALINHAMENTO COM O TIME PARA TRAZER CLAREZA A RESPEITO DAS FUNÇÕES DE TODOS OS MEMBROS DA EQUIPE | I7: NATASHA | J7: 46028 | K7: A INICIAR | M7: EM ANDAMENTO
C8: =C7+1 -> 3 | D8: ESTRATÉGICO | E8: ELABORAÇÃO E APRESENTAÇÃO DO REGULAMENTO INTERNO PARA GARANTIR REGRAS E PADRÕES DA EMPRESA | F8: ALTO | G8: 2 | H8: 1. ASSISTIR A AULA DE REGULAMENTO INTERNO PARA CONSTRUIR O DOCUMENTO QUE CONTÉM AS REGRAS E PADRÕES DA EMPRESA (USAR PLANILHA 1.3) 2. REALIZAR REUNIÃO DE ALINHAMENTO COM O TIME PARA VALIDAR O DOCUMENTO DE REGULAMENTO INTERNO COM A EQUIPE | I8: NATASHA | J8: 46028 | K8: A INICIAR | M8: CONCLUÍDA
C9: =C8+1 -> 4 | D9: ESTRATÉGICO | E9: DEFINIÇÃO DE METAS ANUAIS E DESDOBRAMENTO DE METAS MÊS A MÊS | F9: ALTO | G9: 0 | H9: 1. ASSISTIR A AULA DE CONTROLE DE METAS E FOTOGRAFIA DA EMPRESA PARA OTIMIZAR OS CONTROLES DA LIDERANÇA (USAR PLANILHA 0.4) 2. CRIAR ROTINA DA LIDERANÇA DE ANÁLISE DOS DADOS APÓS O FECHAMENTO DO RESULTADO MENSAL | I9: BRUNO | J9: 46028 | K9: A INICIAR | M9: ATRASADA
C10: =C9+1 -> 5 | D10: ESTRATÉGICO | E10: ROTINA DE REUNIÃO MENSAL: PARA ANÁLISE DOS RESULTADOS (POR ÁREA E INDICADOR) | F10: ALTO | G10: 0 | H10: 1. ASSISTIR A AULA DE ANÁLISE DOS RESULTADOS MENSAIS (MÓDULO 1) DA EMPRESA PARA CRIAR ROTINA COM SÓCIOS E LÍDERES 2. CRIAR ROTINA DA LIDERANÇA DE ANÁLISE DOS DADOS APÓS O FECHAMENTO DO RESULTADO MENSAL | I10: BRUNO | J10: 46028 | K10: A INICIAR
C11: =C10+1 -> 6 | D11: ESTRATÉGICO | E11: ROTINA DE REUNIÃO SEMANAL: PARA ALINHAMENTO 1 A 1 (COM LÍDERES DE CADA ÁREA) | F11: ALTO | G11: 0 | K11: A INICIAR
C12: =C11+1 -> 7 | D12: ESTRATÉGICO | E12: ROTINA DE REUNIÃO DIÁRIA: PARA ALINHAMENTO DO TIME (FOCO NAS ROTINAS E PADRÕES) | F12: ALTO | G12: 0 | H12: 1. ASSISTIR A AULA DE REUNIÃO DIÁRIA NOTA 10 PARA OTIMIZAR OS ALINHAMENTO COM A EQUIPE 2. CRIAR ROTINA DE REUNIÕES DIÁRIAS COM O TIME PARA REDUZIR RETRABALHOS E FALHAS DE COMUNICAÇÃO | I12: NATASHA | J12: 46028 | K12: A INICIAR
C13: =C12+1 -> 8 | D13: MARKETING | E13: RAIO-X DO CLIENTE DOS SONHOS, ANÁLISE DA CONCORRÊNCIA E ESTUDO DE MERCADO | F13: ALTO | G13: 0 | K13: A INICIAR
C14: =C13+1 -> 9 | D14: MARKETING | E14: GESTÃO DE PÁGINAS, SITES, GOOGLE MEU NEGÓCIO | F14: ALTO | G14: 0 | K14: A INICIAR
C15: =C14+1 -> 10 | D15: MARKETING | E15: GESTÃO DAS REDES SOCIAIS E CRIAÇÃO DE CONTEÚDOS ORGÂNICOS/VIRAIS | F15: ALTO | G15: 0 | K15: A INICIAR
C16: =C15+1 -> 11 | D16: MARKETING | E16: GESTÃO DE TRÁFEGO PAGO/ANÚNCIOS ONLINE | F16: ALTO | G16: 0 | K16: A INICIAR
C17: =C16+1 -> 12 | D17: VENDAS | E17: EXECUÇÃO DIÁRIA DA AMPULHETA DE VENDAS (DA PROSPECÇÃO ATÉ A VENDA E INDICAÇÕES) | F17: ALTO | G17: 2 | K17: A INICIAR
C18: =C17+1 -> 13 | D18: VENDAS | E18: GESTÃO CONTÍNUA DA BASE DE CLIENTES (ATIVOS E INATIVOS) | F18: ALTO | G18: 0 | K18: A INICIAR
C19: =C18+1 -> 14 | D19: VENDAS | E19: ROTINA/SCRIPT DE ATENDIMENTO AO LEAD/CLIENTE | F19: ALTO | G19: 0 | K19: A INICIAR
C20: =C19+1 -> 15 | D20: VENDAS | E20: DIAGNÓSTICO DO CLIENTE E MAPEAMENTO DAS NECESSIDADES (AMPULHETA DE VENDAS) | F20: ALTO | G20: 1 | K20: A INICIAR
C21: =C20+1 -> 16 | D21: VENDAS | E21: ROTINA DE COLETA E DIVULGAÇÃO DE PROVAS SOCIAIS | F21: ALTO | G21: 0 | K21: A INICIAR
C22: =C21+1 -> 17 | D22: VENDAS | E22: ROTINA DE FOLLOWUP DE PROPOSTAS EM ABERTO PARA CLIENTES | F22: ALTO | G22: 0 | K22: A INICIAR
C23: =C22+1 -> 18 | D23: PESSOAS | E23: ROTINAS DE RECRUTAMENTO E SELEÇÃO DE NOVOS COLABORADORES | F23: ALTO | G23: 3 | K23: A INICIAR
C24: =C23+1 -> 19 | D24: PESSOAS | E24: TREINAMENTO INTRODUTÓRIO NA CULTURA E REG. INTERNO PARA NOVOS FUNCIONÁRIOS | F24: ALTO | G24: 2 | K24: A INICIAR
... C51: =C50+1 -> 46 | D51: DESIGN | E51: ROTINA DE PRODUÇÃO E EDIÇÃO DE CONTEÚDOS (POSTS ESTÁTICOS/ARTES) | F51: ALTO | G51: 3 | K51: A INICIAR

Sheet 0.4
B2: < CLIQUE AQUI E VOLTE AO PAINEL INICIAL | C2: CONTROLE DE METAS (ANÁLISE MENSAL)
B4: Indicador | C4: FATURAMENTO
B5: Responsável | C5: BRUNO
B6: Última atualização | C6: 45951
B7: Sentido do indicador
D8: 1 | E8: =IF(COUNT(E11)<>0,D8+1,D8) -> 2 | F8: =IF(COUNT(F11)<>0,E8+1,E8) -> 3 | G8: =IF(COUNT(G11)<>0,F8+1,F8) -> 4 | H8: =IF(COUNT(H11)<>0,G8+1,G8) -> 4 | I8: =IF(COUNT(I11)<>0,H8+1,H8) -> 4 | J8: =IF(COUNT(J11)<>0,I8+1,I8) -> 4 | K8: =IF(COUNT(K11)<>0,J8+1,J8) -> 4 | L8: =IF(COUNT(L11)<>0,K8+1,K8) -> 4 | ... O8: =IF(COUNT(O11)<>0,N8+1,N8) -> 4 | AG8: =MAX($D8:$O8) -> 4
B9: 2025 | C9: Histórico Anual | D9: 45962 | E9: =DATE(YEAR(D9),MONTH(D9)+1,DAY(D9)) -> 45992 | F9: =DATE(YEAR(E9),MONTH(E9)+1,DAY(E9)) -> 46023 | G9: =DATE(YEAR(F9),MONTH(F9)+1,DAY(F9)) -> 46054 | H9: =DATE(YEAR(G9),MONTH(G9)+1,DAY(G9)) -> 46082 | I9: =DATE(YEAR(H9),MONTH(H9)+1,DAY(H9)) -> 46113 | J9: =DATE(YEAR(I9),MONTH(I9)+1,DAY(I9)) -> 46143 | K9: =DATE(YEAR(J9),MONTH(J9)+1,DAY(J9)) -> 46174 | L9: =DATE(YEAR(K9),MONTH(K9)+1,DAY(K9)) -> 46204 | ... O9: =DATE(YEAR(N9),MONTH(N9)+1,DAY(N9)) -> 46296 | P9: TOTAL | AF9: Mês | AG9: =HLOOKUP(AG$8,$D$8:$P$14,2,0) -> 46054 | AH9: Extra | AI9: Acumulado
B10: Meta | C10: =AVERAGE(D10:O10) -> 22333.333 | D10: 15000 | E10: 18000 | F10: =E10+1000 -> 19000 | G10: =F10+1000 -> 20000 | H10: =G10+1000 -> 21000 | I10: =H10+1000 -> 22000 | J10: =I10+1000 -> 23000 | K10: =J10+1000 -> 24000 | L10: =K10+1000 -> 25000 | M10: =L10+1000 -> 26000 | ... O10: =N10+1000 -> 28000 | P10: =SUM(D10:O10) -> 268000 | AF10: ="Meta "&PROPER(TEXT(AG9,"mmm")) -> Meta Fev | AG10: =HLOOKUP(AG$8,$D$8:$P$14,3,0) -> 20000 | AH10: Meta acum. | AI10: =P10 -> 268000
B11: Realizado | C11: =AVERAGE(D11:O11) -> 18249.75 | D11: 16000 | E11: 17000 | F11: 20000 | G11: 19999 | P11: =SUM(D11:O11) -> 72999 | AF11: ="Real "&PROPER(TEXT(AG9,"mmm")) -> Real Fev | AG11: =HLOOKUP(AG$8,$D$8:$P$14,4,0) -> 19999 | AH11: Real acum. | AI11: =P11 -> 72999
B12: Abaixo da meta | C12: - | D12: =IF(D11<D10,D11,"") | E12: =IF(E11<E10,E11,"") -> 17000 | F12: =IF(F11<F10,F11,"") | G12: =IF(G11<G10,G11,"") -> 19999 | H12: =IF(H11<H10,H11,"") -> 0 | I12: =IF(I11<I10,I11,"") -> 0 | J12: =IF(J11<J10,J11,"") -> 0 | K12: =IF(K11<K10,K11,"") -> 0 | ... O12: =IF(O11<O10,O11,"") -> 0 | AF12: Abaixo da meta | AI12: =P12 -> 0
B13: Acima da meta | AF13: Acima da meta | AI13: =P13 -> 0
B14: Desvio mensal | C14: =C11-C10 -> -4083.5833 | D14: =D11-D10 -> 1000 | E14: =E11-E10 -> -1000 | F14: =F11-F10 -> 1000 | G14: =G11-G10 -> -1 | H14: =H11-H10 -> -21000 | I14: =I11-I10 -> -22000 | J14: =J11-J10 -> -23000 | ... P14: =P11-P10 -> -195001 | AF14: Diferença | AG14: =HLOOKUP(AG$8,$D$8:$P$14,7,0) -> -1 | AI14: =P14 -> -195001
AF16: Vermelho | AG16: =IF(AG14<0,1,0) -> 1
B18: Indicador | C18: LUCRO
B19: Responsável | C19: BRUNO
B20: Última atualização | C20: 45951
B21: Sentido do indicador
D22: 1 | E22: =IF(COUNT(E25)<>0,D22+1,D22) -> 1 | F22: =IF(COUNT(F25)<>0,E22+1,E22) -> 1 | G22: =IF(COUNT(G25)<>0,F22+1,F22) -> 1 | H22: =IF(COUNT(H25)<>0,G22+1,G22) -> 1 | I22: =IF(COUNT(I25)<>0,H22+1,H22) -> 1 | J22: =IF(COUNT(J25)<>0,I22+1,I22) -> 1 | K22: =IF(COUNT(K25)<>0,J22+1,J22) -> 1 | L22: =IF(COUNT(L25)<>0,K22+1,K22) -> 1 | ... O22: =IF(COUNT(O25)<>0,N22+1,N22) -> 1 | AG22: =MAX($D22:$O22) -> 1
B23: 2025 | C23: Histórico Anual | D23: =D9 -> 45962 | E23: =DATE(YEAR(D23),MONTH(D23)+1,DAY(D23)) -> 45992 | F23: =DATE(YEAR(E23),MONTH(E23)+1,DAY(E23)) -> 46023 | G23: =DATE(YEAR(F23),MONTH(F23)+1,DAY(F23)) -> 46054 | H23: =DATE(YEAR(G23),MONTH(G23)+1,DAY(G23)) -> 46082 | I23: =DATE(YEAR(H23),MONTH(H23)+1,DAY(H23)) -> 46113 | J23: =DATE(YEAR(I23),MONTH(I23)+1,DAY(I23)) -> 46143 | K23: =DATE(YEAR(J23),MONTH(J23)+1,DAY(J23)) -> 46174 | L23: =DATE(YEAR(K23),MONTH(K23)+1,DAY(K23)) -> 46204 | ... O23: =DATE(YEAR(N23),MONTH(N23)+1,DAY(N23)) -> 46296 | P23: TOTAL | AF23: Mês | AG23: =HLOOKUP(AG$22,$D$22:$P$28,2,0) -> 45962 | AH23: Extra | AI23: Acumulado
B24: Meta | C24: =AVERAGE(D24:O24) -> 17866.667 | D24: =80%*D10 -> 12000 | E24: =80%*E10 -> 14400 | F24: =80%*F10 -> 15200 | G24: =80%*G10 -> 16000 | H24: =80%*H10 -> 16800 | I24: =80%*I10 -> 17600 | J24: =80%*J10 -> 18400 | K24: =80%*K10 -> 19200 | ... O24: =80%*O10 -> 22400 | P24: =SUM(D24:O24) -> 214400 | AF24: ="Meta "&PROPER(TEXT(AG23,"mmm")) -> Meta Nov | AG24: =HLOOKUP(AG$22,$D$22:$P$28,3,0) -> 12000 | AH24: Meta acum. | AI24: =P24 -> 214400
B25: Realizado | C25: =AVERAGE(D25:O25) -> #DIV/0! | P25: =SUM(D25:O25) -> 0 | AF25: ="Real "&PROPER(TEXT(AG23,"mmm")) -> Real Nov | AG25: =HLOOKUP(AG$22,$D$22:$P$28,4,0) -> 0 | AH25: Real acum. | AI25: =P25 -> 0
B26: Abaixo da meta | C26: - | D26: =IF(D25<D24,D25,"") -> 0 | E26: =IF(E25<E24,E25,"") -> 0 | F26: =IF(F25<F24,F25,"") -> 0 | G26: =IF(G25<G24,G25,"") -> 0 | H26: =IF(H25<H24,H25,"") -> 0 | I26: =IF(I25<I24,I25,"") -> 0 | J26: =IF(J25<J24,J25,"") -> 0 | K26: =IF(K25<K24,K25,"") -> 0 | ... O26: =IF(O25<O24,O25,"") -> 0 | AF26: Abaixo da meta | AI26: =P26 -> 0
B27: Acima da meta | AF27: Acima da meta | AI27: =P27 -> 0
B28: Desvio mensal | C28: =C25-C24 -> #DIV/0! | D28: =D25-D24 -> -12000 | E28: =E25-E24 -> -14400 | F28: =F25-F24 -> -15200 | G28: =G25-G24 -> -16000 | H28: =H25-H24 -> -16800 | I28: =I25-I24 -> -17600 | J28: =J25-J24 -> -18400 | ... P28: =P25-P24 -> -214400 | AF28: Diferença | AG28: =HLOOKUP(AG$22,$D$22:$P$28,7,0) -> -12000 | AI28: =P28 -> -214400
AF30: Vermelho | AG30: =IF(AG28<0,1,0) -> 1
B32: Indicador | C32: DESPESAS
B33: Responsável | C33: BRUNO
B34: Última atualização | C34: 45951
B35: Sentido do indicador
D36: 1 | E36: =IF(COUNT(E39)<>0,D36+1,D36) -> 1 | F36: =IF(COUNT(F39)<>0,E36+1,E36) -> 1 | G36: =IF(COUNT(G39)<>0,F36+1,F36) -> 1 | H36: =IF(COUNT(H39)<>0,G36+1,G36) -> 1 | I36: =IF(COUNT(I39)<>0,H36+1,H36) -> 1 | J36: =IF(COUNT(J39)<>0,I36+1,I36) -> 1 | K36: =IF(COUNT(K39)<>0,J36+1,J36) -> 1 | L36: =IF(COUNT(L39)<>0,K36+1,K36) -> 1 | ... O36: =IF(COUNT(O39)<>0,N36+1,N36) -> 1 | AG36: =MAX($D36:$O36) -> 1
B37: 2025 | C37: Histórico Anual | D37: =D9 -> 45962 | E37: =DATE(YEAR(D37),MONTH(D37)+1,DAY(D37)) -> 45992 | F37: =DATE(YEAR(E37),MONTH(E37)+1,DAY(E37)) -> 46023 | G37: =DATE(YEAR(F37),MONTH(F37)+1,DAY(F37)) -> 46054 | H37: =DATE(YEAR(G37),MONTH(G37)+1,DAY(G37)) -> 46082 | I37: =DATE(YEAR(H37),MONTH(H37)+1,DAY(H37)) -> 46113 | J37: =DATE(YEAR(I37),MONTH(I37)+1,DAY(I37)) -> 46143 | K37: =DATE(YEAR(J37),MONTH(J37)+1,DAY(J37)) -> 46174 | L37: =DATE(YEAR(K37),MONTH(K37)+1,DAY(K37)) -> 46204 | ... O37: =DATE(YEAR(N37),MONTH(N37)+1,DAY(N37)) -> 46296 | P37: TOTAL | AF37: Mês | AG37: =HLOOKUP(AG$36,$D$36:$P$42,2,0) -> 45962 | AH37: Extra | AI37: Acumulado
B38: Meta | C38: =AVERAGE(D38:O38) -> 19250 | D38: 16000 | E38: 16000 | F38: 16000 | G38: 19000 | H38: 19000 | I38: 19000 | J38: 19000 | K38: 19000 | L38: 22000 | M38: 22000 | N38: 22000 | O38: 22000 | P38: =SUM(D38:O38) -> 231000 | AF38: ="Meta "&PROPER(TEXT(AG37,"mmm")) -> Meta Nov | AG38: =HLOOKUP(AG$36,$D$36:$P$42,3,0) -> 16000 | AH38: Meta acum. | AI38: =P38 -> 231000
B39: Realizado | C39: =AVERAGE(D39:O39) -> #DIV/0! | P39: =SUM(D39:O39) -> 0 | AF39: ="Real "&PROPER(TEXT(AG37,"mmm")) -> Real Nov | AG39: =HLOOKUP(AG$36,$D$36:$P$42,4,0) -> 0 | AH39: Real acum. | AI39: =P39 -> 0
B40: Abaixo da meta | C40: - | D40: =IF(D39>D38,D39,"") | E40: =IF(E39>E38,E39,"") | F40: =IF(F39>F38,F39,"") | G40: =IF(G39>G38,G39,"") | H40: =IF(H39>H38,H39,"") | I40: =IF(I39>I38,I39,"") | J40: =IF(J39>J38,J39,"") | K40: =IF(K39>K38,K39,"") | ... O40: =IF(O39>O38,O39,"") | AF40: Abaixo da meta | AI40: =P40 -> 0
B41: Acima da meta | AF41: Acima da meta | AI41: =P41 -> 0
B42: Desvio mensal | C42: =C39-C38 -> #DIV/0! | D42: =D39-D38 -> -16000 | E42: =E39-E38 -> -16000 | F42: =F39-F38 -> -16000 | G42: =G39-G38 -> -19000 | H42: =H39-H38 -> -19000 | I42: =I39-I38 -> -19000 | J42: =J39-J38 -> -19000 | ... P42: =P39-P38 -> -231000 | AF42: Diferença | AG42: =HLOOKUP(AG$36,$D$36:$P$42,7,0) -> -16000 | AI42: =P42 -> -231000
AF44: Verde | AG44: =IF(AG42<=0,1,0) -> 1
AF45: Vermelho | AG45: =IF(AG42>0,1,0) -> 0

Sheet 0.5
D2: < CLIQUE AQUI E VOLTE AO PAINEL INICIAL | E2: FOTOGRAFIA DA EMPRESA (CNPJ X CPF)
C4: # | D4: PERGUNTAS | E4: COMO CALCULAR | F4: MÉDIA HISTÓRICA (ÚLTIMOS 12 MESES) | G4: 47757 | H4: =DATE(YEAR(G4),MONTH(G4)+1,DAY(G4)) -> 47788 | I4: =DATE(YEAR(H4),MONTH(H4)+1,DAY(H4)) -> 47818 | J4: =DATE(YEAR(I4),MONTH(I4)+1,DAY(I4)) -> 47849 | K4: =DATE(YEAR(J4),MONTH(J4)+1,DAY(J4)) -> 47880 | L4: =DATE(YEAR(K4),MONTH(K4)+1,DAY(K4)) -> 47908 | M4: =DATE(YEAR(L4),MONTH(L4)+1,DAY(L4)) -> 47939 | N4: =DATE(YEAR(M4),MONTH(M4)+1,DAY(M4)) -> 47969 | O4: =DATE(YEAR(N4),MONTH(N4)+1,DAY(N4)) -> 48000 | ... R4: =DATE(YEAR(Q4),MONTH(Q4)+1,DAY(Q4)) -> 48092
C5: 1 | D5: Qual o seu faturamento médio mensal? | E5: Total de vendas em média nos últimos meses | F5: 15000 | G5: 1000000 | H5: 1000000 | I5: 1000000 | J5: 1000000 | K5: 1000000 | L5: 1000000 | M5: 1000000 | N5: 1000000 | O5: 1000000 | P5: 1000000 | Q5: 1000000 | R5: 1000000
C6: 2 | D6: Qual seu gasto médio mensal? | E6: Total de obrigações que você possui com sua empresa (alugel, salários, etc) | F6: NÃO SABE EXATAMENTE
C7: 3 | D7: Qual seu lucro médio mensal? | E7: Total de dinheiro limpo que tem sobrado ao final de cada mês no seu caixa | F7: NÃO SABE EXATAMENTE
C8: 4 | D8: Qual seu fundo de reserva hoje? | E8: Total de dinheiro separado para eventuais emergências da empresa | F8: 37000
C9: 5 | D9: Qual seu pró-labore hoje? | E9: Total (em R$) que você retira da empresa para se pagar (seu salário como dono(a)) | F9: 11000
C10: 6 | D10: Qual o número de funcionários você possui? | E10: Total de pessoas que trabalham com você em sua empresa (contando com você) | F10: 5
C11: 7 | D11: Quantas horas em média você trabalha por dia? | E11: Total de horas que você dedica a sua empresa ao longo de 1 dia de trabalho | F11: 12
C12: 8 | D12: Quantos dias 100% offline você tira ao mês? | E12: Total de dias que você consegue tirar no mês para descansar e se dedicar à família | F12: 4
C13: 9 | D13: De 0 a 10 que nota você dá para a EQUIPE que toca as rotinas da sua empresa? | E13: Avalie criticamente como sua empresa está organizada hoje | F13: 7
C14: 10 | D14: De 0 a 10 que nota você dá para VOCÊ como gestor(a) da sua empresa? | E14: Avalie criticamente como você está preparado(a) hoje | F14: 5

Sheet 1.1
B2: < CLIQUE AQUI E VOLTE AO PAINEL INICIAL | D2: MISSÃO, VISÃO E VALORES
B4: MISSÃO | D4: VISÃO | F4: VALORES | H4: O QUE SIGNIFICA ESSE VALOR?
B6: TRANSFORMAR MARCAS EM EXPERIÊNCIAS VIVAS POR MEIO DA INTEGRAÇÃO ESTRATÉGICA DE PESSOAS, IDEIAS E FERRAMENTAS DIGITAIS, CRIANDO SOLUÇÕES DE MARKETING QUE FUNCIONAM EM HARMONIA COM OS OBJETIVOS DOS CLIENTES | D6: VISÃO DE FUTURO DA EMPRESA EM RELAÇÃO AOS PRÓXIMOS ANOS (3 A 5). EX: SER UMA REFERÊNCIA EM XYZ... | H6: POR QUE ESSE VALOR É IMPORTANTE PARA A EMPRESA?
H8: POR QUE ESSE VALOR É IMPORTANTE PARA A EMPRESA?
H10: POR QUE ESSE VALOR É IMPORTANTE PARA A EMPRESA?
H12: POR QUE ESSE VALOR É IMPORTANTE PARA A EMPRESA?
H14: POR QUE ESSE VALOR É IMPORTANTE PARA A EMPRESA?
H16: POR QUE ESSE VALOR É IMPORTANTE PARA A EMPRESA?

Sheet 1.2
B2: # | C2: << VOLTAR AO PAINEL DE CONTROLE | D2: MAPA DE CARGOS E FUNÇÕES
B4: # | C4: SÓCIA NATASHA | E4: # | F4: SÓCIO BRUNO | H4: # | I4: SOCIAL MEDIA (NOME DA PESSOA) | L4: # | M4: GESTOR DE TRAFEGO (NOME DA PESSOA) | P4: # | Q4: SOCIAL SELLER (NOME DA PESSOA)
B6: 1 | C6: LISTE AS FUNÇÕES DO CARGO | E6: 1 | F6: LISTE AS FUNÇÕES DO CARGO | H6: 1 | I6: LISTE AS FUNÇÕES DO CARGO | L6: 1 | M6: LISTE AS FUNÇÕES DO CARGO | P6: 1 | Q6: LISTE AS FUNÇÕES DO CARGO
B7: 2 | C7: LISTE AS FUNÇÕES DO CARGO | E7: 2 | F7: LISTE AS FUNÇÕES DO CARGO | H7: 2 | I7: LISTE AS FUNÇÕES DO CARGO | L7: 2 | M7: LISTE AS FUNÇÕES DO CARGO | P7: 2 | Q7: LISTE AS FUNÇÕES DO CARGO
B8: 3 | C8: LISTE AS FUNÇÕES DO CARGO | E8: 3 | F8: LISTE AS FUNÇÕES DO CARGO | H8: 3 | I8: LISTE AS FUNÇÕES DO CARGO | L8: 3 | M8: LISTE AS FUNÇÕES DO CARGO | P8: 3 | Q8: LISTE AS FUNÇÕES DO CARGO
B9: 4 | C9: LISTE AS FUNÇÕES DO CARGO | E9: 4 | F9: LISTE AS FUNÇÕES DO CARGO | H9: 4 | I9: LISTE AS FUNÇÕES DO CARGO | L9: 4 | M9: LISTE AS FUNÇÕES DO CARGO | P9: 4 | Q9: LISTE AS FUNÇÕES DO CARGO
B10: 5 | C10: LISTE AS FUNÇÕES DO CARGO | E10: 5 | F10: LISTE AS FUNÇÕES DO CARGO | H10: 5 | I10: LISTE AS FUNÇÕES DO CARGO | L10: 5 | M10: LISTE AS FUNÇÕES DO CARGO | P10: 5 | Q10: LISTE AS FUNÇÕES DO CARGO
B11: 6 | C11: LISTE AS FUNÇÕES DO CARGO | E11: 6 | F11: LISTE AS FUNÇÕES DO CARGO | H11: 6 | I11: LISTE AS FUNÇÕES DO CARGO | L11: 6 | M11: LISTE AS FUNÇÕES DO CARGO | P11: 6 | Q11: LISTE AS FUNÇÕES DO CARGO
B12: 7 | C12: LISTE AS FUNÇÕES DO CARGO | E12: 7 | F12: LISTE AS FUNÇÕES DO CARGO | H12: 7 | I12: LISTE AS FUNÇÕES DO CARGO | L12: 7 | M12: LISTE AS FUNÇÕES DO CARGO | P12: 7 | Q12: LISTE AS FUNÇÕES DO CARGO
B13: 8 | C13: LISTE AS FUNÇÕES DO CARGO | E13: 8 | F13: LISTE AS FUNÇÕES DO CARGO | H13: 8 | I13: LISTE AS FUNÇÕES DO CARGO | L13: 8 | M13: LISTE AS FUNÇÕES DO CARGO | P13: 8 | Q13: LISTE AS FUNÇÕES DO CARGO
B14: 9 | C14: LISTE AS FUNÇÕES DO CARGO | E14: 9 | F14: LISTE AS FUNÇÕES DO CARGO | H14: 9 | I14: LISTE AS FUNÇÕES DO CARGO | L14: 9 | M14: LISTE AS FUNÇÕES DO CARGO | P14: 9 | Q14: LISTE AS FUNÇÕES DO CARGO
B15: 10 | C15: LISTE AS FUNÇÕES DO CARGO | E15: 10 | F15: LISTE AS FUNÇÕES DO CARGO | H15: 10 | I15: LISTE AS FUNÇÕES DO CARGO | L15: 10 | M15: LISTE AS FUNÇÕES DO CARGO | P15: 10 | Q15: LISTE AS FUNÇÕES DO CARGO

Sheet 1.3
C2: < CLIQUE AQUI E VOLTE AO PAINEL INICIAL | D2: REGULAMENTO INTERNO
B4: # | C4: BLOCO | E4: PERGUNTAS PARA ANÁLISE | G4: ASSINALE O QUE VOCÊ IRÁ INSERIR NO SEU R.I.
B6: 1 | C6: INTRODUTÓRIO | E6: O regulamento interno da empresa é um documento em que está descrito um conjunto de direitos e deveres que tanto o empregador quanto os empregados devem seguir. | G6: X
B7: 2 | C7: INTRODUTÓRIO | E7: Neste bloco você deve inserir uma frase objetiva para cada um desses 3 pilares da sua empresa | G7: X
B8: 3 | C8: INTRODUTÓRIO | E8: Aqui você vai inserir o modelo de contratação: CLT, PJ, Freelancer, Temporário, Terceirizado, Home Office, Jovem Aprendiz, Estágio, etc | G8: X
B9: 4 | C9: UNIFORMES E EPI'S | E9: É indispensável o uso de uniforme completo por parte dos funcionários no interior da empresa e no caso de extravio ou de qualquer dano (por culpa do funcionário) o uniforme deverá ser ressarcido ao seu empregador. | G9: X
B10: 5 | C10: UNIFORMES E EPI'S | E10: Funções que exigem o uso de EPIs (Equipamentos de Proteção Individual), jamais podem ser exercidas sem que os funcionários estejam utilizando os itens obrigatórios. | G10: X
B11: 6 | C11: HORÁRIOS DE TRABALHO | E11: Os funcionários deverão se apresentar para o trabalho com cinco minutos de antecedência;
B12: 7 | C12: HORÁRIOS DE TRABALHO | E12: Os horários estabelecidos pelo Departamento de Pessoal (inclusive para café, almoço e lanche) deverão ser estritamente cumpridos, sob pena de descontos dos salários na razão do tempo de trabalho perdido;
B13: 8 | C13: HORÁRIOS DE TRABALHO | E13: O registro nos controles de frequência serão feitos por meio de ... (Ex: cartão de ponto) e os funcionários são obrigados a marcar cautelosamente as entradas e saídas, a fim de evitar registros errados.
B14: 9 | C14: HORÁRIOS DE TRABALHO | E14: O controle de frequência será verificado para monitorar as presenças, faltas e atrasos (neste caso serão procedidos descontos no salário);
B15: 10 | C15: HORÁRIOS DE TRABALHO | E15: As reincidências de ausências, ou atrasos ao serviço, sem causa justificada, constituem motivo passível de rescisão do Contrato de Trabalho por justa causa;
B16: 11 | C16: HORÁRIOS DE TRABALHO | E16: É necessária a apresentação de atestado médico para abono de faltas e atrasos nas rotinas de trabalho;
B17: 12 | C17: HORÁRIOS DE TRABALHO | E17: As saídas antecipadas somente serão permitidas, com a devida autorização do responsável pelo Departamento e, após a marcação do cartão de ponto;
B18: 13 | C18: HORÁRIOS DE TRABALHO | E18: Inserir como funciona as escalas e quando o colaborador poderá gozar do seu dia de folga
B19: 14 | C19: HORÁRIOS DE TRABALHO | E19: As férias devem ser solicitadas e aprovadas previamente pela liderança imediata do funcionário (com antecedência de X meses);
B20: 15 | C20: ROTINAS INTERNAS | E20: O funcionário não pode permanecer sem o uniforme durante as atividades na empresa ou em serviços fora da empresa;
B21: 16 | C21: ROTINAS INTERNAS | E21: O funcionário não pode recusar-se a assinar o cartão de ponto ou o controle de horas trabalhadas;
B22: 17 | C22: ROTINAS INTERNAS | E22: O funcionário não pode ausentar-se dos departamentos ou seções onde trabalha, sem prévia autorização dos seus chefes;
... B43: 38 | C43: PROMOÇÕES NA CARREIRA | E43: É um diferencial saber trabalhar sob pressão, seja para cumprir os prazos de entrega, atender clientes difíceis, lidar com conflitos no dia a dia e agir de forma madura e profissional.

Sheet 1.5
B2: # | C2: < CLIQUE AQUI E VOLTE AO PAINEL INICIAL | D2: REUNIÃO NOTA 10 (DIÁRIA OU SEMANAL)
B4: # | C4: NOME DA PESSOA | E4: # | F4: NOME DA PESSOA | H4: # | I4: NOME DA PESSOA | L4: # | M4: NOME DA PESSOA | P4: # | Q4: NOME DA PESSOA
C6: AÇÃO PARA SER EXECUTADA ESCRITA COM VERBO NO INFINITIVO E QUE SEJA DE RESPONSABILIDADE DA PESSOA OU DO TIME DA PESSOA, POIS ELA SERÁ COBRADA NO DIA SEGUINTE | F6: AÇÃO PARA SER EXECUTADA ESCRITA COM VERBO NO INFINITIVO E QUE SEJA DE RESPONSABILIDADE DA PESSOA OU DO TIME DA PESSOA, POIS ELA SERÁ COBRADA NO DIA SEGUINTE | I6: AÇÃO PARA SER EXECUTADA ESCRITA COM VERBO NO INFINITIVO E QUE SEJA DE RESPONSABILIDADE DA PESSOA OU DO TIME DA PESSOA, POIS ELA SERÁ COBRADA NO DIA SEGUINTE | M6: AÇÃO PARA SER EXECUTADA ESCRITA COM VERBO NO INFINITIVO E QUE SEJA DE RESPONSABILIDADE DA PESSOA OU DO TIME DA PESSOA, POIS ELA SERÁ COBRADA NO DIA SEGUINTE | Q6: AÇÃO PARA SER EXECUTADA ESCRITA COM VERBO NO INFINITIVO E QUE SEJA DE RESPONSABILIDADE DA PESSOA OU DO TIME DA PESSOA, POIS ELA SERÁ COBRADA NO DIA SEGUINTE
B7: 1 | E7: 1 | H7: 1 | L7: 1 | P7: 1
B8: 2 | E8: 2 | H8: 2 | L8: 2 | P8: 2
B9: 3 | E9: 3 | H9: 3 | L9: 3 | P9: 3

Sheet 1.6
C2: < CLIQUE AQUI E VOLTE AO PAINEL INICIAL | D2: ANÁLISE DE RESULTADOS MENSAIS
D4: INDICADOR ANALISADO | F4: META | G4: REALIZADO | H4: DESVIO | I4: FAROL
D6: VENDAS NO AÇOUGUE | F6: 100000 | G6: 90000 | H6: =F6-G6 -> 10000 | I6: n
D8: Causa Primária | E8: Causa 2 | F8: Causa 3 | G8: Causa 4 | H8: Causa 5 | I8: Causa Raiz
D9: TICKET MEDIO NÃO BATEU A META | E9: ERA PRA ALCANÇAR 50 E FICAMOS EM 45 | F9: AÇOUGUEIRO NÃO ATENDEU CORRETAMENTO OS CLIENTES | G9: NÃO HÁ UM SCRIPT DE ATENDIMENTO E NEM TREINAMENTO DOS AÇOUGUEIROS
D11: Ação Corretiva | H11: Quem | I11: Prazo
D12: CRIAR SCRIPT E TREINAR OS AÇOUGUEIROS PARA AUMENTAR AS OFERTAS OFERECENDO ITENS CORRELACIONADOS PARA INCREMENTAR O TICKET MÉDIO | H12: DANIEL REICHE | I12: 45688

Sheet 1.7
C2: < CLIQUE AQUI E VOLTE AO PAINEL INICIAL | D2: CRIAÇÃO DE CULTURA FORTE | M2: NOTA DA AVALIAÇÃO > | P2: =AVERAGE(H6,H7,H8,H9,H10,P6,P7,P8,P9,P10) -> 6.5
D4: # | F4: TÓPICO ANALISADO | H4: NOTA ATUAL | K4: # | M4: TÓPICO ANALISADO | P4: NOTA ATUAL
D6: 1 | F6: DEFINIR E COMUNICAR A MISSÃO, VISÃO E VALORES NO DIA A DIA (QUADROS, PAREDES, PROTEÇÃO DE TELA, ETC) | H6: 5 | K6: 6 | M6: DEFINIÇÃO DE METAS, PROPÓSITOS CLAROS E AÇÕES CONCRETAS (FOCO EM RESULTADO) | P6: 4
D7: 2 | F7: PROMOVER TREINAMENTOS ESPECÍFICOS PARA MEMBROS DA EQUIPE (ESTÍMULO PARA CARGOS E HABILIDADES ESPECÍFICAS) | H7: 6 | K7: 7 | M7: REUNIÃO DE ALINHAMENTO DIÁRIO, SEMANAL E MENSAL (ALINHAMENTO DE EXPECTATIVAS E PRIORIDADES SEMPRE) | P7: 6
D8: 3 | F8: PROMOVER EVENTOS ABERTOS AO TIME (ANIVERSÁRIO DA EMPRESA, SEMANA DA QUALIDADE, DIA DE REFORÇO DOS PILARES DA CULTURA) | H8: 7 | K8: 8 | M8: COMEMORAÇÃO POR METAS BATIDAS COM A EQUIPE (PASSEIOS, RESTAURANTES, FESTAS, ETC) | P8: 5
D9: 4 | F9: REALIZAR PESQUISA DE CLIMA ORGANIZACIONAL (ESTRATÉGIA OBRIGATÓRIA PARA FORTALECER A CULTURA) | H9: 8 | K9: 9 | M9: COMEMORAÇÃO EM DATAS ESPECIAIS (DIA DO TRABALHO, DIA DA MULHER, DIA DAS MÃES, DIA DOS PAIS, DAY OFF (FOLGA) NO ANIVERSÁRIO | P9: 7
D10: 5 | F10: PROMOVER COMUNICAÇÃO INTERNA (E-MAILS, NEWSLETTER, COMUNICADOS, ALINHAMENTO COM FUNCIONÁRIOS, FORNECEDORES E CLIENTES) | H10: 9 | K10: 10 | M10: FEEDBACKS INDIVIDUAIS COM O TIME (REFORÇO ESPECÍFICO AOS PILARES COM BASE NOS COMPORTAMENTOS DE CADA PESSOA) | P10: 8

Sheet 1.8
C2: < CLIQUE AQUI E VOLTE AO PAINEL INICIAL | E2: REMUNERAÇÃO VARIÁVEL
C4: >>>>>>> Tabela para projetar o valor que será pago em bônus para todo o time após 1 ano de trabalho >>>>>>>> | E4: Cargos | F4: Bônus em Número de Salários / Ano (Referência de Mercado) | G4: Bônus em Número de Salários / Ano (Ex: Para minha empresa) | H4: # Colaboradores na minha empresa hoje | I4: R$ Salário pago na minha empresa hoje | J4: R$ Bônus previsto a ser pago
E5: Júnior | F5: 1 | G5: 1 | H5: 3 | I5: 2000 | J5: =G5*H5*I5 -> 6000
E6: Pleno | F6: 2 | G6: 1 | H6: 2 | I6: 3000 | J6: =G6*H6*I6 -> 6000
E7: Sênior | F7: 3 | G7: 1 | H7: 2 | I7: 5000 | J7: =G7*H7*I7 -> 10000
E8: Coordenador/Supervisor | F8: 4 | G8: 1 | H8: 2 | I8: 8000 | J8: =G8*H8*I8 -> 16000
E9: Head/Gerente | F9: 6 | G9: 1 | H9: 2 | I9: 10000 | J9: =G9*H9*I9 -> 20000
E10: Diretor | F10: 12 | G10: 1 | H10: 1 | I10: 20000 | J10: =G10*H10*I10 -> 20000
E11: Total | F11: - | G11: - | H11: =SUM(H5:H10) -> 12 | I11: - | J11: =SUM(J5:J10) -> 78000
E13: Quanto quero distribuir após um ano? > | J13: =J11 -> 78000 | K13: < Célula preenchida automaticamente
E15: Qual meu lucro anual estimado após um ano? > | J15: 1000000 | K15: < Digite aqui o valor que você espera lucrar em 12 meses
E17: Qual % que será distribuído se as estimativas acima estiverem certas? > | J17: =J13/J15 -> 0.078 | K17: < Célula preenchida automaticamente

Sheet 2.1
B2: < CLIQUE AQUI E VOLTE AO PAINEL INICIAL | D2: RAIO-X DO CLIENTE DOS SONHOS
B4: DORES | D4: DESEJOS | F4: CRENÇAS | H4: OBJEÇÕES
B6: DIGITE AQUI UMA DOR ESPECÍFICA QUE SEU CLIENTE DOS SONHOS POSSUI DIARIAMENTE E VOCÊ PODE SOLUCIONAR | D6: DIGITE AQUI UM DESEJO ESPECÍFICO QUE SEU CLIENTE DOS SONHOS POSSUI DIARIAMENTE E VOCÊ PODE REALIZAR | F6: DIGITE AQUI UMA CRENÇA LIMITANTE SOBRE SEU PRODUTO OU SERVIÇO QUE SEU CLIENTE POSSUI E VOCÊ PRECISA COMBATER DIARIAMENTE | H6: DIGITE AQUI UMA OBJEÇÃO QUE SEU CLIENTE DOS SONHOS POSSUI DIARIAMENTE E VOCÊ PODE SOLUCIONAR
B7: "NÃO CONSIGO FAZER MINHA EMPRESA FUNCIONAR SEM DEPENDER DE MIM" | D7: "QUERO PODER TIRAR FÉRIAS DA MINHA EMPRESA, MAS ESTOU PRESO(A) NA OPERAÇÃO" | F7: "NÃO ACHO QUE UMA MENTORIA VAI AJUDAR MINHA EMPRESA A MUDAR" | H7: "NÃO TENHO DINHEIRO AGORA, MAS QUANDO TIVER, EU ENTRO PARA SUA MENTORIA"
B8: "NÃO CONFIO NO MEU TIME E TENHO QUE CONFERIR TUDO QUE PEÇO PARA OS FUNCIONÁRIOS" | D8: "QUERO CUIDAR MELHOR DA MINHA FAMÍLIA, MAS MINHA EMPRESA NÃO PERMITE" | F8: "ESTUDAR ONLINE NÃO É PRA MIM E NÃO VAI ME AJUDAR EM MEU NEGÓCIO" | H8: "NÃO TENHO TEMPO PARA ME DEDICAR E ESTUDAR COMO DEVERIA PARA SUA MENTORIA"
B9: "NÃO ACHO GENTE BOA PARA TRABALHAR E CADA DIA ESTÁ MAIS DIFÍCIL CONTRATAR FUNCIONÁRIOS" | D9: "QUERO CUIDAR DA MINHA SAÚDE, MAS NÃO SOBRA TEMPO DE IR PRA ACADEMIA" | F9: "ESTOU VELHO PARA COMEÇAR A ME CAPACITAR NOVAMENTE" | H9: "NÃO ESTOU NO MOMENTO CERTO PRA ENTRAR, PORQUE PRECISO ME ORGANIZAR PRIMEIRO"
B10: "NÃO TENHO UMA EQUIPE ENGAJADA, PROATIVA E COM ATITUDE DE DONO NO DIA A DIA DA EMPRESA" | D10: "QUERO TER UM EMPRESA QUE FUNCIONE COMIGO POR PERTO OU MESMO SEM A MINHA PRESENÇA" | F10: "NO MEU CASO ESPECÍFICO, PRO MEU NICHO, EU ACHO QUE ISSO NÃO FUNCIONA" | H10: "NÃO TENHO LIMITE NO CARTÃO PARA FAZER O PAGAMENTO AGORA"
B11: "NÃO VEJO O RETORNO FINANCEIRO QUE GOSTARIA DE VER, MESMO TRABALHANDO MUITO DURO" | D11: "QUERO PODER GARANTIR MINHA INDEPENDÊNCIA FINANCEIRA E DOS MEUS FILHOS" | F11: "ACHO QUE JÁ ATINGI MEU POTENCIAL MÁXIMO COM MINHA EMPRESA" | H11: "PRECISO FALAR COM MEU SÓCIO(A) E DEPOIS TE DOU UM RETORNO"
B13: DORES | D13: DESEJOS | F13: CRENÇAS | H13: OBJEÇÕES

Sheet 2.2
B2: < CLIQUE AQUI E VOLTE AO PAINEL INICIAL | D2: CRIAÇÃO DE CONTEÚDOS | J2: 70 HEADLINES PARA POSTS QUE ENGAJAM
B4: DORES | D4: DESEJOS | F4: CRENÇAS | H4: OBJEÇÕES
B6: DIGITE AQUI UMA DOR ESPECÍFICA QUE SEU CLIENTE DOS SONHOS POSSUI DIARIAMENTE E VOCÊ PODE SOLUCIONAR | D6: DIGITE AQUI UM DESEJO ESPECÍFICO QUE SEU CLIENTE DOS SONHOS POSSUI DIARIAMENTE E VOCÊ PODE REALIZAR | F6: DIGITE AQUI UMA CRENÇA LIMITANTE SOBRE SEU PRODUTO OU SERVIÇO QUE SEU CLIENTE POSSUI E VOCÊ PRECISA COMBATER DIARIAMENTE | H6: DIGITE AQUI UMA OBJEÇÃO QUE SEU CLIENTE DOS SONHOS POSSUI DIARIAMENTE E VOCÊ PODE SOLUCIONAR | J6: 1. Se você age assim olha o que acontece | K6: 11. Sem saber isso você não consegue (objetivo do seu avatar) | L6: 21. Se você quer (objetivo do avatar), este é o caminho | M6: 31. Não é (algo que o seu avatar acredita que é a solução) que traz resultado. É isso aqui! | N6: 41. Quem está (situação comum do seu avatar) é por que ainda não percebeu/aprendeu/descobriu isso | O6: 51. Os segredos por trás de (algo do seu nicho) | P6: 61. Por que eu não recomendo que você (atitude ineficaz comum do seu avatar)
B7: "NÃO CONSIGO FAZER MINHA EMPRESA FUNCIONAR SEM DEPENDER DE MIM" | D7: "QUERO PODER TIRAR FÉRIAS DA MINHA EMPRESA, MAS ESTOU PRESO(A) NA OPERAÇÃO" | F7: "NÃO ACHO QUE UMA MENTORIA VAI AJUDAR MINHA EMPRESA A MUDAR" | H7: "NÃO TENHO DINHEIRO AGORA, MAS QUANDO TIVER, EU ENTRO PARA SUA MENTORIA" | J7: 2. Este é pra quem tem/faz (erro comum do avatar) | K7: 12. Mais um segredo do (algo do seu nicho) que muita gente não sabe | L7: 22. Se você já (erro comum), veja esse vídeo | M7: 32. Assim que você faz (objetivo do seu avatar) sem precisar (objeção do avatar) | N7: 42. Enquanto você não (atitude que seu avatar desconsidera) você não vai (objetivo do seu avatar) | O7: 52. Você pensa que é difícil (resultado desejado) mas assim fica bem mais fácil | P7: 62. Aplique isso e seus resultados vão explodir
B8: 3 ERROS QUE IMPEDEM SUA EMPRESA DE FUNCIONAR SEM VOCÊ | D8: VOCÊ NUNCA VAI TIRAR FÉRIAS SE COMETER ESSES 4 ERROS | F8: COMO A MENTORIA MUDOU MINHA EMPRESA EM X MESES | H8: SE SUA EMPRESA ESTÁ SEM DINHEIRO VOCÊ PODE ESTAR ERRANDO NESSES PONTOS... | J8: 3. Aposto que você pensa que (pensamento comum do avatar) | K8: 13. Isso é o que meus alunos fazem para (resultado obtido no seu curso) | L8: 23. Estou (situação indesejada comum do seu avatar). O que eu faço? | M8: 33. Vou te provar que (algo que seu avatar não acredita) | N8: 43. Essa é pra você que precisa (objetivo do avatar) | O8: 53. Por que eu não acredito que (ação ineficaz comum do seu avatar para chegar ao resultado) dá certo | P8: 63. Fazer tal coisa ou fazer tal coisa, o que é melhor pra você? (dúvida comum do seu avatar)
B9: SUA EMPRESA FUNCIONARÁ SEM VOCÊ DEPOIS DESSA ÚNICA AÇÃO | D9: EMPRESÁRIOS COM FÉRIAS DE 30 DIAS AO ANO, FAZEM EXATAMENTE ISSO | F9: DEPOIS DA MENTORIA, ESSE FOI O RESULTADO QUE EU TIVE | H9: QUANDO ANTES VOCÊ SOUBER DISSO, MENOS DINHEIRO VOCÊ PERDE NA SUA EMPRESA | J9: 4. Se te dizem que (objeção comum do avatar) então veja esse vídeo | K9: 14. Entenda o que (tema do seu nicho) tem a ver com (algo que seu avatar não sabe) | L9: 24. É isso que te falta para (objetivo do seu avatar) | M9: 34. Duvido que depois desse vídeo você ainda pense que (algo que seu avatar acredita) | N9: 44. Essa é o problema de (comportamento comum do seu avatar) | O9: 54. Definitivamente desse jeito você não vai conseguir (resultado desejado) | P9: 64. Talvez seja por isso que você não consegue (resultado desejado).
B10: EMPRESÁRIOS COM LIBERDADE, NÃO COMETEM ESSES ERROS | D10: TREINE SUA EQUIPE DESSA FORMA E TENHA FÉRIAS TODOS OS ANOS | F10: EMPRESÁRIOS QUE TEM MENTORES AVANÇAM MUITO POR CAUSA DESSE DIFERENCIAL... | H10: SE SUA EMPRESA VIVE SEM DINHEIRO, VEJA ESSE VÍDEO AGORA | J10: 5. Quando (grupo do seu avatar – mulheres, autônomo, pais) descobrem isso, é um choque! | K10: 15. Você também precisa olhar para (algo do seu nicho) assim | L10: 25. Assista a esse vídeo se você quer (objetivo do seu avatar) | M10: 35. É isso que acontece quando (erro comum do avatar) | N10: 45. É possível evitar (resultado indesejado comum) assim | O10: 55. O motivo pelo qual você não consegue (resultado desejado) | P10: 65. O ponto chave para (resultado desejado)
B11: "NÃO CONFIO NO MEU TIME E TENHO QUE CONFERIR TUDO QUE PEÇO PARA OS FUNCIONÁRIOS" | D11: "QUERO CUIDAR MELHOR DA MINHA FAMÍLIA, MAS MINHA EMPRESA NÃO PERMITE" | F11: "ESTUDAR ONLINE NÃO É PRA MIM E NÃO VAI ME AJUDAR EM MEU NEGÓCIO" | H11: "NÃO TENHO TEMPO PARA ME DEDICAR E ESTUDAR COMO DEVERIA PARA SUA MENTORIA" | J11: 6. Como fazer para (objetivo do avatar) sem ter que (objeção do avatar) | K11: 16. É assim que você descobre como começar | L11: 26. Quem fez isso conseguiu (objetivo do seu avatar) | M11: 36. Entre tal coisa e tal coisa você deve começar por... (dúvida comum do seu avatar) | N11: 46. A forma mais efetiva de (resultado desejado) | O11: 56. A ideia mais incrível para quem quer (resultado indesejado) | P11: 66. Você não precisa ser (comportamento comum) para (resultado desejado)
B12: SE VOCÊ NÃO CONFIA NA SUA EQUIPE, ESSE VÍDEO É PRA VOCÊ | D12: EU FIZ ESSAS 4 COISAS PRA CONSEGUIR TOCAR MINHA EMPRESA E TER TEMPO PRA MINHA FAMÍLIA | F12: SE VOCÊ TEM EMPRESA E NÃO SABE ONDE BUSCAR AJUDA PRA CRESCER, ASSISTA ISSO | H12: SE VOCÊ SENTE QUE NÃO TEM TEMPO PRA NADA, ESCUTE ESSE VÍDEO ATÉ O FIM | J12: 7. Se você está fazendo isso está cometendo um grande erro | K12: 17. Eu fiz essas X coisas para conseguir (resultado que seu avatar quer) | L12: 27. Se você é assim, então melhor nem ver esse vídeo | M12: 37. Você quer ter ânimo para (algo que ele procrastina)? | N12: 47. O melhor jeito de (resultado desejado) sem (objeção) | O12: 57. A sacada mais eficaz para quem não sabe (resultado desejado) | P12: 67. O risco escondido em (comportamento comum)
B13: QUEM FEZ ISSO, CONSEGUIU DELEGAR E PARAR DE CONFERIR TUDO | D13: SE VOCE NÃO FIZER ISSO NA SUA EMPRESA, OLHA O QUE ACONTECE NA SUA FAMÍLIA | F13: ESSA É PRA EMPRESÁRIOS QUE COMEÇARAM NA CARA E NA CORAGEM SEM ESTUDO ALGUM | H13: A FORMA MAIS EFETIVA PARA EMPRESÁRIOS SEM TEMPO PROSPERAREM É ESSA | J13: 8. Essa é pra quem (comportamento comum do avatar) e não sabe como resolver | K13: 18. É por isso que você não precisa (objeção do seu avatar) | L13: 28. Se você não fizer (algo que avatar está procrastinando), olha o que acontece | M13: 38. Quanto mais você fizer isso, mais vai conseguir (objetivo do avatar) | N13: 48. O que eu penso quando me dizem que (frase repetida pelo seu avatar) | O13: 58. Um guia rápido para (resultado desejado) | P13: 68. Consiga (resultado desejado) sem perder (algo que seu avatar não quer perder)
B14: É ISSO QUE FALTA PRA VOCÊ PARAR DE CONFERIR O TRABALHO DOS SEUS FUNCIONÁRIOS | D14: É ISSO QUE TE FALTA PRA TER UMA EMPRESA LUCRATIVA SEM AFETAR SUA FAMILIA | F14: É POR ISSO QUE SUA EMPRESA PAROU DE CRESCER E ESTAGNOU | H14: ESSE VIDEO VAI TE SALVAR DA ARMADILHA QUE É NÃO BUSCAR MENTORES PARA SUA EMPRESA | J14: 9. Essa é pra quem (comportamento comum do avatar) e quer muito mudar | K14: 19. É assim que se faz para (resultado que seu avatar quer) | L14: 29. É por isso que (algo que seu avatar acha que é a solução) não funciona | M14: 39. Essa é pra quem está (frustrado, desesperado, tenso) com (situação comum do seu avatar) | N14: 49. Use isso na hora de (situação corriqueira do seu avatar) | O14: 59. Aprenda isso antes de querer (algo que seu avatar quer ou está fazendo) | P14: 69. Se livre de (problema) de uma vez por todas.
B15: "NÃO ACHO GENTE BOA PARA TRABALHAR E CADA DIA ESTÁ MAIS DIFÍCIL CONTRATAR FUNCIONÁRIOS" | D15: "QUERO CUIDAR DA MINHA SAÚDE, MAS NÃO SOBRA TEMPO DE IR PRA ACADEMIA" | F15: "ESTOU VELHO PARA COMEÇAR A ME CAPACITAR NOVAMENTE" | H15: "NÃO ESTOU NO MOMENTO CERTO PRA ENTRAR, PORQUE PRECISO ME ORGANIZAR PRIMEIRO" | J15: 10. Essa atitude fez muita diferença na minha vida | K15: 20. Se você quiser de verdade, você consegue fazendo isso! | L15: 30. Esse vídeo vai te salvar dessa armadilha. Ou “Esse vídeo vai te salvar da armadilha de (algo que acontece com seu avatar) | M15: 40. A única maneira de (objetivo do seu avatar) é essa | N15: 50. A verdade oculta sobre (algo do seu nicho) | O15: 60. A pior maneira de (resultado desejado) | P15: 70. O quanto antes você souber isso melhor.
B16: QUANTO ANTES VOCE SOUBER DESSES 3 PONTOS, MAIS GENTE BOA VIRÁ PRA SUA EMPRESA | D16: VOCÊ PRECISA FAZER ISSO PRA SER UM EMPRESÁRIO DE SUCESSO SEM DESTRUIR SUA SAÚDE | F16: ESSA SITUAÇÃO FEZ MUITA DIFERENÇA, MESMO SENDO EMPRESÁRIO HÁ MAIS DE X ANOS... (PROVA SOCIAL) | H16: QUEM TENTOU SE ORGANIZAR SOZINHO PRA DEPOIS BUSCAR AJUDA PRA SUA EMPRESA, SOFREU ASSIM...
B17: É POR ESSE FATOR QUE VOCÊ NÃO CONSEGUE CONTRATAR BONS FUNCIONÁRIOS | D17: SE VOCÊ É EMPRESÁRIO E NÃO TEM TEMPO DE IR PRA ACADEMIA, DEVE ESTAR ERRANDO NISSO | F17: EU NÃO SEI COMO EU CHEGUEI ATÉ AQUI SEM CONHECER O...(NOME DA SOLUÇÃO/ MENTOR) (PROVA SOCIAL) | H17: O MELHOR JEITO DE CRESCER SUA EMPRESA NÃO É TENTANDO ORGANIZAR ELA SOZINHO E SIM....
B18: ESSA É PRA QUEM ACHA QUE NÃO TEM MÃO DE OBRA QUALIFICADA NA SUA CIDADE | D18: ENTRE SUA EMPRESA E SUA SAÚDE, VOCE NÃO PRECISA ESCOLHER 1 COISA SÓ. BASTA DOMINAR ISSO! | F18: VOCE QUER TER ANIMO PRA EMPREENDER E JÁ TEM MAIS DE X ANOS? ASSISTA ESSE VIDEO! | H18: VOU TE PROVAR QUE SE VOCÊ TENTAR ORGANIZAR SUA EMPRESA SOZINHO, VOCÊ PERDERÁ TEMPO
B19: "NÃO TENHO UMA EQUIPE ENGAJADA, PROATIVA E COM ATITUDE DE DONO NO DIA A DIA DA EMPRESA" | D19: "QUERO TER UM EMPRESA QUE FUNCIONE COMIGO POR PERTO OU MESMO SEM A MINHA PRESENÇA" | F19: "NO MEU CASO ESPECÍFICO, PRO MEU NICHO, EU ACHO QUE ISSO NÃO FUNCIONA" | H19: "NÃO TENHO LIMITE NO CARTÃO PARA FAZER O PAGAMENTO AGORA"
B20: APRENDA ISSO E TENHA UMA EQUIPE SUPER ENGAJADA | D20: ESSE É O PROBLEMA PRINCIPAL DE EMPRESÁRIOS PRESOS NA OPERAÇÃO | F20: VEJA O QUE A EMPRESA DE ..... OBTEVE APÓS NOSSA METODOLOGIA SER IMPLEMENTADA | H20: SE O LIMITE DO SEU CARTÃO É BAIXO E VOCE É DONO DE EMPRESA, ESCUTE ATÉ O FINAL
B21: VOU TE PROVAR QUE UMA EQUIPE PROATIVA NÃO SE CRIA SOMENTE PAGANDO MELHOR | D21: EU FIZ ESSAS X COISAS PARA MINHA EMPRESA FUNCIONAR SEM MIM | F21: ELE É ......E CONSEGUIU CRESCER X% APÓS EXECUTAR ESSA ÚNICA AÇÃO | H21: DUVIDO QUE DEPOIS DESSE VIDEO VOCE VAI CONTINUAR ACHANDO QUE NÃO CONSEGUE SER NOSSO CLIENTE...
B22: ESSE É UM SEGREDO DAS EQUIPES DE ALTA PERFORMANCE QUE VOCÊ JAMAIS PENSOU | D22: VOCÊ NÃO PRECISA TRABALHAR 16 HORAS PARA SUA EMPRESA FUNCIONAR SE SOUBER DISSO... | F22: PRA VOCE QUE TAMBEM É ......VEJA ESSE RESULTADO SURPREENDENTE | H22: APOSTO QUE VOCE PENSA QUE NÃO CONSEGUE COMPRAR ..... MAS EU VOU TE PROVAR QUE...
B23: "NÃO VEJO O RETORNO FINANCEIRO QUE GOSTARIA DE VER, MESMO TRABALHANDO MUITO DURO" | D23: "QUERO PODER GARANTIR MINHA INDEPENDÊNCIA FINANCEIRA E DOS MEUS FILHOS" | F23: "ACHO QUE JÁ ATINGI MEU POTENCIAL MÁXIMO COM MINHA EMPRESA" | H23: "PRECISO FALAR COM MEU SÓCIO(A) E DEPOIS TE DOU UM RETORNO"
B24: 3 LADRÕES DE LUCRO QUE TODO EMPRESÁRIO DEVE COMBATER | D24: DEFINITIVAMENTE DESSE JEITO, VOCÊ NÃO SERÁ UM EMPRESÁRIO RICO | F24: É ASSIM QUE VOCE DESCOBRE SE SUA EMPRESA JÁ ATINGIU O POTENCIAL MÁXIMO OU NÃO | H24: SOMENTE HOJE, QUEM FECHAR CONOSCO TERÁ ACESSO AO BONUS X
B25: A VERDADE OCULTA SOBRE EMPRESAS QUE VIVEM NO VERMELHO | D25: ESSAS 2 ATITUDES FIZERAM MINHA EMPRESA GERAR RIQUEZA ABUNDANTE | F25: ESSE É O PONTO CHAVE PRA QUEM ESTÁ COM A EMPRESA ESTAGNADA | H25: ASSISTA ESSE VIDEO SE VOCE AINDA TEM DUVIDAS SOBRE O PRODUTO XYZ...
B26: NÃO VEJO O LUCRO DO MEU NEGÓCIO. O QUE EU FAÇO? | D26: A VERDADE OCULTA SOBRE EMPRESAS MULTI MILIONÁRIAS | F26: O GRANDE RISCO PARA EMPRESAS QUE PARARAM DE CRESCER É ... | H26: QUEM COMPRAR AMANHÃ E NÃO HOJE, PERDERÁ OS BONUS XYZ....

Sheet 2.3
B2: < CLIQUE AQUI E VOLTE AO PAINEL INICIAL | C2: FUNIL DE PROSPECÇÃO ATIVA PELO DIRECT (SOCIAL SELLER)
B4: 1 | C4: IDENTIFICAÇÃO DO PERFIL DO LEAD QUALIFICADO (MQL ou CDP)
B5: 2 | C5: QUAIS AS CARACTERÍSTICAS DA PERSONA DO MEU PRODUTO? (EX: DONO DE EMPRESA, COM MINIMO DE 10 FUNCIONÁRIOS, VIDA E FAMÍLIA ESTRUTURADA, VIAGENS, FÉRIAS, ETC)
B6: 3 | C6: QUAIS ELEMENTOS DA REDE SOCIAL VOU USAR NO CHECKLIST DA MINHA PERSONA? (FOTO,Nº PUBLICAÇÕES, Nº DE SEGUIDORES,INFO NA BIO, SEGUIDORES EM COMUM...)
B7: 4 | C7: IDENTIFICAÇÃO DA LINGUAGEM QUE SERÁ UTILIZADA COM O LEAD
B8: 5 | C8: QUAL O TOM DE VOZ QUE A SUA MARCA SE COMUNICA? (HUMOR, DESCOLADO, FORMAL)
B9: 6 | C9: QUAIS EXPRESSÕES E TERMOS PADRÕES DA COMUNICAÇÃO DA MARCA (JARGÃO, FRASE, PALAVRAS CHAVE)
B10: 7 | C10: QUAIS EXPRESSÕES E TERMOS NÃO USAR (DO CONCORRENTE)
B11: 8 | C11: CRIAÇÃO DE LISTA DE CONTROLE DE ABORDAGENS
B12: 9 | C12: REGISTRAR DADOS PARA GERENCIAR ESTE LEAD (NOME, @, CIDADE, CLASSIFICAÇÃO, DATA DE CONTATO, DE QUAL POST)
B13: 10 | C13: DEFINIR PERIODICIDADE DOS CONTATOS E MONITORAR LEADS SEM CONTATO A "X DIAS"
B14: 11 | C14: ELABORAÇÃO DE CONTEÚDOS INTENCIONAIS PARA GERAR INTERAÇÃO ("LEVANTADA DE MÃO")
B15: 12 | C15: MAPEAR AS DORES, DESEJOS, CRENÇAS LIMITANTES E OBJEÇÕES DO MEU CLIENTE DOS SONHOS
... B49: 46 | C49: SE SIM: ENVIAR LINK DE FORMULÁRIO OU SOLICITAR CONEXÃO VIA WHATSAPP PARA ABRIR PROCESSO DE ATENDIMENTO INDIVIDUAL
B50: FIM

Sheet 2.4
B2: < CLIQUE AQUI E VOLTE AO PAINEL INICIAL | C2: LIVE SHOP
B4: 1
B5: 2
B6: 3
B7: 4
B8: 5
B9: 6
B10: 7
B11: 8
B12: 9
B13: 10
B14: 11
B15: 12
... B49: 46
B50: FIM

Sheet 3.1
B2: < CLIQUE AQUI E VOLTE AO PAINEL INICIAL | C2: AMPULHETA DE VENDAS (MÉDIA GERAL) > | H2: =(D26+H26)/2 -> 6.6
B4: FASE | C4: PERGUNTA | D4: NOTA DE 0 A 10 | E4: MÉDIA | F4: FASE | G4: PERGUNTA | H4: NOTA DE 0 A 10 | I4: MÉDIA
B5: PROSPECÇÃO | C5: 1.1 VOCÊ ESTÁ AONDE O SEU CLIENTE FAZ BUSCAS E ESTÁ PROCURANDO? | D5: 10 | E5: =AVERAGE(D5:D9) -> 8 | F5: PÓS VENDA | G5: 5.1 SEU CLIENTE RECEBE CONTATOS APÓS EFETUAR A COMPRA PRA SABER SE ESTÁ TUDO OK? | H5: 9 | I5: =AVERAGE(H5:H9) -> 8.2
C6: 1.2 VOCÊ POSSUI UMA BUSCA ATIVA PELO SEU CLIENTE? | D6: 9 | G6: 5.2 SEU CLIENTE É PROVOCADO(A) PARA QUE FORNEÇA FEEDBACKS? | H6: 9
C7: 1.3 VOCÊ BUSCA DE FORMA AUTOMÁTICA, ATRAVÉS DE TRÁFEGO PAGO FOCADO NA DOR? | D7: 8 | G7: 5.3 SUA TAXA DE CONVERSÃO É MEDIDA (LEADS OBTIDOS X VENDAS REALIZADAS)? | H7: 8
C8: 1.4 VOCÊ MONITORA A PERFORMANCE DOS SEUS ANÚNCIOS? | D8: 7 | G8: 5.4 SEU CLIENTE RECLAMA COM FREQUÊNCIA DE ALGUM PONTO DA SUA ENTREGA? | H8: 7
C9: 1.5 VOCÊ TESTA SEUS ANÚNCIOS EM VÁRIOS FORMATOS? | D9: 6 | G9: 5.5 SEU CLIENTE “DEIXA DE EXISTIR” APÓS REALIZAR A COMPRA NA SUA EMPRESA? | H9: 8
B10: CONEXÃO | C10: 2.1 SEU CLIENTE CHEGA NA SUA PÁGINA/SITE/LOJA E PERCEBE SUA AUTORIDADE? ELA É ATRATIVA? | D10: 9 | E10: =AVERAGE(D10:D14) -> 7 | F10: FIDELIZAÇÃO | G10: 6.1 VOCÊ OFERTA COMBOS E PROMOÇÕES QUE BUSCAM FIDELIZAR? | H10: 6 | I10: =AVERAGE(H10:H14) -> 7.6
C11: 2.2 SEU CLIENTE É BEM ACOLHIDO(A) QUANDO FAZ O PRIMEIRO CONTATO? | D11: 8 | G11: 6.2 VOCÊ POSSUI "ASSINATURAS" OU "PLANOS“ ANUAIS, SEMESTRAIS? | H11: 7
C12: 2.3 SEU TEMPO DE ATENDIMENTO É ÁGIL E AS RESPOSTAS RÁPIDAS? | D12: 7 | G12: 6.3 VOCÊ POSSUI UMA ROTINA DE CONTACTAR CLIENTES ANTIGOS QUE ESTÃO "SUMIDOS"? | H12: 8
C13: 2.4 SEU CLIENTE SE SENTE CUIDADO(A) DE FORMA DIFERENCIADA ANTES DE COMPRAR? | D13: 6 | G13: 6.4 VOCÊ “MIMA” SEU CLIENTES MAIS FIÉIS (PARABÉNS, OFERTAS ESPECIAIS, BRINDES)? | H13: 9
C14: 2.5 SEU CLIENTE PERCEBE SEU INTERESSE GENUÍNO EM INVESTIGAR O PROBLEMA DELE? | D14: 5 | G14: 6.5 VOCÊ PREMIA OU BONIFICA OS CLIENTES MAIS FIEIS E ANTIGOS NA SUA EMPRESA? | H14: 8
B15: DIAGNÓSTICO | C15: 3.1 VOCÊ PERGUNTA COMO SEU CLIENTE TE CONHECEU? | D15: 6 | E15: =AVERAGE(D15:D19) -> 4 | F15: RETENÇÃO | G15: 7.1 SEU CLIENTE FICA EM MÉDIA COM VOCÊ POR QUANTO TEMPO (ANOS/MESES)? | H15: 7 | I15: =AVERAGE(H15:H19) -> 5.2
C16: 3.2 VOCÊ INVESTIGA SE ELE JÁ TENTOU COMPRAR DE OUTRA EMPRESA ANTES? | D16: 5 | G16: 7.2 SEU CLIENTE POSSUI ALGUM TIPO DE BENEFÍCIO ATRAVÉS DE INDICAÇÕES DE NOVOS CLIENTES? | H16: 6
C17: 3.3 VOCÊ BUSCA DESCOBRIR O DIFERENCIAL QUE O CLIENTE DESEJA? (PREÇO, PRAZO, QUALIDADE) | D17: 4 | G17: 7.3 SEU CLIENTE É MONITORADO MENSALMENTE PARA QUE VOCÊ PROVOQUE NOVAS VENDAS? | H17: 5
C18: 3.4 VOCÊ POSSUI UM SCRIPT DE PERGUNTAS INICIAIS AO SEU CLIENTE? | D18: 3 | G18: 7.4 SEU CLIENTE ESTÁ EM UMA BASE DE DADOS MONITORADA PERIODICAMENTE? | H18: 4
C19: 3.5 VOCÊ MAIS FALA OU MAIS ESCUTA NO INÍCIO DA ABORDAGEM? | D19: 2 | G19: 7.5 SEU CLIENTE TEM UM PLANO COM OS PRÓXIMOS PASSOS CLAROS E ANUNCIADOS? | H19: 4
B20: OFERTA | C20: 4.1 VOCÊ ENVIA ORÇAMENTOS POR EMAIL OU PELO WHATSAPP? | D20: 5 | E20: =AVERAGE(D20:D24) -> 7 | F20: NOVA OFERTA | G20: 8.1 VOCÊ POSSUI UMA BASE DE LEADS (CONTATOS) QUE NÃO COMPRARAM PRA FAZER DOWNSELL? | H20: 4 | I20: =AVERAGE(H20:H24) -> 5.8
C21: 4.2 VOCÊ USA GATILHOS MENTAIS? (HISTÓRIA, PROVA SOCIAL, AUTORIDADE, ESCASSEZ, ETC)? | D21: 6 | G21: 8.2 VOCÊ GERENCIA SUA BASE DE LEADS (CONTATOS) PARA FAZER CROSSELL? | H21: 5
C22: 4.3 VOCÊ ENTREGA BONUS QUE AUMENTAM A PERCEPÇÃO DE VALOR DO CLIENTE? | D22: 7 | G22: 8.3 VOCÊ GERENCIA SUA BASE DE LEADS (CONTATOS) PARA FAZER UPSELL? | H22: 6
C23: 4.4 VOCÊ POSSUI DIFERENCIAIS NA SUA OFERTA OU COPIA ALGO PARECIDO COM A CONCORRÊNCIA? | D23: 8 | G23: 8.4 VOCÊ MONITORA SEUS CONTATOS PARA FAZER UMA OFERTA A CADA X DIAS? | H23: 7
C24: 4.5 VOCÊ CONSTRÓI SUA OFERTA COM BASE NAS DORES DO CLIENTE? | D24: 9 | G24: 8.5 VOCÊ TEM VERGONHA DE OFERTAR E OFERTAR E OFERTAR? NÃO NEGUE SOCORRO! | H24: 7
C26: TOTAL GERAL | D26: =AVERAGE(D5:D24) -> 6.5 | G26: TOTAL GERAL | H26: =AVERAGE(H5:H24) -> 6.7

Sheet 3.2
B2: < CLIQUE AQUI E VOLTE AO PAINEL INICIAL | C2: GESTÃO DA BASE DE CLIENTES (MODO BABÁ)
B4: QUE DIA É HOJE? | D4: NOME + SOBRENOME DO CLIENTE (PF OU PJ) | E4: ÚLTIMO DIA QUE ENTREI EM CONTATO | F4: NUMERO DE DIAS DESDE O ÚLTIMO CONTATO
B5: =TODAY() -> 45951 | E5: 45646 | F5: =$B$5-E5 -> 305
E6: 45680 | F6: =$B$5-E6 -> 271
D7: ELIABE, MAX E SERGIO | E7: 45698 | F7: =$B$5-E7 -> 253
E8: 45699 | F8: =$B$5-E8 -> 252
E9: 45700 | F9: =$B$5-E9 -> 251
D10: TTTT | E10: 45701 | F10: =$B$5-E10 -> 250
D11: DDD | E11: 45702 | F11: =$B$5-E11 -> 249
D12: AAAA | E12: 45703 | F12: =$B$5-E12 -> 248
D13: XXXX | E13: 45704 | F13: =$B$5-E13 -> 247
D14: RRRR | E14: 45705 | F14: =$B$5-E14 -> 246
D15: TTTT | E15: 45706 | F15: =$B$5-E15 -> 245
D16: DDD | E16: 45707 | F16: =$B$5-E16 -> 244
D17: AAAA | E17: 45708 | F17: =$B$5-E17 -> 243
F18: =$B$5-E18 -> 45951
F19: =$B$5-E19 -> 45951
F20: =$B$5-E20 -> 45951
F21: =$B$5-E21 -> 45951

Sheet 3.3
B2: < CLIQUE AQUI E VOLTE AO PAINEL INICIAL | C2: SCRIPT DE ATENDIMENTO | E2: SCRIPT DE ATENDIMENTO
B4: ROTINA DE ATENDIMENTO VIA WHATSAP
B5: BOAS VINDAS E RECEPÇÃO | E5: 1
B6: 1 | C6: OLÁ, BOM DIA (BOA TARDE), POSSO TE AJUDAR? | E6: 2
B7: 2 | C7: DESCOBRIR O MOTIVO DO CONTATO (COMPRA, PAGAMENTO OU INFORMAÇÕES GERAIS) | E7: 3
B8: INVESTIGAÇÃO DO MOTIVO DO CONTATO: COMPRA X PAGAMENTO X INFORMAÇÕES GERAIS | E8: 4
B9: 3 | C9: DESCOBRIR O TIPO DE COMPRA QUE VAI SER REALIZADA (COMPRA PESSOAL X COMPRA DE PRESENTE PARA TERCEIROS) | E9: 5
B10: COMPRA DE PRESENTE PARA TERCEIROS | E10: 6
B11: 4 | C11: VOCÊ TEM ALGUMA PREFERÊNCIA POR ALGUM DEPARTAMENTO DA LOJA? | E11: 7
B12: 5 | C12: SIM: DEFINIR QUAL DEPARTAMENTO | E12: 8
B13: 6 | C13: SE NÃO: APRESENTAR AS OPÇÕES (COSMÉTICOS, MAQUIAGEM, MODA PRAIA, MODA FITNESS, PIJAMAS, BIJUTERIAS, BOLSAS, CALÇADOS, ACESSÓRIOS, DECORAÇÃO) | E13: 9
B14: 7 | C14: VOCÊ SABE A IDADE DA PESSOA QUE GANHARÁ O PRESENTE? | E14: 10
B15: 8 | C15: SE SIM: APRESENTAR PRODUTOS RELACIONADOS À IDADE DA PESSOA E AO DEPARTAMENTO ESCOLHIDO | E15: 11
B16: 9 | C16: SE NÃO: DEFINIR SE É INFANTIL, JOVEM OU ADULTO PARA SEGMENTAR MELHOR | E16: 12
B17: 10 | C17: O PRESENTE É PARA HOMEM OU MULHER? | E17: 13
B18: 11 | C18: SE FOR PARA MULHER: APRESENTAR PRODUTOS FEMININOS | E18: 14
B19: 12 | C19: SE FOR PARA HOMEM: APRESENTAR PRODUTOS MASCULINOS | E19: 15
B20: 13 | C20: VOCÊ TEM ALGUMA VERBA LIMITE? | E20: 16
B21: 14 | C21: SIM: QUAL O VALOR? | E21: 17
B22: 15 | C22: NÃO: APRESENTAR OS PRODUTOS DE TODAS AS FAIXAS DE PREÇO (ALTO, MÉDIO E BAIXO) | E22: 18
B23: DEPARTAMENTOS COM FOCO EM MULHERES | E23: 19
B24: 16 | C24: "SE HÁ INTERESSE POR COSMÉTICOS" | E24: 20
B25: 17 | C25: A PESSOA PREFERE CHEIRO MAIS DOCE OU MENOS ADOCICADO? A PESSOA GOSTA DE CORES MAIS NEUTRAS? O QUE ACHA DE ACRESCENTAR ALGO PRA MELHORAR SEU PRESENTE? (MAQUIAGEM, PERFUMARIA, ITENS DE HIGIENE, ETC) | E25: 21
B26: 18 | C26: "SE HÁ INTERESSE POR PIJAMAS" | E26: 22
B27: 19 | C27: QUAL TAMANHO QUE A PESSOA VESTE? VOCÊ QUER UMA PEÇA DA COLEÇÃO DE VERÃO OU INVERNO? VOCÊ DESEJA UMA PEÇA COM CORES MAIS CLARAS OU ESCURAS? O QUE ACHA DE ACRESCENTAR ALGO PRA MELHORAR SEU PRESENTE? (PANTUFA, ROUPÃO,ETC) | E27: 23
B28: 20 | C28: "SE HÁ INTERESSE POR BIJUTERIAS" | E28: 24
B29: 21 | C29: VOCÊ PREFERE UMA PEÇA DOURADA OU PRATA? A PESSOA QUE SERÁ PRESENTEADA TEM FURO NA ORELHA? O QUE ACHA DE ACRESCENTAR ALGO PRA MELHORAR SEU PRESENTE? (BRINCOS, COLARES, PULSEIRAS, ANÉIS) | E29: 25
B30: 22 | C30: "SE HÁ INTERESSE POR BOLSAS/CARTEIRAS/NECESSAIRE" | E30: 26
B31: 23 | C31: VOCÊ PREFERE CORES MAIS NEUTRAS? VOCÊ TEM PREFERÊNCIA POR TAMANHO DE PREFERÊNCIA? | E31: 27
B32: 24 | C32: "SE HÁ INTERESSE EM "CALÇADOS" | E32: 28
B33: 25 | C33: VOCÊ PREFERE PRESENTEAR A PESSOA DE QUE FORMA? (CHINELO, TÊNIS, BOTA, MULE, SANDÁLIA, RASTEIRINHAS) VOCÊ SABE QUANTO A PESSOA CALÇA? VOCÊ TEM PREFERÊNCIA POR COR DO PRESENTE? VOCÊ PREFERE O CALÇADO COM OU SEM SALTO? | E33: 29
B34: 26 | C34: "SE HÁ INTERESSE POR MODA PRAIA" | E34: 30
B35: 27 | C35: VOCÊ SABIA QUE VENDEMOS AS PARTES DO BIQUINI SEPARADAMENTE? VOCÊ SABE QUE TAMANHO ELA USA EM CIMA E EMBAIXO? VOCÊ TEM PREFERÊNCIA POR MODELO? (MAIS LARGUINHO, FIO DENTAL, TOMARA QUE CAIA, MELHOR SUSTENTAÇÃO) VOCÊ TEM PREFERÊNCIA POR COR? O QUE ACHA DE ACRESCENTAR ALGO PRA MELHORAR SEU PRESENTE? (SAÍDAS DE PRAIA, CANGAS, ACESSÓRIOS, ETC) | E35: 31
... B40: 32 | C40: AO COLETAR AS PREFERENCIAS DO CLIENTE: ENVIAR AS OPÇÕES COM FOTOS | E40: 36
B41: ESCOLHA DAS PEÇAS | E41: 37
B42: 33 | C42: O CLIENTE FEZ A ESCOLHA DO PRESENTE? | E42: 38
B43: 34 | C43: SIM: AVANÇAR PARA DEFINIÇÃO DA FORMA DE PAGAMENTO | E43: 39
B44: 35 | C44: NÃO:APROFUNDAR A INVESTIGAÇÃO E APRESENTAR MAIS OS PRODUTOS | E44: 40
B45: DEFINIÇÃO DA FORMA DE RECEBIMENTO DO PRESENTE | E45: 41
B46: 36 | C46: ENTREGA NA CASA DO CLIENTE: COLETAR O ENDEREÇO DO CLIENTE PARA COTAR A TAXA DE ENTREGAR, APROVAR E DEFINIR HORÁRIO | E46: 42
B47: 37 | C47: RETIRADA EM LOJA: SEPARAÇÃO E RESERVA DO PEDIDO, DEFININDO QUEM E QUANDO SERÁ FEITA A RETIRADA | E47: 43
B48: DEFINIÇÃO DA FORMA DE PAGAMENTO | E48: 44
B49: 38 | C49: VOCÊ PREFERE FAZER QUE TIPO DE PAGAMENTO? | E49: 45
B50: 39 | C50: PAGAMENTO NA RETIRADA PAGAMENTO NA ENTREGA PAGAMENTO VIA PIX PAGAMENTO VIA CREDIÁRIO | E50: 46
B51: FIM DO PROCESSO | E51: FIM DO PROCESSO

Sheet 3.4
B2: < CLIQUE AQUI E VOLTE AO PAINEL INICIAL | C2: QUEBRA DE OBJEÇÕES
B4: # | C4: ORIGEM DA OBJEÇÃO | E4: O QUE NÃO FALAR | G4: O QUE FALAR
B6: 1 | C6: Cliente precisa de tempo pra pensar | E6: Você gostaria de pensar mais um pouco? | G6: Quando nós começamos a implementar essa solução para você?
B7: 2 | C7: Cliente apresentou dúvidas | E7: Tudo bem, então voltamos a falar em breve... | G7: 99% das suas dúvidas, eu acho que posso solucionar. Pergunte!
B8: 3 | C8: Cliente aparentemente não gostou do que foi apresentado | E8: Mas se você não gostar, podemos ver outra coisa! | G8: Eu tenho certeza que isso vai atender perfeitamente as suas necessidades.
B9: 4 | C9: Cliente sem data de fechamento exata | E9: Se der, me avisa quando você quiser fechar. Ok? | G9: Podemos fechar agora mesmo e começar a resolver esse problema.
B10: 5 | C10: Cliente pedindo desconto | E10: Olha, eu acho que não consigo dar mais desconto | G10: Entendi, mas é o valor justo pelo que você vai receber e vale cada centavo!
B11: 6 | C11: Cliente sem tempo para falar ou se reunir | E11: Ah, se você quiser, pode me ligar depois, tá bom? | G11: Vamos agendar nosso próximo contato para avançar com isso?
B12: 7 | C12: Cliente sem tempo para falar ou se reunir | E12: Será que você não tem um tempinho pra falar agora? | G12: Sei que seu tempo é curto, mas fica tranquilo que eu serei breve.
B13: 8 | C13: Cliente demonstrando desconfiança na solução | E13: Cliente, eu acho que eu poderia te ajudar com isso. | G13: Eu tenho certeza que essa solução vai agregar muito no seu negócio.
B14: 9 | C14: Cliente com limitações financeiras | E14: Oh, nós podemos ver se cabe no seu planejamento financeiro. | G14: Vamos ajustar isso para que você tenha o melhor retorno sobre o investimento.
B15: 10 | C15: Cliente que precisa de mais informações | E15: Eu posso te enviar mais informações por e-mail? | G15: Eu vou te enviar os detalhes agora para já iniciarmos o processo.
B16: 11 | C16: Cliente sem confiança para decidir | E16: Se você mudar de ideia me avisa. | G16: Vou te acompanhar nesse processo para que você tome a melhor decisão.
B17: 12 | C17: Cliente quer falar com marido/esposa/ sócio(a) | E17: Tudo bem. Quando tiver falado me avise. | G17: Se dependesse somente de você, estaríamos fechados? Se sim, o que acha que essa pessoa pode ter que te impeça de fechar agora?

Sheet 3.5
C2: < CLIQUE AQUI E VOLTE AO PAINEL INICIAL | D2: GATILHOS MENTAIS | M2: NOTA DA AVALIAÇÃO > | P2: =AVERAGE(H6,H7,H8,H9,H10,P6,P7,P8,P9,P10) -> 7
D4: # | F4: TÓPICO ANALISADO | H4: NOTA ATUAL | K4: # | M4: TÓPICO ANALISADO | P4: NOTA ATUAL
D6: 1 | F6: VOCÊ E SEU TIME USAM E DOMINAM O GATILHO DA ESCASSEZ? | H6: 6 | K6: 6 | M6: VOCÊ E SEU TIME USAM E DOMINAM O GATILHO DA HISTÓRIA? | P6: 6
D7: 2 | F7: VOCÊ E SEU TIME USAM E DOMINAM O GATILHO DA URGÊNCIA? | H7: 7 | K7: 7 | M7: VOCÊ APRESENTA SEUS PRODUTOS/ SERVIÇOS DE FORMA A CONDUZIR A ESCOLHA DO CLIENTE? | P7: 5
D8: 3 | F8: VOCÊ E SEU TIME USAM E DOMINAM O GATILHO DA AUTORIDADE? | H8: 8 | K8: 8 | M8: VOCÊ E SEU TIME USAM E DOMINAM O GATILHO DA ANTECIPAÇÃO? | P8: 7
D9: 4 | F9: VOCÊ E SEU TIME USAM E DOMINAM O GATILHO DA PROVA SOCIAL? | H9: 9 | K9: 9 | M9: VOCÊ E SEU TIME USAM E DOMINAM O GATILHO DO “SEM COMPROMISSO” PARA QUE O CLIENTE USE/TESTE ANTES? | P9: 8
D10: 5 | F10: VOCÊ E SEU TIME USAM E DOMINAM O GATILHO DA RECIPROCIDADE? | H10: 5 | K10: 10 | M10: VOCÊ E SEU TIME USAM E DOMINAM PERGUNTAS CHAVES PARA QUEBRA DE OBJEÇÕES? | P10: 9

Sheet 4.1
D2: < CLIQUE AQUI E VOLTE AO PAINEL INICIAL | F2: RECRUTAMENTO E SELEÇÃO
D4: # | F4: PROCESSO DE RECRUTAMENTO | I4: # | K4: ROTEIRO DE ENTREVISTA DO CANDIDATO | L4: A PERCEPÇÃO FOI: (+ OU -) | M4: ANOTAÇÕES | P4: A PERCEPÇÃO FOI: (+ OU -)
D6: 1 | F6: LISTAR ATRIBUIÇÕES E PERFIL COMPORTAMENTAL PARA A FUNÇÃO DESEJADA NA EMPRESA | I6: 8.1 | K6: INTRODUÇÃO DA ENTREVISTA | P6: POSITIVA
D7: 2 | F7: CALCULAR O CUSTO REFERENTE A VAGA A SER PREENCHIDA E VALIDAR COM O SETOR FINANCEIRO | I7: 8.2 | K7: CUMPRIMENTE A PESSOA, DIGA SEU NOME E INICIE A ENTREVISTA | P7: NEGATIVA
D8: 3 | F8: ELABORAR O ANÚNCIO DA VAGA (ENVOLVER O MARKETING) | I8: 8.3 | K8: INFORME AS FUNÇÕES A SEREM EXERCIDAS, HORÁRIO DE TRABALHO E EXPECTATIVAS PRO CARGO | P8: NEUTRA
D9: 4 | F9: DIVULGAR O ANÚNCIO DA VAGA (SITES ESPECIALIZADOS, PORTAIS DE RECRUTAMENTO, ETC) | I9: 8.4 | K9: DEPOIS DE TUDO APRESENTADO, VOCÊ CONTINUA COM INTERESSE NA VAGA?
D10: 5 | F10: OBTER CURRÍCULOS PARA A VAGA ABERTA | I10: 8.5 | K10: SE NÃO: AGRADEÇA A PARTICIPAÇÃO E ENCERRE A ENTREVISTA
D11: 6 | F11: REALIZAR A TRIAGEM CURRICULAR | I11: 8.6 | K11: SE SIM: DÊ CONTINUIDADE A ENTREVISTA
D12: 7 | F12: AGENDAR ENTREVISTAS INICIAIS (PRESENCIAL OU VIDEO CONFERÊNCA) | I12: 8.7 | K12: AVALIANDO O CONTEXTO PESSOAL DO CANDIDATO(A):
D13: 8 | F13: REALIZAR ENTREVISTAS INICIAIS (PRESENCIAL OU VIDEO CONFERÊNCA) - ATIVIDADE CRÍTICA | I13: 8.8 | K13: ONDE E COM QUEM VOCÊ MORA ATUALMENTE? (BUSQUE ENTENDER O CONTEXTO FAMILIAR DA PESSOA)
D14: 9 | F14: O CANDIDATO FOI APROVADO(A) NA ENTREVISTA INICIAL? | I14: 8.9 | K14: QUAIS SÃO SEUS PLANOS PROFISSIONAIS E DE CARREIRA?
D15: 10 | F15: SE NÃO: ENVIAR FEEDBACK POR EMAIL E ENCERRAR PROCESSO SELETIVO DO CANDIDATO(A) | I15: 8.10 | K15: O QUE VOCÊ FAZ NO SEU TEMPO LIVRE? VOCÊ TEM ALGUM HOBBIE? DIGA 3 COISAS QUE VOCÊ AMA NA VIDA
D16: 11 | F16: SE SIM: AGENDAR A APLICAÇÃO DE PROVAS TÉCNICAS PRESENCIAIS (SE HOUVER) | I16: 8.11 | K16: VOCÊ FAZ PARTE DE ALGUM GRUPO (RELIGIÃO, ONG, BANDA, ESPORTE)?
D17: 12 | F17: O CANDIDATO FOI APROVADO(A) NAS PROVAS TÉCNICAS? | I17: 8.12 | K17: AVALIANDO O QUE TROUXE O CANDIDATO(A) ATÉ A EMPRESA:
D18: 13 | F18: SE NÃO: ENVIAR FEEDBACK POR EMAIL E ENCERRAR PROCESSO SELETIVO DO CANDIDATO(A) | I18: 8.13 | K18: POR QUE VOCÊ SE CANDIDATOU PARA ESSA VAGA?
D19: 14 | F19: SE SIM: CONSOLIDAR TODAS ETAPAS DO PROCESSO DE CONTRATAÇÃO DOS CANDIDATOS APROVADOS | I19: 8.14 | K19: O QUE VOCÊ SABE SOBRE NOSSA EMPRESA?
D20: 15 | F20: ENTREGAR TODOS OS RESULTADOS DE CADA ETAPA PARA O GESTOR SOLICITANTE | I20: 8.15 | K20: O QUE VOCÊ SABE SOBRE NOSSOS PRODUTOS/SERVIÇOS?
... D24: 19 | F24: AGENDAR ASSINATURA DO CONTRATO DE TRABALHO E ENTREGA DOS DOCUMENTOS | I24: 8.19 | K24: O QUE MAIS GOSTOU E MENOS GOSTOU NAS EMPRESAS ONDE TRABALHOU?
D25: FIM | I25: 8.20 | K25: VOCÊ JÁ RECEBEU CRÍTICAS SOBRE O SEU TRABALHO? O QUE FOI DITO? COMO VOCÊ REAGIU?
I26: 8.21 | K26: AVALIANDO A HUMILDADE DO CANDIDATO(A):
I27: 8.22 | K27: PARA O CARGO QUE VOCÊ DISPUTA, VOCÊ ACHA QUE ESTÁ 100% PREPARADO(A)? ONDE PODE MELHORAR?
I28: 8.23 | K28: QUANDO AS PESSOAS TE ELOGIAM, O QUE ELAS FALAM? EVIDENCIE COM EXEMPOS.
I29: 8.24 | K29: NO QUE VOCÊ ESTÁ CONCENTRADO EM MELHORAR ATUALMENTE? EXEMPLIFIQUE
I30: 8.25 | K30: NA SUA OPINIÃO O QUE UM BOM/BOA______________(NOME DO CARGO) PRECISA TER?
I31: 8.26 | K31: QUAIS DESSAS CARACTERÍSTICAS (DA PERGUNTA ANTERIOR), VOCÊ ACHA QUE POSSUI? EVIDENCIE.
I32: 8.27 | K32: DIGA UMA COISA INESQUECÍVEL QUE VOCÊ REALIZOU E SENTE MUITO ORGULHO DE TER FEITO
I33: 8.28 | K33: AVALIANDO A CAPACIDADE DE TRABALHAR EM EQUIPE/SOB PRESSÃO DO CANDIDATO(A):
I34: 8.29 | K34: QUAL ÚLTIMO PROJETO QUE ATUOU? COMO TRABALHOU PRA ALCANÇA-LO?
I35: 8.30 | K35: COMO VOCÊ TOMAVA DECISÕES DENTRO DA SUA ÚLTIMA EMPRESA/ EXPERIÊNCIA?
I36: 8.31 | K36: JÁ FOI TRATADO COM GROSSERIA POR ALGUM CLIENTE?
I37: 8.32 | K37: COMO É PRA VOCÊ TRABALHAR COM METAS AUDACIOSAS? E SE PRECISAR FAZER HORAS EXTRAS?
... I43: 8.38 | K43: ONDE VOCÊ DESEJA ESTAR PROFISSIONALMENTE DAQUI 1, 2 OU 3 ANOS?
I44: FIM

Sheet 4.2
B2: < CLIQUE AQUI E VOLTE AO PAINEL INICIAL | C2: SCRIPT DE ATENDIMENTO IDEAL (EXEMPLO: AÇOUGUE)
B4: # | C4: PROCESSO CRÍTICO: ATENDIMENTO PRESENCIAL DE CLIENTES NO AÇOUGUE | E4: # | F4: PROCESSO CRÍTICO: NOME DO PROCESSO
B5: 1 | C5: DESEJAR AS BOAS VINDAS AO CLIENTE (BOM DIA, BOA TARDE, BOA NOITE) | E5: 1
B6: 2 | C6: QUAL OCASIÃO TE TROUXE ATÉ AQUI EM NOSSO AÇOUGUE? | E6: 2
B7: 3 | C7: COMPRA DA SEMANA: REFEIÇÕES DO COTIDIANO | E7: 3
B8: 4 | C8: COMPRA DE FINAL DE SEMANA: REFEIÇÃO ESPECIAL | E8: 4
B9: 5 | C9: COMPRA DE FINAL DE SEMANA: CHURRASCO COM OS AMIGOS | E9: 5
B10: 6 | C10: VOCÊ VEIO BUSCANDO ALGUM CORTE ESPECÍFICO PRA ESSE PEDIDO? | E10: 6
B11: 7 | C11: SE A PESSOA BUSCA UM CORTE FRANGO: | E11: 7
B12: 8 | C12: VOCÊ PLANEJA FAZER ALGUM PRATO ESPECÍFICA COM O FRANGO? | E12: 8
B13: 9 | C13: SUGERIR PRATOS COM FRANGO: ESTROGONOFF, FRICASSÊ, EMPADÃO DE FRANGO, FRANGO À MILANESA | E13: 9
B14: 10 | C14: OFERTAR OS CORTES JÁ TEMPERADOS | E14: 10
B15: 11 | C15: OFERTAR OS CORTES JÁ NAS BANDEJAS | E15: 11
B16: 12 | C16: OFERTAR OS CORTES COM OSSOS (COXA, SOBRECOXA, ASINHA, PEITO INTEIRO) | E16: 12
... B38: 34 | C38: ESPERO QUE VOCÊ VOLTE EM BREVE E ME CONTE COMO FOI A EXPERIÊNCIA COM AS SUGESTÕES SUGERIDAS | E38: 34

Sheet 4.3
C2: < CLIQUE AQUI E VOLTE AO PAINEL INICIAL | D2: OCIOSIDADE X PRODUTIVIDADE
C4: # | D4: NOME: | E4: CRITICIDADE DA ROTINA | F4: FREQUÊNCIA DA ROTINA | G4: TEMPO DESTINADO (POR DIA) | H4: TEMPO DESTINADO (POR SEMANA) | I4: TEMPO DESTINADO (POR MÊS) | J4: AUTO AVALIAÇÃO | K4: AVALIAÇÃO DA LIDERANÇA | L4: DESVIO
C6: 1 | D6: DESCRIÇÃO DA ATIVIDADE | E6: ALTA | F6: DIÁRIA | G6: 0.00034722222 | J6: 8 | K6: 4 | L6: =K6-J6 -> -4
C7: 2 | D7: DESCRIÇÃO DA ATIVIDADE | E7: MÉDIA | F7: DIÁRIA | G7: 0.00034722222 | J7: 10 | K7: 5 | L7: =K7-J7 -> -5
C8: 3 | D8: DESCRIÇÃO DA ATIVIDADE | E8: ALTA | F8: DIÁRIA | G8: 0.00034722222 | J8: 9 | K8: 6 | L8: =K8-J8 -> -3
C9: 4 | D9: DESCRIÇÃO DA ATIVIDADE | E9: MÉDIA | F9: DIÁRIA | G9: 0.00034722222 | J9: 9 | K9: 7 | L9: =K9-J9 -> -2
C10: 5 | D10: DESCRIÇÃO DA ATIVIDADE | E10: ALTA | F10: DIÁRIA | G10: 0.00034722222 | J10: 8 | K10: 6 | L10: =K10-J10 -> -2
C11: 6 | D11: DESCRIÇÃO DA ATIVIDADE | E11: BAIXA | F11: DIÁRIA | G11: 0.00034722222 | J11: 9 | K11: 5 | L11: =K11-J11 -> -4
C12: 7 | D12: DESCRIÇÃO DA ATIVIDADE | E12: ALTA | F12: DIÁRIA | G12: 0.00034722222 | J12: 7 | K12: 6 | L12: =K12-J12 -> -1
C13: 8 | D13: DESCRIÇÃO DA ATIVIDADE | E13: BAIXA | F13: DIÁRIA | G13: 0.00034722222 | J13: 8 | K13: 8 | L13: =K13-J13 -> 0
C14: 9 | D14: DESCRIÇÃO DA ATIVIDADE | E14: BAIXA | F14: DIÁRIA | G14: 0.00034722222 | J14: 8 | K14: 8 | L14: =K14-J14 -> 0
C15: 10 | D15: DESCRIÇÃO DA ATIVIDADE | E15: MÉDIA | F15: DIÁRIA | G15: 0.00034722222 | J15: 8 | K15: 8 | L15: =K15-J15 -> 0
C16: 11 | D16: DESCRIÇÃO DA ATIVIDADE | E16: BAIXA | F16: SEMANAL | H16: 0.0013888889 | J16: 8 | K16: 8 | L16: =K16-J16 -> 0
C17: 12 | D17: DESCRIÇÃO DA ATIVIDADE | E17: MÉDIA | F17: SEMANAL | H17: 0.0020833333 | J17: 8 | K17: 8 | L17: =K17-J17 -> 0
C18: 13 | D18: DESCRIÇÃO DA ATIVIDADE | E18: BAIXA | F18: SEMANAL | H18: 0.0010416667 | J18: 8 | K18: 8 | L18: =K18-J18 -> 0
C19: 14 | D19: DESCRIÇÃO DA ATIVIDADE | E19: ALTA | F19: MENSAL | I19: 0.0027777778 | J19: 8 | K19: 8 | L19: =K19-J19 -> 0
C20: 15 | D20: DESCRIÇÃO DA ATIVIDADE | E20: ALTA | F20: MENSAL | I20: 0.0041666667 | J20: 8 | K20: 8 | L20: =K20-J20 -> 0
C22: TOTAL DAS AVALIAÇÕES > | G22: =SUM(G6:G20) -> 0.0034722222 | H22: =SUM(H6:H20) -> 0.0045138889 | I22: =SUM(I6:I20) -> 0.0069444444 | J22: =AVERAGE(J6:J15) -> 8.4 | K22: =AVERAGE(K6:K15) -> 6.3 | L22: =AVERAGE(L6:L15) -> -2.1

Sheet 4.4
C2: < CLIQUE AQUI E VOLTE AO PAINEL INICIAL | E2: FEEDBACKS 1 X 1
E4: # | G4: TÓPICO ANALISADO | J4: # | L4: TÓPICO ANALISADO
E6: 1 | G6: ELABORAR CALENDÁRIO DE REUNIÕES POR FUNCIONÁRIO (Sugestão: 30 minutos por pessoas) | J6: 14 | L6: VOCÊ SE SENTE DESAFIADO(A) NO DIA A DIA DAS SUAS ROTINAS?
E7: 2 | G7: EXPLICAR PARA A EQUIPE O PROPÓSITO DAS REUNIÕES INDIVIDUAIS (Alinhamento de expectativas) | J7: 15 | L7: COMO A EMPRESA PODE MELHORAR PARA FACILITAR AINDA MAIS AS SUAS ROTINAS?
E8: 3 | G8: DEFINIR A DATA, HORÁRIO,LOCAL E AGENDAR REUNIÃO (Preferencialmente fora do ambiente de trabalho) | J8: 16 | L8: COMO VOCÊ PODE MELHORAR PARA DESEMPENHAR MELHOR SUAS FUNÇÕES NA EMPRESA?
E9: 4 | G9: PERGUNTAS PARA CONDUÇÃO DA REUNIÃO (LADO PESSOAL) | J9: 17 | L9: FEEDBACK POSITIVO:
E10: 5 | G10: COMO ESTÁ SUA FAMÍLIA TENDO EM VISTA QUE ISSO É A BASE PARA SEU BOM DESEMPENHO? | J10: 18 | L10: APRESENTAR CARACTERÍSTICAS FORTES E TRAZER EVIDÊNCIAS COM EXEMPLOS REIAS
E11: 6 | G11: SEU TRABALHO HOJE INTERFERE NEGATIVAMENTE EM ALGUMA ESFERA DA SUA VIDA PESSOAL? | J11: 19 | L11: FEEDBACK NEGATIVO:
E12: 7 | G12: VOCÊ CONSEGUE CONCILIAR BEM SUA VIDA FAMILIAR COM O TRABALHO? (ex: Tempo de qualidade) | J12: 20 | L12: APRESENTAR PONTOS DE MELHORIA E TRAZER EVIDÊNCIAS COM EXEMPLOS REAIS
E13: 8 | G13: VOCÊ CONSEGUE CONCILIAR BEM SUA SAÚDE COM O TRABALHO (Ex: Atividades físicas) | J13: 21 | L13: ALIANÇA DE COMPROMISSO E FECHAMENTO DA REUNIÃO
E14: 9 | G14: HÁ ALGUMA SITUAÇÃO PESSOAL HOJE QUE TEM ROUBADO SUA PAZ OU ATENÇÃO (EX: Dívidas) | J14: 22 | L14: PARA ROTINAS QUE FUNCIONÁRIO FAZ BEM: SOLICITAR QUE A ROTINA SEJA PADRONIZADA
E15: 10 | G15: PERGUNTAS PARA CONDUÇÃO DA REUNIÃO (LADO PROFISSIONAL) | J15: 23 | L15: PARA ROTINAS QUE UM FUNCIONÁRIO PODE MELHORAR: CRIAR E VALIDAR AÇÕES CORRETIVAS
E16: 11 | G16: VOCÊ É FELIZ NO DIA A DIA DO SEU TRABALHO AQUI NA EMPRESA? | J16: 24 | L16: PARA ROTINAS QUE A EMPRESA PODE MELHORAR: CRIAR E VALIDAR AÇÕES CORRETIVAS
E17: 12 | G17: VOCÊ CONSIDERA SEU AMBIENTE DE TRABALHO ADEQUADO? SE NÃO, COMO PODERIA MELHORAR? | J17: 25 | L17: AGENDAR DATA, HORÁRIO E LOCAL DA PRÓXIMA REUNIÃO INDIVIDUA
E18: 13 | G18: COMO VOCÊ TEM SE SENTIDO NO DIA A DIA DA EXECUÇÃO DO SEU CARGO E FUNÇÕES? | J18: 26 | L18: FIM

Sheet 4.5
C2: < CLIQUE AQUI E VOLTE AO PAINEL INICIAL | E2: TREINAMENTO E AVALIAÇÃO DE LIDERANÇAS
C4: TÓPICOS ANALISADOS | G4: TÓPICOS ANALISADOS
C6: MARQUE O “X” AQUI↓ | E6: HABILIDADES DE LIDERANÇA TEMA: DAR A DIREÇÃO | G6: MARQUE O “X” AQUI↓ | I6: HABILIDADES DE LIDERANÇA TEMA: LIDAR COM MUDANÇAS
E7: PROMOVER O DESENVOLVIMENTO DE UMA VISÃO COMUM/COMPARTILHADA | I7: DESAFIAR O ESTADO “SEMPRE FOI FEITO DESSA FORMA”
C8: X | E8: PROVER DIRECIONAMENTO CLARO E DEFINIR PRIORIDADES PARA O TIME | I8: ESTIMULAR AS PESSOAS A FAZER MUDANÇAS E MELHORIAS
E9: ESCLARECER PAPÉIS E RESPONSABILIDADES ENTRE OS INTEGRANTES DO TIME | I9: ENVOLVER OUTRAS PESSOAS NO PROCESSO DE MUDANÇA
E10: CONCILIAR A VISÃO DE CADA UM DA EQUIPE COM A VISÃO INSTITUCIONAL | I10: PREPARAR AS PESSOAS PARA ENTENDER AS MUDANÇAS
E11: COMUNICAR EM ASPECTOS MAIS AMPLOS E ESTRATÉGICOS | G11: MARQUE O “X” AQUI↓ | I11: HABILIDADES DE LIDERANÇA TEMA: MOTIVAR OUTRAS PESSOAS
C12: X | E12: ATENTAR-SE PARA OS DETALHES CHAVE E QUE SÃO REALMENTE RELEVANTES | I12: CONFIAR NA COMPETÊNCIA DE OUTRAS PESSOAS PARA EXECUTAR UM BOM TRBALHO
C13: MARQUE O “X” AQUI↓ | E13: HABILIDADES DE LIDERANÇA TEMA: DETERMINAÇÃO E BOM SENSO | I13: INSPIRAR PESSOAS A EXCEDER SUAS PRÓPRIAS EXPECTATIVAS
E14: TRADUZIR AS ESTRATÉGIAS INSTITUCIONAIS EM OBJETIVOS CLAROS | I14: CRIAR UM AMBIENTE QUE FAÇA DO TRABALHO UM AMBIENTE LEVE E DIVERTIDO
C15: X | E15: ANALISAR PROBLEMAS SOB DIFERENTES PONTOS DE VISTA | I15: MOTIVAR PESSOAS QUE TENHAM RECEBIDO FEEDBACKS NEGATIVOS
E16: TOMAR DECISÕES EM CENÁRIOS DE INCERTEZAS | I16: PERCEBER QUANDO AS PESSOAS FAZEM COISAS BOAS E RECONHECE
C17: MARQUE O “X” AQUI↓ | E17: HABILIDADES DE LIDERANÇA TEMA: DECIDIR CORAJOSAMENTE | G17: MARQUE O “X” AQUI↓ | I17: HABILIDADES INTERPESSOAIS TEMA: CONSTRUIR RELACIONAMENTOS
E18: ADOTAR UMA POSIÇÃO E RESOLVER QUESTÕES CRÍTICAS | I18: CONSTRUIR RELACIONAMENTO EFETIVO COM SEUS COLABORADORES DIRETOS
E19: MUDAR DE IDEIA OU TOMADA DE AÇÃO QUANDO A SITUAÇÃO EXIGE | I19: CONSTRUIR RELACIONAMENTO EFETIVO COM SEUS PARES
C20: X | E20: COMPROMETER-SE DE CORPO E ALMA APESAR DE RECEIOS E DÚVIDAS | I20: CONSTRUIR RELACIONAMENTO EFETIVO COM PESSOAS CHAVE DE OUTRAS FUNÇÕES/GRUPOS
C21: X | E21: TOMAR DECISÕES DIFÍCEIS QUE PODEM IMPACTAR NEGATIVAMENTE OUTRAS PESSOAS | I21: FAZER USO DA REDE INFORMAL DE RELACIONAMENTO NA EMPRESA PARA CONSEGUIR AVANÇOS
E22: DESAFIAR OUTRAS PESSOAS A FAZER ESCOLHAS DIFÍCEIS | G22: MARQUE O “X” AQUI↓ | I22: HABILIDADES INTERPESSOAIS TEMA: GERENCIAR POR MEIO DAS DIFERENÇAS
C23: MARQUE O “X” AQUI↓ | E23: HABILIDADES DE LIDERANÇA TEMA: INFLUENCIAR OUTRAS PESSOAS | I23: CRIAR UM AMBIENTE NO QUAL PESSOAS DE DIFERENTES PERFIS SE SINTAM À VONTADE
E24: ORDENAR ATENÇÃO DA EQUIPE | I24: AJUDAR PESSOAS DE DIFERENTES CULTURAS A TER SUCESSO NA ORGANIZAÇÃO
E25: CONVERGIR EMOÇÕES, ENERGIA E PRÓPÓSITO | I25: GERENCIAR SEU PRÓPRIO DESCONFORTO QUANDO TRABALHA COM PESSOAS DIFERENTES
E26: GANHAR O APOIO DA EQUIPE | I26: CONSTRUIR RELACIONAMENTO EFETIVO COM PESSAS MUITO DIFERENTES DE VOCÊ
E27: CONDUZIR OUTROS A TOMAR AS PRÓPRIAS MEDIDAS | G27: MARQUE O “X” AQUI↓ | I27: HABILIDADES INTERPESSOAIS TEMA: RESOLVER CONFLITOS
E28: OUVIR ATENTAMENTE E REFLETIR SOBRE O ASSUNTO | I28: EXPRESSAR DESACORDO COM TATO E SENSIBILIDADE
E29: CONSTRUIR ENTENDIMENTO COMUM ENTRE A EQUIPE | I29: ENDEREÇAR SITUAÇÕES E TRABALHAR PARA RESOLVER CONFLITOS
E30: INFLUENCIAR E AJUSTAR DECISÕES VINDAS DE NÍVEIS SUPERIORES | G30: X | I30: REDUZIR SUA PRÓPRIA POSIÇÃO DEFENSIVA
C31: MARQUE O “X” AQUI↓ | E31: HABILIDADES DE LIDERANÇA TEMA: INSPIRAR TRABALHO EM EQUIPE | I31: ENGAJAR PESSOAS EM CONVERSAS DIFÍCEIS
E32: VALORIZAR A CONTRIBUIÇÃO DE CADA INTEGRANTE DA EQUIPE | G32: MARQUE O “X” AQUI↓ | I32: HABILIDADES DE GERENCIAMENTO TEMA: LIDERANÇA EXEMPLAR
C33: X | E33: ENVOLVER NA TOMADA DE DECISÃO AS PESSOAS QUE SERÃO IMPACTADAS POR ELA | I33: VIVER DE ACORDO COM OS COMPROMISSOS FIRMADOS
C34: X | E34: PROMOVER COOPERAÇÃO E CAMARADAGEM ENTRE A EQUIPE | G34: X | I34: DEMONSTRAR PRINCÍPIOS E ÉTICA AO EXERCER LIDERANÇA
E35: REPROVAR O PENSAMENTO “EU” EM DETRIMENTO DO “NÓS” | I35: LIDAR DE FORMA CONSTRUTIVA COM SEUS PRÓPRIOS ERROS E FRACASSOS
E36: ENERGIZAR A EQUIPE AO ENFRENTAR TAREFAS DIFÍCEIS | I36: TRABALHAR DE FORMA CONSTRUTIVA MESMO SOB STRESS E PRESSÃO
E37: RECONHECER E COMEMORAR AS CONQUISTAS DO TIME | I37: ACEITAR CRÍTICAS DE FORMA ABERTA E NÃO DEFENSIVA
I38: DEMONSTRAR PACIÊNCIA EM NÍVEIS APROPRIADOS
I39: ADAPTAR COMPORTAMENTO EM RESPOSTA A FEEDBACKS

Sheet 4.6
C2: < CLIQUE AQUI E VOLTE AO PAINEL INICIAL | D2: PESQUISA DE CLIMA ORGANIZACIONAL | M2: NOTA DA AVALIAÇÃO > | P2: =AVERAGE(H6:H15,P6:P15) -> 5.2
D4: # | F4: TÓPICO ANALISADO | H4: NOTA ATUAL | K4: # | M4: TÓPICO ANALISADO | P4: NOTA ATUAL
D6: 1 | F6: SUA EQUIPE SE SENTE 100% CONFORTÁVEL NO AMBIENTE DE TRABALHO? | H6: 6 | K6: 11 | M6: A LIDERANÇA DÁ AUTONOMIA PARA O TIME NA EXECUÇÃO DE TAREFAS? | P6: 3
D7: 2 | F7: O DIA A DIA DE TRABALHO É AGRADÁVEL PARA O TIME? | H7: 4 | K7: 12 | M7: A EMPRESA OFERECE OPÇÕES DE CRESCIMENTO PARA A EQUIPE? | P7: 8
D8: 3 | F8: EXISTEM LAÇOS DE AMIZADE ENTRE OS MEMBROS DO TIME? | H8: 9 | K8: 13 | M8: A EMPRESA SINALIZA QUAIS ENTREGAS SÃO NECESSÁRIAS PARA PROMOÇÕES? | P8: 2
D9: 4 | F9: O TRABALHO IMPACTA POSITIVAMENTE A VIDA DE ALGUMA PESSOA? | H9: 10 | K9: 14 | M9: A EMPRESA OFERECE UM AMBIENTE DE TRABALHO ADEQUADO PRO TIME? | P9: 5
D10: 5 | F10: A LIDERANÇA É CLARA NAS FUNÇÕES QUE DELEGA PARA A EQUIPE? | H10: 5 | K10: 15 | M10: AS CONDIÇÕES ERGONÔMICAS DE TRABALHO SÃO BOAS? | P10: 7
D11: 6 | F11: A LIDERANÇA DÁ LIBERDADE PARA PEDIR E DAR FEEDBACKS? | H11: 6 | K11: 16 | M11: A EQUIPE ESTÁ SATISFEITA COM REMUNERAÇÃO RECEBIDA? | P11: 8
D12: 7 | F12: A LIDERANÇA DÁ ABERTURA PARA QUE TODOS OPINEM? | H12: 7 | K12: 17 | M12: A EQUIPE RECEBE BONIFICAÇÕES QUE MOTIVAM E ENGAJAM? | P12: 0
D13: 8 | F13: A LIDERANÇA RECONHECE AS AÇÕES POSITIVAS DA SUA EQUIPE? | H13: 3 | K13: 18 | M13: SUA EQUIPE INDICARIA SUA EMPRESA PARA UMA PESSOA PRÓXIMA OU AMIGO? | P13: 7
D14: 9 | F14: A EQUIPE ESTÁ FELIZ COM AS FUNÇÕES DESEMPENHADAS? | H14: 2 | K14: 19 | M14: SUA EQUIPE SENTE ORGULHO DE TRABALHAR NA SUA EMPRESA? | P14: 6
D15: 10 | F15: A LIDERANÇA DIVIDE BEM AS ATIVIDADES EVITANDO SOBRECARGA NO TIME? | H15: 1 | K15: 20 | M15: SUA EMPRESA PERMITE A REALIZAÇÃO PROFISSIONAL DE CADA FUNCIONÁRIO? | P15: 5

Sheet 4.7
B2: < CLIQUE AQUI E VOLTE AO PAINEL INICIAL | C2: ENTREVISTA DE DESLIGAMENTO
B4: # | C4: DESCRIÇÃO DA ETAPA
B5: PREPARAÇÃO | C5: EXPLICAR O QUE É A ENTREVISTA: É UMA ETAPA DO PROCESSO DEMISSIONAL QUE CONSISTE NUMA CONVERSA ESTRUTURADA ENTRE O PROFISSIONAL DESLIGADO E UM COLABORADOR DO TIME DE RH
C6: EXPLICAR PARA QUE SERVE A ENTREVISTA: SERVE PARA COLETAR INFORMAÇÕES E PERCEPÇÕES PARA MELHORAR O AMBIENTE ORGANIZACIONAL COM PERGUNTAS DIRETAS SOBRE O PONTO DE VISTA DO EX-FUNCIONÁRIO
C7: COMO CONDUZIR O ROTEIRO DA ENTREVISTA: SEJA UM BOM OUVINTE E PERMITA QUE SE EXPRESSE LIVREMENTE, SEM INTERRUPÇÕES E SEM FICAR NA DEFENSIVA, MAS FILTRE AS OPINIÕES, POIS A PESSOA PODE ESTAR ABALADA.
B8: 1 | C8: Qual motivo fez você pedir demissão? (em caso de demissão voluntária);
B9: 2 | C9: Existem outros fatores que contribuíram para a sua decisão?
B10: 3 | C10: O que você acha que a empresa poderia ter feito para evitar a situação?
B11: 4 | C11: Em quais pontos você acredita que a empresa precisa melhorar?
B12: 5 | C12: O que você gostaria de saber no início da sua jornada na empresa?
B13: 6 | C13: Você recomendaria nossa organização para outras pessoas?
B14: 7 | C14: Qual a sua opinião sobre o ambiente de trabalho e a infraestrutura da empresa?
B15: 8 | C15: Você acha que a empresa ofereceu oportunidades para você se desenvolver profissionalmente?
B16: 9 | C16: Quais foram os pontos positivos e negativos em sua trajetória na empresa?
B17: 10 | C17: Você se sentia reconhecido profissionalmente?
B18: 11 | C18: Qual a sua opinião sobre a política salarial e o pacote de benefícios oferecido?
B19: 12 | C19: Como era o seu relacionamento com líderes e colegas?
... B29: 22 | C29: Você tem mais alguma crítica, comentário ou sugestão que não foi abordada nas perguntas anteriores?
B30: FIM

Sheet 5.1
B2: < CLIQUE AQUI E VOLTE AO PAINEL INICIAL | C2: GESTÃO MATRICIAL DE DESPESAS | H2: ALTERE O PRIMEIRO MÊS E TODOS OS MESES ATUALIZAÇÃO AUTOMATICAMENTE → | K2: 45658 | O2: =DATE(YEAR(K2),MONTH(K2)+1,DAY(K2)) -> 45689 | S2: =DATE(YEAR(O2),MONTH(O2)+1,DAY(O2)) -> 45717 | W2: =DATE(YEAR(S2),MONTH(S2)+1,DAY(S2)) -> 45748 | AA2: =DATE(YEAR(W2),MONTH(W2)+1,DAY(W2)) -> 45778 | AE2: =DATE(YEAR(AA2),MONTH(AA2)+1,DAY(AA2)) -> 45809 | AI2: =DATE(YEAR(AE2),MONTH(AE2)+1,DAY(AE2)) -> 45839 | AM2: =DATE(YEAR(AI2),MONTH(AI2)+1,DAY(AI2)) -> 45870 | AQ2: =DATE(YEAR(AM2),MONTH(AM2)+1,DAY(AM2)) -> 45901 | AU2: =DATE(YEAR(AQ2),MONTH(AQ2)+1,DAY(AQ2)) -> 45931 | AY2: =DATE(YEAR(AU2),MONTH(AU2)+1,DAY(AU2)) -> 45962 | BC2: =DATE(YEAR(AY2),MONTH(AY2)+1,DAY(AY2)) -> 45992 | BG2: ACUMULADO
B3: SOMATÓRIO TOTAL DAS LINHAS → | D3: =SUM(D6:D25) -> 1150000 | H3: # | I3: NOME DO PRODUTO/SERVIÇO | J3: MÉDIA HISTÓRICA MENSAL | K3: META | L3: REAL | M3: DESVIO ABS. | N3: DESVIO % | O3: META | P3: REAL | Q3: DESVIO ABS. | R3: DESVIO % | S3: META | T3: REAL | U3: DESVIO ABS. | V3: DESVIO % | W3: META | X3: REAL | Y3: DESVIO ABS. | Z3: DESVIO % | AA3: META | AB3: REAL | AC3: DESVIO ABS. | AD3: DESVIO % | AE3: META | AF3: REAL | AG3: DESVIO ABS. | AH3: DESVIO % | AI3: META | AJ3: REAL | AK3: DESVIO ABS. | AL3: DESVIO % | AM3: META | AN3: REAL | AO3: DESVIO ABS. | AP3: DESVIO % | AQ3: META | AR3: REAL | AS3: DESVIO ABS. | AT3: DESVIO % | AU3: META | AV3: REAL | AW3: DESVIO ABS. | AX3: DESVIO % | AY3: META | AZ3: REAL | BA3: DESVIO ABS. | BB3: DESVIO % | BC3: META | BD3: REAL | BE3: DESVIO ABS. | BF3: DESVIO % | BG3: META | BH3: REAL | BI3: DESVIO ABS. | BJ3: DESVIO %
B5: # | C5: NOME DA DESPESA | D5: MÉDIA HISTÓRICA MENSAL | E5: REPRESENTATIVIDADE DA DESPESA NO VALOR TOTAL | F5: REPRESENTATIVIDADE DA DESPESA ACUMULADA | H5: 1 | I5: NOME DA DESPESA | J5: 100000 | K5: 100000 | L5: 95000 | M5: =IF(AND(K5="",L5=""),"-",L5-K5) -> -5000 | N5: =IFERROR((L5/K5)-1,"-") -> -0.05 | Q5: =IF(AND(O5="",P5=""),"-",P5-O5) -> - | R5: =IFERROR((P5/O5)-1,"-") -> - | U5: =IF(AND(S5="",T5=""),"-",T5-S5) -> - | V5: =IFERROR((T5/S5)-1,"-") -> - | Y5: =IF(AND(W5="",X5=""),"-",X5-W5) -> - | Z5: =IFERROR((X5/W5)-1,"-") -> - | AC5: =IF(AND(AA5="",AB5=""),"-",AB5-AA5) -> - | AD5: =IFERROR((AB5/AA5)-1,"-") -> - | AG5: =IF(AND(AE5="",AF5=""),"-",AF5-AE5) -> - | AH5: =IFERROR((AF5/AE5)-1,"-") -> - | AK5: =IF(AND(AI5="",AJ5=""),"-",AJ5-AI5) -> - | AL5: =IFERROR((AJ5/AI5)-1,"-") -> - | AO5: =IF(AND(AM5="",AN5=""),"-",AN5-AM5) -> - | AP5: =IFERROR((AN5/AM5)-1,"-") -> - | AS5: =IF(AND(AQ5="",AR5=""),"-",AR5-AQ5) -> - | AT5: =IFERROR((AR5/AQ5)-1,"-") -> - | AW5: =IF(AND(AU5="",AV5=""),"-",AV5-AU5) -> - | AX5: =IFERROR((AV5/AU5)-1,"-") -> - | BA5: =IF(AND(AY5="",AZ5=""),"-",AZ5-AY5) -> - | BB5: =IFERROR((AZ5/AY5)-1,"-") -> - | BE5: =IF(AND(BC5="",BD5=""),"-",BD5-BC5) -> - | BF5: =IFERROR((BD5/BC5)-1,"-") -> - | BG5: =BC5+AY5+AU5+AQ5+AM5+AI5+AE5+AA5+W5+S5+O5+K5 -> 100000 | BH5: =BD5+AZ5+AV5+AR5+AN5+AJ5+AF5+AB5+X5+T5+P5+L5 -> 95000 | BI5: =IF(AND(BG5="",BH5=""),"-",BH5-BG5) -> -5000 | BJ5: =IFERROR((BH5/BG5)-1,"-") -> -0.05
B6: 1 | C6: NOME DA DESPESA | D6: 200000 | E6: =D6/$D$3 -> 0.17391304 | F6: =E6 -> 0.17391304 | H6: 2 | I6: NOME DA DESPESA | J6: 10000 | K6: 10000 | L6: 12000 | M6: =IF(AND(K6="",L6=""),"-",L6-K6) -> 2000 | N6: =IFERROR((L6/K6)-1,"-") -> 0.2 | Q6: =IF(AND(O6="",P6=""),"-",P6-O6) -> - | R6: =IFERROR((P6/O6)-1,"-") -> - | U6: =IF(AND(S6="",T6=""),"-",T6-S6) -> - | V6: =IFERROR((T6/S6)-1,"-") -> - | Y6: =IF(AND(W6="",X6=""),"-",X6-W6) -> - | Z6: =IFERROR((X6/W6)-1,"-") -> - | AC6: =IF(AND(AA6="",AB6=""),"-",AB6-AA6) -> - | AD6: =IFERROR((AB6/AA6)-1,"-") -> - | AG6: =IF(AND(AE6="",AF6=""),"-",AF6-AE6) -> - | AH6: =IFERROR((AF6/AE6)-1,"-") -> - | AK6: =IF(AND(AI6="",AJ6=""),"-",AJ6-AI6) -> - | AL6: =IFERROR((AJ6/AI6)-1,"-") -> - | AO6: =IF(AND(AM6="",AN6=""),"-",AN6-AM6) -> - | AP6: =IFERROR((AN6/AM6)-1,"-") -> - | AS6: =IF(AND(AQ6="",AR6=""),"-",AR6-AQ6) -> - | AT6: =IFERROR((AR6/AQ6)-1,"-") -> - | AW6: =IF(AND(AU6="",AV6=""),"-",AV6-AU6) -> - | AX6: =IFERROR((AV6/AU6)-1,"-") -> - | BA6: =IF(AND(AY6="",AZ6=""),"-",AZ6-AY6) -> - | BB6: =IFERROR((AZ6/AY6)-1,"-") -> - | BE6: =IF(AND(BC6="",BD6=""),"-",BD6-BC6) -> - | BF6: =IFERROR((BD6/BC6)-1,"-") -> - | BG6: =BC6+AY6+AU6+AQ6+AM6+AI6+AE6+AA6+W6+S6+O6+K6 -> 10000 | BH6: =BD6+AZ6+AV6+AR6+AN6+AJ6+AF6+AB6+X6+T6+P6+L6 -> 12000 | BI6: =IF(AND(BG6="",BH6=""),"-",BH6-BG6) -> 2000 | BJ6: =IFERROR((BH6/BG6)-1,"-") -> 0.2
B7: 14 | C7: NOME DA DESPESA | D7: 100000 | E7: =D7/$D$3 -> 0.086956522 | F7: =E7+F6 -> 0.26086957 | H7: 3 | I7: NOME DA DESPESA | J7: 700 | K7: 700 | L7: 600 | M7: =IF(AND(K7="",L7=""),"-",L7-K7) -> -100 | N7: =IFERROR((L7/K7)-1,"-") -> -0.14285714 | Q7: =IF(AND(O7="",P7=""),"-",P7-O7) -> - | R7: =IFERROR((P7/O7)-1,"-") -> - | U7: =IF(AND(S7="",T7=""),"-",T7-S7) -> - | V7: =IFERROR((T7/S7)-1,"-") -> - | Y7: =IF(AND(W7="",X7=""),"-",X7-W7) -> - | Z7: =IFERROR((X7/W7)-1,"-") -> - | AC7: =IF(AND(AA7="",AB7=""),"-",AB7-AA7) -> - | AD7: =IFERROR((AB7/AA7)-1,"-") -> - | AG7: =IF(AND(AE7="",AF7=""),"-",AF7-AE7) -> - | AH7: =IFERROR((AF7/AE7)-1,"-") -> - | AK7: =IF(AND(AI7="",AJ7=""),"-",AJ7-AI7) -> - | AL7: =IFERROR((AJ7/AI7)-1,"-") -> - | AO7: =IF(AND(AM7="",AN7=""),"-",AN7-AM7) -> - | AP7: =IFERROR((AN7/AM7)-1,"-") -> - | AS7: =IF(AND(AQ7="",AR7=""),"-",AR7-AQ7) -> - | AT7: =IFERROR((AR7/AQ7)-1,"-") -> - | AW7: =IF(AND(AU7="",AV7=""),"-",AV7-AU7) -> - | AX7: =IFERROR((AV7/AU7)-1,"-") -> - | BA7: =IF(AND(AY7="",AZ7=""),"-",AZ7-AY7) -> - | BB7: =IFERROR((AZ7/AY7)-1,"-") -> - | BE7: =IF(AND(BC7="",BD7=""),"-",BD7-BC7) -> - | BF7: =IFERROR((BD7/BC7)-1,"-") -> - | BG7: =BC7+AY7+AU7+AQ7+AM7+AI7+AE7+AA7+W7+S7+O7+K7 -> 700 | BH7: =BD7+AZ7+AV7+AR7+AN7+AJ7+AF7+AB7+X7+T7+P7+L7 -> 600 | BI7: =IF(AND(BG7="",BH7=""),"-",BH7-BG7) -> -100 | BJ7: =IFERROR((BH7/BG7)-1,"-") -> -0.14285714
B8: 15 | C8: NOME DA DESPESA | D8: 100000 | E8: =D8/$D$3 -> 0.086956522 | F8: =E8+F7 -> 0.34782609 | H8: 4 | I8: NOME DA DESPESA | J8: 600 | K8: 600 | L8: 800 | M8: =IF(AND(K8="",L8=""),"-",L8-K8) -> 200 | N8: =IFERROR((L8/K8)-1,"-") -> 0.33333333 | Q8: =IF(AND(O8="",P8=""),"-",P8-O8) -> - | R8: =IFERROR((P8/O8)-1,"-") -> - | U8: =IF(AND(S8="",T8=""),"-",T8-S8) -> - | V8: =IFERROR((T8/S8)-1,"-") -> - | Y8: =IF(AND(W8="",X8=""),"-",X8-W8) -> - | Z8: =IFERROR((X8/W8)-1,"-") -> - | AC8: =IF(AND(AA8="",AB8=""),"-",AB8-AA8) -> - | AD8: =IFERROR((AB8/AA8)-1,"-") -> - | AG8: =IF(AND(AE8="",AF8=""),"-",AF8-AE8) -> - | AH8: =IFERROR((AF8/AE8)-1,"-") -> - | AK8: =IF(AND(AI8="",AJ8=""),"-",AJ8-AI8) -> - | AL8: =IFERROR((AJ8/AI8)-1,"-") -> - | AO8: =IF(AND(AM8="",AN8=""),"-",AN8-AM8) -> - | AP8: =IFERROR((AN8/AM8)-1,"-") -> - | AS8: =IF(AND(AQ8="",AR8=""),"-",AR8-AQ8) -> - | AT8: =IFERROR((AR8/AQ8)-1,"-") -> - | AW8: =IF(AND(AU8="",AV8=""),"-",AV8-AU8) -> - | AX8: =IFERROR((AV8/AU8)-1,"-") -> - | BA8: =IF(AND(AY8="",AZ8=""),"-",AZ8-AY8) -> - | BB8: =IFERROR((AZ8/AY8)-1,"-") -> - | BE8: =IF(AND(BC8="",BD8=""),"-",BD8-BC8) -> - | BF8: =IFERROR((BD8/BC8)-1,"-") -> - | BG8: =BC8+AY8+AU8+AQ8+AM8+AI8+AE8+AA8+W8+S8+O8+K8 -> 600 | BH8: =BD8+AZ8+AV8+AR8+AN8+AJ8+AF8+AB8+X8+T8+P8+L8 -> 800 | BI8: =IF(AND(BG8="",BH8=""),"-",BH8-BG8) -> 200 | BJ8: =IFERROR((BH8/BG8)-1,"-") -> 0.33333333
B9: 16 | C9: NOME DA DESPESA | D9: 100000 | E9: =D9/$D$3 -> 0.086956522 | F9: =E9+F8 -> 0.43478261 | H9: 5 | I9: NOME DA DESPESA | J9: 500 | K9: 500 | L9: 500 | M9: =IF(AND(K9="",L9=""),"-",L9-K9) -> 0 | N9: =IFERROR((L9/K9)-1,"-") -> 0 | Q9: =IF(AND(O9="",P9=""),"-",P9-O9) -> - | R9: =IFERROR((P9/O9)-1,"-") -> - | U9: =IF(AND(S9="",T9=""),"-",T9-S9) -> - | V9: =IFERROR((T9/S9)-1,"-") -> - | Y9: =IF(AND(W9="",X9=""),"-",X9-W9) -> - | Z9: =IFERROR((X9/W9)-1,"-") -> - | AC9: =IF(AND(AA9="",AB9=""),"-",AB9-AA9) -> - | AD9: =IFERROR((AB9/AA9)-1,"-") -> - | AG9: =IF(AND(AE9="",AF9=""),"-",AF9-AE9) -> - | AH9: =IFERROR((AF9/AE9)-1,"-") -> - | AK9: =IF(AND(AI9="",AJ9=""),"-",AJ9-AI9) -> - | AL9: =IFERROR((AJ9/AI9)-1,"-") -> - | AO9: =IF(AND(AM9="",AN9=""),"-",AN9-AM9) -> - | AP9: =IFERROR((AN9/AM9)-1,"-") -> - | AS9: =IF(AND(AQ9="",AR9=""),"-",AR9-AQ9) -> - | AT9: =IFERROR((AR9/AQ9)-1,"-") -> - | AW9: =IF(AND(AU9="",AV9=""),"-",AV9-AU9) -> - | AX9: =IFERROR((AV9/AU9)-1,"-") -> - | BA9: =IF(AND(AY9="",AZ9=""),"-",AZ9-AY9) -> - | BB9: =IFERROR((AZ9/AY9)-1,"-") -> - | BE9: =IF(AND(BC9="",BD9=""),"-",BD9-BC9) -> - | BF9: =IFERROR((BD9/BC9)-1,"-") -> - | BG9: =BC9+AY9+AU9+AQ9+AM9+AI9+AE9+AA9+W9+S9+O9+K9 -> 500 | BH9: =BD9+AZ9+AV9+AR9+AN9+AJ9+AF9+AB9+X9+T9+P9+L9 -> 500 | BI9: =IF(AND(BG9="",BH9=""),"-",BH9-BG9) -> 0 | BJ9: =IFERROR((BH9/BG9)-1,"-") -> 0
B10: 17 | C10: NOME DA DESPESA | D10: 100000 | E10: =D10/$D$3 -> 0.086956522 | F10: =E10+F9 -> 0.52173913 | H10: 6 | I10: NOME DA DESPESA | J10: 300 | K10: 300 | L10: 350 | M10: =IF(AND(K10="",L10=""),"-",L10-K10) -> 50 | N10: =IFERROR((L10/K10)-1,"-") -> 0.16666667 | Q10: =IF(AND(O10="",P10=""),"-",P10-O10) -> - | R10: =IFERROR((P10/O10)-1,"-") -> - | U10: =IF(AND(S10="",T10=""),"-",T10-S10) -> - | V10: =IFERROR((T10/S10)-1,"-") -> - | Y10: =IF(AND(W10="",X10=""),"-",X10-W10) -> - | Z10: =IFERROR((X10/W10)-1,"-") -> - | AC10: =IF(AND(AA10="",AB10=""),"-",AB10-AA10) -> - | AD10: =IFERROR((AB10/AA10)-1,"-") -> - | AG10: =IF(AND(AE10="",AF10=""),"-",AF10-AE10) -> - | AH10: =IFERROR((AF10/AE10)-1,"-") -> - | AK10: =IF(AND(AI10="",AJ10=""),"-",AJ10-AI10) -> - | AL10: =IFERROR((AJ10/AI10)-1,"-") -> - | AO10: =IF(AND(AM10="",AN10=""),"-",AN10-AM10) -> - | AP10: =IFERROR((AN10/AM10)-1,"-") -> - | AS10: =IF(AND(AQ10="",AR10=""),"-",AR10-AQ10) -> - | AT10: =IFERROR((AR10/AQ10)-1,"-") -> - | AW10: =IF(AND(AU10="",AV10=""),"-",AV10-AU10) -> - | AX10: =IFERROR((AV10/AU10)-1,"-") -> - | BA10: =IF(AND(AY10="",AZ10=""),"-",AZ10-AY10) -> - | BB10: =IFERROR((AZ10/AY10)-1,"-") -> - | BE10: =IF(AND(BC10="",BD10=""),"-",BD10-BC10) -> - | BF10: =IFERROR((BD10/BC10)-1,"-") -> - | BG10: =BC10+AY10+AU10+AQ10+AM10+AI10+AE10+AA10+W10+S10+O10+K10 -> 300 | BH10: =BD10+AZ10+AV10+AR10+AN10+AJ10+AF10+AB10+X10+T10+P10+L10 -> 350 | BI10: =IF(AND(BG10="",BH10=""),"-",BH10-BG10) -> 50 | BJ10: =IFERROR((BH10/BG10)-1,"-") -> 0.16666667
B11: 18 | C11: NOME DA DESPESA | D11: 100000 | E11: =D11/$D$3 -> 0.086956522 | F11: =E11+F10 -> 0.60869565 | H11: 7 | I11: NOME DA DESPESA | J11: 450 | K11: 500 | L11: 450 | M11: =IF(AND(K11="",L11=""),"-",L11-K11) -> -50 | N11: =IFERROR((L11/K11)-1,"-") -> -0.1 | Q11: =IF(AND(O11="",P11=""),"-",P11-O11) -> - | R11: =IFERROR((P11/O11)-1,"-") -> - | U11: =IF(AND(S11="",T11=""),"-",T11-S11) -> - | V11: =IFERROR((T11/S11)-1,"-") -> - | Y11: =IF(AND(W11="",X11=""),"-",X11-W11) -> - | Z11: =IFERROR((X11/W11)-1,"-") -> - | AC11: =IF(AND(AA11="",AB11=""),"-",AB11-AA11) -> - | AD11: =IFERROR((AB11/AA11)-1,"-") -> - | AG11: =IF(AND(AE11="",AF11=""),"-",AF11-AE11) -> - | AH11: =IFERROR((AF11/AE11)-1,"-") -> - | AK11: =IF(AND(AI11="",AJ11=""),"-",AJ11-AI11) -> - | AL11: =IFERROR((AJ11/AI11)-1,"-") -> - | AO11: =IF(AND(AM11="",AN11=""),"-",AN11-AM11) -> - | AP11: =IFERROR((AN11/AM11)-1,"-") -> - | AS11: =IF(AND(AQ11="",AR11=""),"-",AR11-AQ11) -> - | AT11: =IFERROR((AR11/AQ11)-1,"-") -> - | AW11: =IF(AND(AU11="",AV11=""),"-",AV11-AU11) -> - | AX11: =IFERROR((AV11/AU11)-1,"-") -> - | BA11: =IF(AND(AY11="",AZ11=""),"-",AZ11-AY11) -> - | BB11: =IFERROR((AZ11/AY11)-1,"-") -> - | BE11: =IF(AND(BC11="",BD11=""),"-",BD11-BC11) -> - | BF11: =IFERROR((BD11/BC11)-1,"-") -> - | BG11: =BC11+AY11+AU11+AQ11+AM11+AI11+AE11+AA11+W11+S11+O11+K11 -> 500 | BH11: =BD11+AZ11+AV11+AR11+AN11+AJ11+AF11+AB11+X11+T11+P11+L11 -> 450 | BI11: =IF(AND(BG11="",BH11=""),"-",BH11-BG11) -> -50 | BJ11: =IFERROR((BH11/BG11)-1,"-") -> -0.1
B12: 19 | C12: NOME DA DESPESA | D12: 100000 | E12: =D12/$D$3 -> 0.086956522 | F12: =E12+F11 -> 0.69565217 | H12: 8 | I12: NOME DA DESPESA | J12: 10000 | M12: =IF(AND(K12="",L12=""),"-",L12-K12) -> - | N12: =IFERROR((L12/K12)-1,"-") -> - | Q12: =IF(AND(O12="",P12=""),"-",P12-O12) -> - | R12: =IFERROR((P12/O12)-1,"-") -> - | U12: =IF(AND(S12="",T12=""),"-",T12-S12) -> - | V12: =IFERROR((T12/S12)-1,"-") -> - | Y12: =IF(AND(W12="",X12=""),"-",X12-W12) -> - | Z12: =IFERROR((X12/W12)-1,"-") -> - | AC12: =IF(AND(AA12="",AB12=""),"-",AB12-AA12) -> - | AD12: =IFERROR((AB12/AA12)-1,"-") -> - | AG12: =IF(AND(AE12="",AF12=""),"-",AF12-AE12) -> - | AH12: =IFERROR((AF12/AE12)-1,"-") -> - | AK12: =IF(AND(AI12="",AJ12=""),"-",AJ12-AI12) -> - | AL12: =IFERROR((AJ12/AI12)-1,"-") -> - | AO12: =IF(AND(AM12="",AN12=""),"-",AN12-AM12) -> - | AP12: =IFERROR((AN12/AM12)-1,"-") -> - | AS12: =IF(AND(AQ12="",AR12=""),"-",AR12-AQ12) -> - | AT12: =IFERROR((AR12/AQ12)-1,"-") -> - | AW12: =IF(AND(AU12="",AV12=""),"-",AV12-AU12) -> - | AX12: =IFERROR((AV12/AU12)-1,"-") -> - | BA12: =IF(AND(AY12="",AZ12=""),"-",AZ12-AY12) -> - | BB12: =IFERROR((AZ12/AY12)-1,"-") -> - | BE12: =IF(AND(BC12="",BD12=""),"-",BD12-BC12) -> - | BF12: =IFERROR((BD12/BC12)-1,"-") -> - | BG12: =BC12+AY12+AU12+AQ12+AM12+AI12+AE12+AA12+W12+S12+O12+K12 -> 0 | BH12: =BD12+AZ12+AV12+AR12+AN12+AJ12+AF12+AB12+X12+T12+P12+L12 -> 0 | BI12: =IF(AND(BG12="",BH12=""),"-",BH12-BG12) -> 0 | BJ12: =IFERROR((BH12/BG12)-1,"-") -> -
B13: 20 | C13: NOME DA DESPESA | D13: 100000 | E13: =D13/$D$3 -> 0.086956522 | F13: =E13+F12 -> 0.7826087 | H13: 9 | I13: NOME DA DESPESA | J13: 10000 | M13: =IF(AND(K13="",L13=""),"-",L13-K13) -> - | N13: =IFERROR((L13/K13)-1,"-") -> - | Q13: =IF(AND(O13="",P13=""),"-",P13-O13) -> - | R13: =IFERROR((P13/O13)-1,"-") -> - | U13: =IF(AND(S13="",T13=""),"-",T13-S13) -> - | V13: =IFERROR((T13/S13)-1,"-") -> - | Y13: =IF(AND(W13="",X13=""),"-",X13-W13) -> - | Z13: =IFERROR((X13/W13)-1,"-") -> - | AC13: =IF(AND(AA13="",AB13=""),"-",AB13-AA13) -> - | AD13: =IFERROR((AB13/AA13)-1,"-") -> - | AG13: =IF(AND(AE13="",AF13=""),"-",AF13-AE13) -> - | AH13: =IFERROR((AF13/AE13)-1,"-") -> - | AK13: =IF(AND(AI13="",AJ13=""),"-",AJ13-AI13) -> - | AL13: =IFERROR((AJ13/AI13)-1,"-") -> - | AO13: =IF(AND(AM13="",AN13=""),"-",AN13-AM13) -> - | AP13: =IFERROR((AN13/AM13)-1,"-") -> - | AS13: =IF(AND(AQ13="",AR13=""),"-",AR13-AQ13) -> - | AT13: =IFERROR((AR13/AQ13)-1,"-") -> - | AW13: =IF(AND(AU13="",AV13=""),"-",AV13-AU13) -> - | AX13: =IFERROR((AV13/AU13)-1,"-") -> - | BA13: =IF(AND(AY13="",AZ13=""),"-",AZ13-AY13) -> - | BB13: =IFERROR((AZ13/AY13)-1,"-") -> - | BE13: =IF(AND(BC13="",BD13=""),"-",BD13-BC13) -> - | BF13: =IFERROR((BD13/BC13)-1,"-") -> - | BG13: =BC13+AY13+AU13+AQ13+AM13+AI13+AE13+AA13+W13+S13+O13+K13 -> 0 | BH13: =BD13+AZ13+AV13+AR13+AN13+AJ13+AF13+AB13+X13+T13+P13+L13 -> 0 | BI13: =IF(AND(BG13="",BH13=""),"-",BH13-BG13) -> 0 | BJ13: =IFERROR((BH13/BG13)-1,"-") -> -
B14: 2 | C14: NOME DA DESPESA | D14: 60000 | E14: =D14/$D$3 -> 0.052173913 | F14: =E14+F13 -> 0.83478261 | H14: 10 | I14: NOME DA DESPESA | J14: 10000 | M14: =IF(AND(K14="",L14=""),"-",L14-K14) -> - | N14: =IFERROR((L14/K14)-1,"-") -> - | Q14: =IF(AND(O14="",P14=""),"-",P14-O14) -> - | R14: =IFERROR((P14/O14)-1,"-") -> - | U14: =IF(AND(S14="",T14=""),"-",T14-S14) -> - | V14: =IFERROR((T14/S14)-1,"-") -> - | Y14: =IF(AND(W14="",X14=""),"-",X14-W14) -> - | Z14: =IFERROR((X14/W14)-1,"-") -> - | AC14: =IF(AND(AA14="",AB14=""),"-",AB14-AA14) -> - | AD14: =IFERROR((AB14/AA14)-1,"-") -> - | AG14: =IF(AND(AE14="",AF14=""),"-",AF14-AE14) -> - | AH14: =IFERROR((AF14/AE14)-1,"-") -> - | AK14: =IF(AND(AI14="",AJ14=""),"-",AJ14-AI14) -> - | AL14: =IFERROR((AJ14/AI14)-1,"-") -> - | AO14: =IF(AND(AM14="",AN14=""),"-",AN14-AM14) -> - | AP14: =IFERROR((AN14/AM14)-1,"-") -> - | AS14: =IF(AND(AQ14="",AR14=""),"-",AR14-AQ14) -> - | AT14: =IFERROR((AR14/AQ14)-1,"-") -> - | AW14: =IF(AND(AU14="",AV14=""),"-",AV14-AU14) -> - | AX14: =IFERROR((AV14/AU14)-1,"-") -> - | BA14: =IF(AND(AY14="",AZ14=""),"-",AZ14-AY14) -> - | BB14: =IFERROR((AZ14/AY14)-1,"-") -> - | BE14: =IF(AND(BC14="",BD14=""),"-",BD14-BC14) -> - | BF14: =IFERROR((BD14/BC14)-1,"-") -> - | BG14: =BC14+AY14+AU14+AQ14+AM14+AI14+AE14+AA14+W14+S14+O14+K14 -> 0 | BH14: =BD14+AZ14+AV14+AR14+AN14+AJ14+AF14+AB14+X14+T14+P14+L14 -> 0 | BI14: =IF(AND(BG14="",BH14=""),"-",BH14-BG14) -> 0 | BJ14: =IFERROR((BH14/BG14)-1,"-") -> -
B15: 3 | C15: NOME DA DESPESA | D15: 35000 | E15: =D15/$D$3 -> 0.030434783 | F15: =E15+F14 -> 0.86521739 | H15: 11 | I15: NOME DA DESPESA | M15: =IF(AND(K15="",L15=""),"-",L15-K15) -> - | N15: =IFERROR((L15/K15)-1,"-") -> - | Q15: =IF(AND(O15="",P15=""),"-",P15-O15) -> - | R15: =IFERROR((P15/O15)-1,"-") -> - | U15: =IF(AND(S15="",T15=""),"-",T15-S15) -> - | V15: =IFERROR((T15/S15)-1,"-") -> - | Y15: =IF(AND(W15="",X15=""),"-",X15-W15) -> - | Z15: =IFERROR((X15/W15)-1,"-") -> - | AC15: =IF(AND(AA15="",AB15=""),"-",AB15-AA15) -> - | AD15: =IFERROR((AB15/AA15)-1,"-") -> - | AG15: =IF(AND(AE15="",AF15=""),"-",AF15-AE15) -> - | AH15: =IFERROR((AF15/AE15)-1,"-") -> - | AK15: =IF(AND(AI15="",AJ15=""),"-",AJ15-AI15) -> - | AL15: =IFERROR((AJ15/AI15)-1,"-") -> - | AO15: =IF(AND(AM15="",AN15=""),"-",AN15-AM15) -> - | AP15: =IFERROR((AN15/AM15)-1,"-") -> - | AS15: =IF(AND(AQ15="",AR15=""),"-",AR15-AQ15) -> - | AT15: =IFERROR((AR15/AQ15)-1,"-") -> - | AW15: =IF(AND(AU15="",AV15=""),"-",AV15-AU15) -> - | AX15: =IFERROR((AV15/AU15)-1,"-") -> - | BA15: =IF(AND(AY15="",AZ15=""),"-",AZ15-AY15) -> - | BB15: =IFERROR((AZ15/AY15)-1,"-") -> - | BE15: =IF(AND(BC15="",BD15=""),"-",BD15-BC15) -> - | BF15: =IFERROR((BD15/BC15)-1,"-") -> - | BG15: =BC15+AY15+AU15+AQ15+AM15+AI15+AE15+AA15+W15+S15+O15+K15 -> 0 | BH15: =BD15+AZ15+AV15+AR15+AN15+AJ15+AF15+AB15+X15+T15+P15+L15 -> 0 | BI15: =IF(AND(BG15="",BH15=""),"-",BH15-BG15) -> 0 | BJ15: =IFERROR((BH15/BG15)-1,"-") -> -
B16: 4 | C16: NOME DA DESPESA | D16: 30000 | E16: =D16/$D$3 -> 0.026086957 | F16: =E16+F15 -> 0.89130435 | H16: 12 | I16: NOME DA DESPESA | M16: =IF(AND(K16="",L16=""),"-",L16-K16) -> - | N16: =IFERROR((L16/K16)-1,"-") -> - | Q16: =IF(AND(O16="",P16=""),"-",P16-O16) -> - | R16: =IFERROR((P16/O16)-1,"-") -> - | U16: =IF(AND(S16="",T16=""),"-",T16-S16) -> - | V16: =IFERROR((T16/S16)-1,"-") -> - | Y16: =IF(AND(W16="",X16=""),"-",X16-W16) -> - | Z16: =IFERROR((X16/W16)-1,"-") -> - | AC16: =IF(AND(AA16="",AB16=""),"-",AB16-AA16) -> - | AD16: =IFERROR((AB16/AA16)-1,"-") -> - | AG16: =IF(AND(AE16="",AF16=""),"-",AF16-AE16) -> - | AH16: =IFERROR((AF16/AE16)-1,"-") -> - | AK16: =IF(AND(AI16="",AJ16=""),"-",AJ16-AI16) -> - | AL16: =IFERROR((AJ16/AI16)-1,"-") -> - | AO16: =IF(AND(AM16="",AN16=""),"-",AN16-AM16) -> - | AP16: =IFERROR((AN16/AM16)-1,"-") -> - | AS16: =IF(AND(AQ16="",AR16=""),"-",AR16-AQ16) -> - | AT16: =IFERROR((AR16/AQ16)-1,"-") -> - | AW16: =IF(AND(AU16="",AV16=""),"-",AV16-AU16) -> - | AX16: =IFERROR((AV16/AU16)-1,"-") -> - | BA16: =IF(AND(AY16="",AZ16=""),"-",AZ16-AY16) -> - | BB16: =IFERROR((AZ16/AY16)-1,"-") -> - | BE16: =IF(AND(BC16="",BD16=""),"-",BD16-BC16) -> - | BF16: =IFERROR((BD16/BC16)-1,"-") -> - | BG16: =BC16+AY16+AU16+AQ16+AM16+AI16+AE16+AA16+W16+S16+O16+K16 -> 0 | BH16: =BD16+AZ16+AV16+AR16+AN16+AJ16+AF16+AB16+X16+T16+P16+L16 -> 0 | BI16: =IF(AND(BG16="",BH16=""),"-",BH16-BG16) -> 0 | BJ16: =IFERROR((BH16/BG16)-1,"-") -> -
B17: 5 | C17: NOME DA DESPESA | D17: 30000 | E17: =D17/$D$3 -> 0.026086957 | F17: =E17+F16 -> 0.9173913 | H17: 13 | I17: NOME DA DESPESA | M17: =IF(AND(K17="",L17=""),"-",L17-K17) -> - | N17: =IFERROR((L17/K17)-1,"-") -> - | Q17: =IF(AND(O17="",P17=""),"-",P17-O17) -> - | R17: =IFERROR((P17/O17)-1,"-") -> - | U17: =IF(AND(S17="",T17=""),"-",T17-S17) -> - | V17: =IFERROR((T17/S17)-1,"-") -> - | Y17: =IF(AND(W17="",X17=""),"-",X17-W17) -> - | Z17: =IFERROR((X17/W17)-1,"-") -> - | AC17: =IF(AND(AA17="",AB17=""),"-",AB17-AA17) -> - | AD17: =IFERROR((AB17/AA17)-1,"-") -> - | AG17: =IF(AND(AE17="",AF17=""),"-",AF17-AE17) -> - | AH17: =IFERROR((AF17/AE17)-1,"-") -> - | AK17: =IF(AND(AI17="",AJ17=""),"-",AJ17-AI17) -> - | AL17: =IFERROR((AJ17/AI17)-1,"-") -> - | AO17: =IF(AND(AM17="",AN17=""),"-",AN17-AM17) -> - | AP17: =IFERROR((AN17/AM17)-1,"-") -> - | AS17: =IF(AND(AQ17="",AR17=""),"-",AR17-AQ17) -> - | AT17: =IFERROR((AR17/AQ17)-1,"-") -> - | AW17: =IF(AND(AU17="",AV17=""),"-",AV17-AU17) -> - | AX17: =IFERROR((AV17/AU17)-1,"-") -> - | BA17: =IF(AND(AY17="",AZ17=""),"-",AZ17-AY17) -> - | BB17: =IFERROR((AZ17/AY17)-1,"-") -> - | BE17: =IF(AND(BC17="",BD17=""),"-",BD17-BC17) -> - | BF17: =IFERROR((BD17/BC17)-1,"-") -> - | BG17: =BC17+AY17+AU17+AQ17+AM17+AI17+AE17+AA17+W17+S17+O17+K17 -> 0 | BH17: =BD17+AZ17+AV17+AR17+AN17+AJ17+AF17+AB17+X17+T17+P17+L17 -> 0 | BI17: =IF(AND(BG17="",BH17=""),"-",BH17-BG17) -> 0 | BJ17: =IFERROR((BH17/BG17)-1,"-") -> -
B18: 6 | C18: NOME DA DESPESA | D18: 20000 | E18: =D18/$D$3 -> 0.017391304 | F18: =E18+F17 -> 0.93478261 | H18: 14 | I18: NOME DA DESPESA | J18: 100000 | K18: 120000 | L18: 123000 | M18: =IF(AND(K18="",L18=""),"-",L18-K18) -> 3000 | N18: =IFERROR((L18/K18)-1,"-") -> 0.025 | Q18: =IF(AND(O18="",P18=""),"-",P18-O18) -> - | R18: =IFERROR((P18/O18)-1,"-") -> - | U18: =IF(AND(S18="",T18=""),"-",T18-S18) -> - | V18: =IFERROR((T18/S18)-1,"-") -> - | Y18: =IF(AND(W18="",X18=""),"-",X18-W18) -> - | Z18: =IFERROR((X18/W18)-1,"-") -> - | AC18: =IF(AND(AA18="",AB18=""),"-",AB18-AA18) -> - | AD18: =IFERROR((AB18/AA18)-1,"-") -> - | AG18: =IF(AND(AE18="",AF18=""),"-",AF18-AE18) -> - | AH18: =IFERROR((AF18/AE18)-1,"-") -> - | AK18: =IF(AND(AI18="",AJ18=""),"-",AJ18-AI18) -> - | AL18: =IFERROR((AJ18/AI18)-1,"-") -> - | AO18: =IF(AND(AM18="",AN18=""),"-",AN18-AM18) -> - | AP18: =IFERROR((AN18/AM18)-1,"-") -> - | AS18: =IF(AND(AQ18="",AR18=""),"-",AR18-AQ18) -> - | AT18: =IFERROR((AR18/AQ18)-1,"-") -> - | AW18: =IF(AND(AU18="",AV18=""),"-",AV18-AU18) -> - | AX18: =IFERROR((AV18/AU18)-1,"-") -> - | BA18: =IF(AND(AY18="",AZ18=""),"-",AZ18-AY18) -> - | BB18: =IFERROR((AZ18/AY18)-1,"-") -> - | BE18: =IF(AND(BC18="",BD18=""),"-",BD18-BC18) -> - | BF18: =IFERROR((BD18/BC18)-1,"-") -> - | BG18: =BC18+AY18+AU18+AQ18+AM18+AI18+AE18+AA18+W18+S18+O18+K18 -> 120000 | BH18: =BD18+AZ18+AV18+AR18+AN18+AJ18+AF18+AB18+X18+T18+P18+L18 -> 123000 | BI18: =IF(AND(BG18="",BH18=""),"-",BH18-BG18) -> 3000 | BJ18: =IFERROR((BH18/BG18)-1,"-") -> 0.025
B19: 7 | C19: NOME DA DESPESA | D19: 20000 | E19: =D19/$D$3 -> 0.017391304 | F19: =E19+F18 -> 0.95217391 | H19: 15 | I19: NOME DA DESPESA | M19: =IF(AND(K19="",L19=""),"-",L19-K19) -> - | N19: =IFERROR((L19/K19)-1,"-") -> - | Q19: =IF(AND(O19="",P19=""),"-",P19-O19) -> - | R19: =IFERROR((P19/O19)-1,"-") -> - | U19: =IF(AND(S19="",T19=""),"-",T19-S19) -> - | V19: =IFERROR((T19/S19)-1,"-") -> - | Y19: =IF(AND(W19="",X19=""),"-",X19-W19) -> - | Z19: =IFERROR((X19/W19)-1,"-") -> - | AC19: =IF(AND(AA19="",AB19=""),"-",AB19-AA19) -> - | AD19: =IFERROR((AB19/AA19)-1,"-") -> - | AG19: =IF(AND(AE19="",AF19=""),"-",AF19-AE19) -> - | AH19: =IFERROR((AF19/AE19)-1,"-") -> - | AK19: =IF(AND(AI19="",AJ19=""),"-",AJ19-AI19) -> - | AL19: =IFERROR((AJ19/AI19)-1,"-") -> - | AO19: =IF(AND(AM19="",AN19=""),"-",AN19-AM19) -> - | AP19: =IFERROR((AN19/AM19)-1,"-") -> - | AS19: =IF(AND(AQ19="",AR19=""),"-",AR19-AQ19) -> - | AT19: =IFERROR((AR19/AQ19)-1,"-") -> - | AW19: =IF(AND(AU19="",AV19=""),"-",AV19-AU19) -> - | AX19: =IFERROR((AV19/AU19)-1,"-") -> - | BA19: =IF(AND(AY19="",AZ19=""),"-",AZ19-AY19) -> - | BB19: =IFERROR((AZ19/AY19)-1,"-") -> - | BE19: =IF(AND(BC19="",BD19=""),"-",BD19-BC19) -> - | BF19: =IFERROR((BD19/BC19)-1,"-") -> - | BG19: =BC19+AY19+AU19+AQ19+AM19+AI19+AE19+AA19+W19+S19+O19+K19 -> 0 | BH19: =BD19+AZ19+AV19+AR19+AN19+AJ19+AF19+AB19+X19+T19+P19+L19 -> 0 | BI19: =IF(AND(BG19="",BH19=""),"-",BH19-BG19) -> 0 | BJ19: =IFERROR((BH19/BG19)-1,"-") -> -
B20: 8 | C20: NOME DA DESPESA | D20: 20000 | E20: =D20/$D$3 -> 0.017391304 | F20: =E20+F19 -> 0.96956522 | H20: 16 | I20: NOME DA DESPESA | M20: =IF(AND(K20="",L20=""),"-",L20-K20) -> - | N20: =IFERROR((L20/K20)-1,"-") -> - | Q20: =IF(AND(O20="",P20=""),"-",P20-O20) -> - | R20: =IFERROR((P20/O20)-1,"-") -> - | U20: =IF(AND(S20="",T20=""),"-",T20-S20) -> - | V20: =IFERROR((T20/S20)-1,"-") -> - | Y20: =IF(AND(W20="",X20=""),"-",X20-W20) -> - | Z20: =IFERROR((X20/W20)-1,"-") -> - | AC20: =IF(AND(AA20="",AB20=""),"-",AB20-AA20) -> - | AD20: =IFERROR((AB20/AA20)-1,"-") -> - | AG20: =IF(AND(AE20="",AF20=""),"-",AF20-AE20) -> - | AH20: =IFERROR((AF20/AE20)-1,"-") -> - | AK20: =IF(AND(AI20="",AJ20=""),"-",AJ20-AI20) -> - | AL20: =IFERROR((AJ20/AI20)-1,"-") -> - | AO20: =IF(AND(AM20="",AN20=""),"-",AN20-AM20) -> - | AP20: =IFERROR((AN20/AM20)-1,"-") -> - | AS20: =IF(AND(AQ20="",AR20=""),"-",AR20-AQ20) -> - | AT20: =IFERROR((AR20/AQ20)-1,"-") -> - | AW20: =IF(AND(AU20="",AV20=""),"-",AV20-AU20) -> - | AX20: =IFERROR((AV20/AU20)-1,"-") -> - | BA20: =IF(AND(AY20="",AZ20=""),"-",AZ20-AY20) -> - | BB20: =IFERROR((AZ20/AY20)-1,"-") -> - | BE20: =IF(AND(BC20="",BD20=""),"-",BD20-BC20) -> - | BF20: =IFERROR((BD20/BC20)-1,"-") -> - | BG20: =BC20+AY20+AU20+AQ20+AM20+AI20+AE20+AA20+W20+S20+O20+K20 -> 0 | BH20: =BD20+AZ20+AV20+AR20+AN20+AJ20+AF20+AB20+X20+T20+P20+L20 -> 0 | BI20: =IF(AND(BG20="",BH20=""),"-",BH20-BG20) -> 0 | BJ20: =IFERROR((BH20/BG20)-1,"-") -> -
B21: 9 | C21: NOME DA DESPESA | D21: 10000 | E21: =D21/$D$3 -> 0.0086956522 | F21: =E21+F20 -> 0.97826087 | H21: 17 | I21: NOME DA DESPESA | M21: =IF(AND(K21="",L21=""),"-",L21-K21) -> - | N21: =IFERROR((L21/K21)-1,"-") -> - | Q21: =IF(AND(O21="",P21=""),"-",P21-O21) -> - | R21: =IFERROR((P21/O21)-1,"-") -> - | U21: =IF(AND(S21="",T21=""),"-",T21-S21) -> - | V21: =IFERROR((T21/S21)-1,"-") -> - | Y21: =IF(AND(W21="",X21=""),"-",X21-W21) -> - | Z21: =IFERROR((X21/W21)-1,"-") -> - | AC21: =IF(AND(AA21="",AB21=""),"-",AB21-AA21) -> - | AD21: =IFERROR((AB21/AA21)-1,"-") -> - | AG21: =IF(AND(AE21="",AF21=""),"-",AF21-AE21) -> - | AH21: =IFERROR((AF21/AE21)-1,"-") -> - | AK21: =IF(AND(AI21="",AJ21=""),"-",AJ21-AI21) -> - | AL21: =IFERROR((AJ21/AI21)-1,"-") -> - | AO21: =IF(AND(AM21="",AN21=""),"-",AN21-AM21) -> - | AP21: =IFERROR((AN21/AM21)-1,"-") -> - | AS21: =IF(AND(AQ21="",AR21=""),"-",AR21-AQ21) -> - | AT21: =IFERROR((AR21/AQ21)-1,"-") -> - | AW21: =IF(AND(AU21="",AV21=""),"-",AV21-AU21) -> - | AX21: =IFERROR((AV21/AU21)-1,"-") -> - | BA21: =IF(AND(AY21="",AZ21=""),"-",AZ21-AY21) -> - | BB21: =IFERROR((AZ21/AY21)-1,"-") -> - | BE21: =IF(AND(BC21="",BD21=""),"-",BD21-BC21) -> - | BF21: =IFERROR((BD21/BC21)-1,"-") -> - | BG21: =BC21+AY21+AU21+AQ21+AM21+AI21+AE21+AA21+W21+S21+O21+K21 -> 0 | BH21: =BD21+AZ21+AV21+AR21+AN21+AJ21+AF21+AB21+X21+T21+P21+L21 -> 0 | BI21: =IF(AND(BG21="",BH21=""),"-",BH21-BG21) -> 0 | BJ21: =IFERROR((BH21/BG21)-1,"-") -> -
B22: 10 | C22: NOME DA DESPESA | D22: 10000 | E22: =D22/$D$3 -> 0.0086956522 | F22: =E22+F21 -> 0.98695652 | H22: 18 | I22: NOME DA DESPESA | M22: =IF(AND(K22="",L22=""),"-",L22-K22) -> - | N22: =IFERROR((L22/K22)-1,"-") -> - | Q22: =IF(AND(O22="",P22=""),"-",P22-O22) -> - | R22: =IFERROR((P22/O22)-1,"-") -> - | U22: =IF(AND(S22="",T22=""),"-",T22-S22) -> - | V22: =IFERROR((T22/S22)-1,"-") -> - | Y22: =IF(AND(W22="",X22=""),"-",X22-W22) -> - | Z22: =IFERROR((X22/W22)-1,"-") -> - | AC22: =IF(AND(AA22="",AB22=""),"-",AB22-AA22) -> - | AD22: =IFERROR((AB22/AA22)-1,"-") -> - | AG22: =IF(AND(AE22="",AF22=""),"-",AF22-AE22) -> - | AH22: =IFERROR((AF22/AE22)-1,"-") -> - | AK22: =IF(AND(AI22="",AJ22=""),"-",AJ22-AI22) -> - | AL22: =IFERROR((AJ22/AI22)-1,"-") -> - | AO22: =IF(AND(AM22="",AN22=""),"-",AN22-AM22) -> - | AP22: =IFERROR((AN22/AM22)-1,"-") -> - | AS22: =IF(AND(AQ22="",AR22=""),"-",AR22-AQ22) -> - | AT22: =IFERROR((AR22/AQ22)-1,"-") -> - | AW22: =IF(AND(AU22="",AV22=""),"-",AV22-AU22) -> - | AX22: =IFERROR((AV22/AU22)-1,"-") -> - | BA22: =IF(AND(AY22="",AZ22=""),"-",AZ22-AY22) -> - | BB22: =IFERROR((AZ22/AY22)-1,"-") -> - | BE22: =IF(AND(BC22="",BD22=""),"-",BD22-BC22) -> - | BF22: =IFERROR((BD22/BC22)-1,"-") -> - | BG22: =BC22+AY22+AU22+AQ22+AM22+AI22+AE22+AA22+W22+S22+O22+K22 -> 0 | BH22: =BD22+AZ22+AV22+AR22+AN22+AJ22+AF22+AB22+X22+T22+P22+L22 -> 0 | BI22: =IF(AND(BG22="",BH22=""),"-",BH22-BG22) -> 0 | BJ22: =IFERROR((BH22/BG22)-1,"-") -> -
B23: 11 | C23: NOME DA DESPESA | D23: 6000 | E23: =D23/$D$3 -> 0.0052173913 | F23: =E23+F22 -> 0.99217391 | H23: 19 | I23: NOME DA DESPESA | M23: =IF(AND(K23="",L23=""),"-",L23-K23) -> - | N23: =IFERROR((L23/K23)-1,"-") -> - | Q23: =IF(AND(O23="",P23=""),"-",P23-O23) -> - | R23: =IFERROR((P23/O23)-1,"-") -> - | U23: =IF(AND(S23="",T23=""),"-",T23-S23) -> - | V23: =IFERROR((T23/S23)-1,"-") -> - | Y23: =IF(AND(W23="",X23=""),"-",X23-W23) -> - | Z23: =IFERROR((X23/W23)-1,"-") -> - | AC23: =IF(AND(AA23="",AB23=""),"-",AB23-AA23) -> - | AD23: =IFERROR((AB23/AA23)-1,"-") -> - | AG23: =IF(AND(AE23="",AF23=""),"-",AF23-AE23) -> - | AH23: =IFERROR((AF23/AE23)-1,"-") -> - | AK23: =IF(AND(AI23="",AJ23=""),"-",AJ23-AI23) -> - | AL23: =IFERROR((AJ23/AI23)-1,"-") -> - | AO23: =IF(AND(AM23="",AN23=""),"-",AN23-AM23) -> - | AP23: =IFERROR((AN23/AM23)-1,"-") -> - | AS23: =IF(AND(AQ23="",AR23=""),"-",AR23-AQ23) -> - | AT23: =IFERROR((AR23/AQ23)-1,"-") -> - | AW23: =IF(AND(AU23="",AV23=""),"-",AV23-AU23) -> - | AX23: =IFERROR((AV23/AU23)-1,"-") -> - | BA23: =IF(AND(AY23="",AZ23=""),"-",AZ23-AY23) -> - | BB23: =IFERROR((AZ23/AY23)-1,"-") -> - | BE23: =IF(AND(BC23="",BD23=""),"-",BD23-BC23) -> - | BF23: =IFERROR((BD23/BC23)-1,"-") -> - | BG23: =BC23+AY23+AU23+AQ23+AM23+AI23+AE23+AA23+W23+S23+O23+K23 -> 0 | BH23: =BD23+AZ23+AV23+AR23+AN23+AJ23+AF23+AB23+X23+T23+P23+L23 -> 0 | BI23: =IF(AND(BG23="",BH23=""),"-",BH23-BG23) -> 0 | BJ23: =IFERROR((BH23/BG23)-1,"-") -> -
B24: 12 | C24: NOME DA DESPESA | D24: 5000 | E24: =D24/$D$3 -> 0.0043478261 | F24: =E24+F23 -> 0.99652174 | H24: 20 | I24: NOME DA DESPESA | M24: =IF(AND(K24="",L24=""),"-",L24-K24) -> - | N24: =IFERROR((L24/K24)-1,"-") -> - | Q24: =IF(AND(O24="",P24=""),"-",P24-O24) -> - | R24: =IFERROR((P24/O24)-1,"-") -> - | U24: =IF(AND(S24="",T24=""),"-",T24-S24) -> - | V24: =IFERROR((T24/S24)-1,"-") -> - | Y24: =IF(AND(W24="",X24=""),"-",X24-W24) -> - | Z24: =IFERROR((X24/W24)-1,"-") -> - | AC24: =IF(AND(AA24="",AB24=""),"-",AB24-AA24) -> - | AD24: =IFERROR((AB24/AA24)-1,"-") -> - | AG24: =IF(AND(AE24="",AF24=""),"-",AF24-AE24) -> - | AH24: =IFERROR((AF24/AE24)-1,"-") -> - | AK24: =IF(AND(AI24="",AJ24=""),"-",AJ24-AI24) -> - | AL24: =IFERROR((AJ24/AI24)-1,"-") -> - | AO24: =IF(AND(AM24="",AN24=""),"-",AN24-AM24) -> - | AP24: =IFERROR((AN24/AM24)-1,"-") -> - | AS24: =IF(AND(AQ24="",AR24=""),"-",AR24-AQ24) -> - | AT24: =IFERROR((AR24/AQ24)-1,"-") -> - | AW24: =IF(AND(AU24="",AV24=""),"-",AV24-AU24) -> - | AX24: =IFERROR((AV24/AU24)-1,"-") -> - | BA24: =IF(AND(AY24="",AZ24=""),"-",AZ24-AY24) -> - | BB24: =IFERROR((AZ24/AY24)-1,"-") -> - | BE24: =IF(AND(BC24="",BD24=""),"-",BD24-BC24) -> - | BF24: =IFERROR((BD24/BC24)-1,"-") -> - | BG24: =BC24+AY24+AU24+AQ24+AM24+AI24+AE24+AA24+W24+S24+O24+K24 -> 0 | BH24: =BD24+AZ24+AV24+AR24+AN24+AJ24+AF24+AB24+X24+T24+P24+L24 -> 0 | BI24: =IF(AND(BG24="",BH24=""),"-",BH24-BG24) -> 0 | BJ24: =IFERROR((BH24/BG24)-1,"-") -> -
B25: 13 | C25: NOME DA DESPESA | D25: 4000 | E25: =D25/$D$3 -> 0.0034782609 | F25: =E25+F24 -> 1 | H25: 21 | I25: NOME DA DESPESA | M25: =IF(AND(K25="",L25=""),"-",L25-K25) -> - | N25: =IFERROR((L25/K25)-1,"-") -> - | Q25: =IF(AND(O25="",P25=""),"-",P25-O25) -> - | R25: =IFERROR((P25/O25)-1,"-") -> - | U25: =IF(AND(S25="",T25=""),"-",T25-S25) -> - | V25: =IFERROR((T25/S25)-1,"-") -> - | Y25: =IF(AND(W25="",X25=""),"-",X25-W25) -> - | Z25: =IFERROR((X25/W25)-1,"-") -> - | AC25: =IF(AND(AA25="",AB25=""),"-",AB25-AA25) -> - | AD25: =IFERROR((AB25/AA25)-1,"-") -> - | AG25: =IF(AND(AE25="",AF25=""),"-",AF25-AE25) -> - | AH25: =IFERROR((AF25/AE25)-1,"-") -> - | AK25: =IF(AND(AI25="",AJ25=""),"-",AJ25-AI25) -> - | AL25: =IFERROR((AJ25/AI25)-1,"-") -> - | AO25: =IF(AND(AM25="",AN25=""),"-",AN25-AM25) -> - | AP25: =IFERROR((AN25/AM25)-1,"-") -> - | AS25: =IF(AND(AQ25="",AR25=""),"-",AR25-AQ25) -> - | AT25: =IFERROR((AR25/AQ25)-1,"-") -> - | AW25: =IF(AND(AU25="",AV25=""),"-",AV25-AU25) -> - | AX25: =IFERROR((AV25/AU25)-1,"-") -> - | BA25: =IF(AND(AY25="",AZ25=""),"-",AZ25-AY25) -> - | BB25: =IFERROR((AZ25/AY25)-1,"-") -> - | BE25: =IF(AND(BC25="",BD25=""),"-",BD25-BC25) -> - | BF25: =IFERROR((BD25/BC25)-1,"-") -> - | BG25: =BC25+AY25+AU25+AQ25+AM25+AI25+AE25+AA25+W25+S25+O25+K25 -> 0 | BH25: =BD25+AZ25+AV25+AR25+AN25+AJ25+AF25+AB25+X25+T25+P25+L25 -> 0 | BI25: =IF(AND(BG25="",BH25=""),"-",BH25-BG25) -> 0 | BJ25: =IFERROR((BH25/BG25)-1,"-") -> -
I26: TOTAL GERAL | J26: =SUM(J5:J25) -> 242550 | K26: =SUM(K5:K25) -> 232600 | L26: =SUM(L5:L25) -> 232700 | M26: =IF(AND(K26="",L26=""),"-",L26-K26) -> 100 | N26: =IFERROR((L26/K26)-1,"-") -> 0.00042992261 | O26: =SUM(O5:O25) -> 0 | P26: =SUM(P5:P25) -> 0 | Q26: =IF(AND(O26="",P26=""),"-",P26-O26) -> 0 | R26: =IFERROR((P26/O26)-1,"-") -> - | S26: =SUM(S5:S25) -> 0 | T26: =SUM(T5:T25) -> 0 | U26: =IF(AND(S26="",T26=""),"-",T26-S26) -> 0 | V26: =IFERROR((T26/S26)-1,"-") -> - | W26: =SUM(W5:W25) -> 0 | X26: =SUM(X5:X25) -> 0 | Y26: =IF(AND(W26="",X26=""),"-",X26-W26) -> 0 | Z26: =IFERROR((X26/W26)-1,"-") -> - | AA26: =SUM(AA5:AA25) -> 0 | AB26: =SUM(AB5:AB25) -> 0 | AC26: =IF(AND(AA26="",AB26=""),"-",AB26-AA26) -> 0 | AD26: =IFERROR((AB26/AA26)-1,"-") -> - | AE26: =SUM(AE5:AE25) -> 0 | AF26: =SUM(AF5:AF25) -> 0 | AG26: =IF(AND(AE26="",AF26=""),"-",AF26-AE26) -> 0 | AH26: =IFERROR((AF26/AE26)-1,"-") -> - | AI26: =SUM(AI5:AI25) -> 0 | AJ26: =SUM(AJ5:AJ25) -> 0 | AK26: =IF(AND(AI26="",AJ26=""),"-",AJ26-AI26) -> 0 | AL26: =IFERROR((AJ26/AI26)-1,"-") -> - | AM26: =SUM(AM5:AM25) -> 0 | AN26: =SUM(AN5:AN25) -> 0 | AO26: =IF(AND(AM26="",AN26=""),"-",AN26-AM26) -> 0 | AP26: =IFERROR((AN26/AM26)-1,"-") -> - | AQ26: =SUM(AQ5:AQ25) -> 0 | AR26: =SUM(AR5:AR25) -> 0 | AS26: =IF(AND(AQ26="",AR26=""),"-",AR26-AQ26) -> 0 | AT26: =IFERROR((AR26/AQ26)-1,"-") -> - | AU26: =SUM(AU5:AU25) -> 0 | AV26: =SUM(AV5:AV25) -> 0 | AW26: =IF(AND(AU26="",AV26=""),"-",AV26-AU26) -> 0 | AX26: =IFERROR((AV26/AU26)-1,"-") -> - | AY26: =SUM(AY5:AY25) -> 0 | AZ26: =SUM(AZ5:AZ25) -> 0 | BA26: =IF(AND(AY26="",AZ26=""),"-",AZ26-AY26) -> 0 | BB26: =IFERROR((AZ26/AY26)-1,"-") -> - | BC26: =SUM(BC5:BC25) -> 0 | BD26: =SUM(BD5:BD25) -> 0 | BE26: =IF(AND(BC26="",BD26=""),"-",BD26-BC26) -> 0 | BF26: =IFERROR((BD26/BC26)-1,"-") -> - | BG26: =SUM(BG5:BG25) -> 232600 | BH26: =SUM(BH5:BH25) -> 232700 | BI26: =SUM(BI5:BI14) -> -2900 | BJ26: =IFERROR((BH26/BG26)-1,"-") -> 0.00042992261

Sheet 5.2
B2: < CLIQUE AQUI E VOLTE AO PAINEL INICIAL | C2: GESTÃO MATRICIAL DE RECEITAS | J2: ALTERE O PRIMEIRO MÊS E TODOS OS MESES ATUALIZAÇÃO AUTOMATICAMENTE → | M2: 45658 | Q2: =DATE(YEAR(M2),MONTH(M2)+1,DAY(M2)) -> 45689 | U2: =DATE(YEAR(Q2),MONTH(Q2)+1,DAY(Q2)) -> 45717 | Y2: =DATE(YEAR(U2),MONTH(U2)+1,DAY(U2)) -> 45748 | AC2: =DATE(YEAR(Y2),MONTH(Y2)+1,DAY(Y2)) -> 45778 | AG2: =DATE(YEAR(AC2),MONTH(AC2)+1,DAY(AC2)) -> 45809 | AK2: =DATE(YEAR(AG2),MONTH(AG2)+1,DAY(AG2)) -> 45839 | AO2: =DATE(YEAR(AK2),MONTH(AK2)+1,DAY(AK2)) -> 45870 | AS2: =DATE(YEAR(AO2),MONTH(AO2)+1,DAY(AO2)) -> 45901 | AW2: =DATE(YEAR(AS2),MONTH(AS2)+1,DAY(AS2)) -> 45931 | BA2: =DATE(YEAR(AW2),MONTH(AW2)+1,DAY(AW2)) -> 45962 | BE2: =DATE(YEAR(BA2),MONTH(BA2)+1,DAY(BA2)) -> 45992 | BI2: ACUMULADO
B3: SOMATÓRIO TOTAL DAS LINHAS → | F3: =SUM(F6:F25) -> 3940000 | J3: # | K3: NOME DO PRODUTO/SERVIÇO | L3: MÉDIA HISTÓRICA MENSAL | M3: META | N3: REAL | O3: DESVIO ABS. | P3: DESVIO % | Q3: META | R3: REAL | S3: DESVIO ABS. | T3: DESVIO % | U3: META | V3: REAL | W3: DESVIO ABS. | X3: DESVIO % | Y3: META | Z3: REAL | AA3: DESVIO ABS. | AB3: DESVIO % | AC3: META | AD3: REAL | AE3: DESVIO ABS. | AF3: DESVIO % | AG3: META | AH3: REAL | AI3: DESVIO ABS. | AJ3: DESVIO % | AK3: META | AL3: REAL | AM3: DESVIO ABS. | AN3: DESVIO % | AO3: META | AP3: REAL | AQ3: DESVIO ABS. | AR3: DESVIO % | AS3: META | AT3: REAL | AU3: DESVIO ABS. | AV3: DESVIO % | AW3: META | AX3: REAL | AY3: DESVIO ABS. | AZ3: DESVIO % | BA3: META | BB3: REAL | BC3: DESVIO ABS. | BD3: DESVIO % | BE3: META | BF3: REAL | BG3: DESVIO ABS. | BH3: DESVIO % | BI3: META | BJ3: REAL | BK3: DESVIO ABS. | BL3: DESVIO %
B5: # | C5: NOME DA DESPESA | D5: PREÇO DE VENDA | E5: MARGEM DE LUCRO | F5: FATURAMENTO MÉDIO MENSAL | G5: REPRESENTATIVIDADE DA DESPESA ACUMULADA | H5: REPRESENTATIVIDADE DA DESPESA ACUMULADA | J5: 1 | K5: NOME DO PRODUTO | L5: 100000 | M5: 150000 | N5: 180000 | O5: =IF(AND(M5="",N5=""),"-",N5-M5) -> 30000 | P5: =IFERROR((N5/M5)-1,"-") -> 0.2 | S5: =IF(AND(Q5="",R5=""),"-",R5-Q5) -> - | T5: =IFERROR((R5/Q5)-1,"-") -> - | W5: =IF(AND(U5="",V5=""),"-",V5-U5) -> - | X5: =IFERROR((V5/U5)-1,"-") -> - | AA5: =IF(AND(Y5="",Z5=""),"-",Z5-Y5) -> - | AB5: =IFERROR((Z5/Y5)-1,"-") -> - | AE5: =IF(AND(AC5="",AD5=""),"-",AD5-AC5) -> - | AF5: =IFERROR((AD5/AC5)-1,"-") -> - | AI5: =IF(AND(AG5="",AH5=""),"-",AH5-AG5) -> - | AJ5: =IFERROR((AH5/AG5)-1,"-") -> - | AM5: =IF(AND(AK5="",AL5=""),"-",AL5-AK5) -> - | AN5: =IFERROR((AL5/AK5)-1,"-") -> - | AQ5: =IF(AND(AO5="",AP5=""),"-",AP5-AO5) -> - | AR5: =IFERROR((AP5/AO5)-1,"-") -> - | AU5: =IF(AND(AS5="",AT5=""),"-",AT5-AS5) -> - | AV5: =IFERROR((AT5/AS5)-1,"-") -> - | AY5: =IF(AND(AW5="",AX5=""),"-",AX5-AW5) -> - | AZ5: =IFERROR((AX5/AW5)-1,"-") -> - | BC5: =IF(AND(BA5="",BB5=""),"-",BB5-BA5) -> - | BD5: =IFERROR((BB5/BA5)-1,"-") -> - | BG5: =IF(AND(BE5="",BF5=""),"-",BF5-BE5) -> - | BH5: =IFERROR((BF5/BE5)-1,"-") -> - | BI5: =BE5+BA5+AW5+AS5+AO5+AK5+AG5+AC5+Y5+U5+Q5+M5 -> 150000 | BJ5: =BF5+BB5+AX5+AT5+AP5+AL5+AH5+AD5+Z5+V5+R5+N5 -> 180000 | BK5: =IF(AND(BI5="",BJ5=""),"-",BJ5-BI5) -> 30000 | BL5: =IFERROR((BJ5/BI5)-1,"-") -> 0.2
B6: 6 | C6: NOME DO PRODUTO/SERVIÇO | D6: 150 | E6: 0.25 | F6: 300000 | G6: =F6/$F$3 -> 0.076142132 | H6: =G6 -> 0.076142132 | J6: 2 | K6: NOME DO PRODUTO | L6: 100000 | M6: 100000 | N6: 95000 | O6: =IF(AND(M6="",N6=""),"-",N6-M6) -> -5000 | P6: =IFERROR((N6/M6)-1,"-") -> -0.05 | S6: =IF(AND(Q6="",R6=""),"-",R6-Q6) -> - | T6: =IFERROR((R6/Q6)-1,"-") -> - | W6: =IF(AND(U6="",V6=""),"-",V6-U6) -> - | X6: =IFERROR((V6/U6)-1,"-") -> - | AA6: =IF(AND(Y6="",Z6=""),"-",Z6-Y6) -> - | AB6: =IFERROR((Z6/Y6)-1,"-") -> - | AE6: =IF(AND(AC6="",AD6=""),"-",AD6-AC6) -> - | AF6: =IFERROR((AD6/AC6)-1,"-") -> - | AI6: =IF(AND(AG6="",AH6=""),"-",AH6-AG6) -> - | AJ6: =IFERROR((AH6/AG6)-1,"-") -> - | AM6: =IF(AND(AK6="",AL6=""),"-",AL6-AK6) -> - | AN6: =IFERROR((AL6/AK6)-1,"-") -> - | AQ6: =IF(AND(AO6="",AP6=""),"-",AP6-AO6) -> - | AR6: =IFERROR((AP6/AO6)-1,"-") -> - | AU6: =IF(AND(AS6="",AT6=""),"-",AT6-AS6) -> - | AV6: =IFERROR((AT6/AS6)-1,"-") -> - | AY6: =IF(AND(AW6="",AX6=""),"-",AX6-AW6) -> - | AZ6: =IFERROR((AX6/AW6)-1,"-") -> - | BC6: =IF(AND(BA6="",BB6=""),"-",BB6-BA6) -> - | BD6: =IFERROR((BB6/BA6)-1,"-") -> - | BG6: =IF(AND(BE6="",BF6=""),"-",BF6-BE6) -> - | BH6: =IFERROR((BF6/BE6)-1,"-") -> - | BI6: =BE6+BA6+AW6+AS6+AO6+AK6+AG6+AC6+Y6+U6+Q6+M6 -> 100000 | BJ6: =BF6+BB6+AX6+AT6+AP6+AL6+AH6+AD6+Z6+V6+R6+N6 -> 95000 | BK6: =IF(AND(BI6="",BJ6=""),"-",BJ6-BI6) -> -5000 | BL6: =IFERROR((BJ6/BI6)-1,"-") -> -0.05
B7: 1 | C7: NOME DO PRODUTO/SERVIÇO | D7: 20 | E7: 0.1 | F7: 400000 | G7: =F7/$F$3 -> 0.10152284 | H7: =G7+H6 -> 0.17766497 | J7: 3 | K7: NOME DO PRODUTO | L7: 100000 | O7: =IF(AND(M7="",N7=""),"-",N7-M7) -> - | P7: =IFERROR((N7/M7)-1,"-") -> - | S7: =IF(AND(Q7="",R7=""),"-",R7-Q7) -> - | T7: =IFERROR((R7/Q7)-1,"-") -> - | W7: =IF(AND(U7="",V7=""),"-",V7-U7) -> - | X7: =IFERROR((V7/U7)-1,"-") -> - | AA7: =IF(AND(Y7="",Z7=""),"-",Z7-Y7) -> - | AB7: =IFERROR((Z7/Y7)-1,"-") -> - | AE7: =IF(AND(AC7="",AD7=""),"-",AD7-AC7) -> - | AF7: =IFERROR((AD7/AC7)-1,"-") -> - | AI7: =IF(AND(AG7="",AH7=""),"-",AH7-AG7) -> - | AJ7: =IFERROR((AH7/AG7)-1,"-") -> - | AM7: =IF(AND(AK7="",AL7=""),"-",AL7-AK7) -> - | AN7: =IFERROR((AL7/AK7)-1,"-") -> - | AQ7: =IF(AND(AO7="",AP7=""),"-",AP7-AO7) -> - | AR7: =IFERROR((AP7/AO7)-1,"-") -> - | AU7: =IF(AND(AS7="",AT7=""),"-",AT7-AS7) -> - | AV7: =IFERROR((AT7/AS7)-1,"-") -> - | AY7: =IF(AND(AW7="",AX7=""),"-",AX7-AW7) -> - | AZ7: =IFERROR((AX7/AW7)-1,"-") -> - | BC7: =IF(AND(BA7="",BB7=""),"-",BB7-BA7) -> - | BD7: =IFERROR((BB7/BA7)-1,"-") -> - | BG7: =IF(AND(BE7="",BF7=""),"-",BF7-BE7) -> - | BH7: =IFERROR((BF7/BE7)-1,"-") -> - | BI7: =BE7+BA7+AW7+AS7+AO7+AK7+AG7+AC7+Y7+U7+Q7+M7 -> 0 | BJ7: =BF7+BB7+AX7+AT7+AP7+AL7+AH7+AD7+Z7+V7+R7+N7 -> 0 | BK7: =IF(AND(BI7="",BJ7=""),"-",BJ7-BI7) -> 0 | BL7: =IFERROR((BJ7/BI7)-1,"-") -> -
B8: 2 | C8: NOME DO PRODUTO/SERVIÇO | D8: 40 | E8: 0.15 | F8: 240000 | G8: =F8/$F$3 -> 0.060913706 | H8: =G8+H7 -> 0.23857868 | J8: 4 | K8: NOME DO PRODUTO | L8: 100000 | O8: =IF(AND(M8="",N8=""),"-",N8-M8) -> - | P8: =IFERROR((N8/M8)-1,"-") -> - | S8: =IF(AND(Q8="",R8=""),"-",R8-Q8) -> - | T8: =IFERROR((R8/Q8)-1,"-") -> - | W8: =IF(AND(U8="",V8=""),"-",V8-U8) -> - | X8: =IFERROR((V8/U8)-1,"-") -> - | AA8: =IF(AND(Y8="",Z8=""),"-",Z8-Y8) -> - | AB8: =IFERROR((Z8/Y8)-1,"-") -> - | AE8: =IF(AND(AC8="",AD8=""),"-",AD8-AC8) -> - | AF8: =IFERROR((AD8/AC8)-1,"-") -> - | AI8: =IF(AND(AG8="",AH8=""),"-",AH8-AG8) -> - | AJ8: =IFERROR((AH8/AG8)-1,"-") -> - | AM8: =IF(AND(AK8="",AL8=""),"-",AL8-AK8) -> - | AN8: =IFERROR((AL8/AK8)-1,"-") -> - | AQ8: =IF(AND(AO8="",AP8=""),"-",AP8-AO8) -> - | AR8: =IFERROR((AP8/AO8)-1,"-") -> - | AU8: =IF(AND(AS8="",AT8=""),"-",AT8-AS8) -> - | AV8: =IFERROR((AT8/AS8)-1,"-") -> - | AY8: =IF(AND(AW8="",AX8=""),"-",AX8-AW8) -> - | AZ8: =IFERROR((AX8/AW8)-1,"-") -> - | BC8: =IF(AND(BA8="",BB8=""),"-",BB8-BA8) -> - | BD8: =IFERROR((BB8/BA8)-1,"-") -> - | BG8: =IF(AND(BE8="",BF8=""),"-",BF8-BE8) -> - | BH8: =IFERROR((BF8/BE8)-1,"-") -> - | BI8: =BE8+BA8+AW8+AS8+AO8+AK8+AG8+AC8+Y8+U8+Q8+M8 -> 0 | BJ8: =BF8+BB8+AX8+AT8+AP8+AL8+AH8+AD8+Z8+V8+R8+N8 -> 0 | BK8: =IF(AND(BI8="",BJ8=""),"-",BJ8-BI8) -> 0 | BL8: =IFERROR((BJ8/BI8)-1,"-") -> -
B9: 3 | C9: NOME DO PRODUTO/SERVIÇO | D9: 60 | E9: 0.2 | F9: 500000 | G9: =F9/$F$3 -> 0.12690355 | H9: =G9+H8 -> 0.36548223 | J9: 5 | K9: NOME DO PRODUTO | L9: 100000 | O9: =IF(AND(M9="",N9=""),"-",N9-M9) -> - | P9: =IFERROR((N9/M9)-1,"-") -> - | S9: =IF(AND(Q9="",R9=""),"-",R9-Q9) -> - | T9: =IFERROR((R9/Q9)-1,"-") -> - | W9: =IF(AND(U9="",V9=""),"-",V9-U9) -> - | X9: =IFERROR((V9/U9)-1,"-") -> - | AA9: =IF(AND(Y9="",Z9=""),"-",Z9-Y9) -> - | AB9: =IFERROR((Z9/Y9)-1,"-") -> - | AE9: =IF(AND(AC9="",AD9=""),"-",AD9-AC9) -> - | AF9: =IFERROR((AD9/AC9)-1,"-") -> - | AI9: =IF(AND(AG9="",AH9=""),"-",AH9-AG9) -> - | AJ9: =IFERROR((AH9/AG9)-1,"-") -> - | AM9: =IF(AND(AK9="",AL9=""),"-",AL9-AK9) -> - | AN9: =IFERROR((AL9/AK9)-1,"-") -> - | AQ9: =IF(AND(AO9="",AP9=""),"-",AP9-AO9) -> - | AR9: =IFERROR((AP9/AO9)-1,"-") -> - | AU9: =IF(AND(AS9="",AT9=""),"-",AT9-AS9) -> - | AV9: =IFERROR((AT9/AS9)-1,"-") -> - | AY9: =IF(AND(AW9="",AX9=""),"-",AX9-AW9) -> - | AZ9: =IFERROR((AX9/AW9)-1,"-") -> - | BC9: =IF(AND(BA9="",BB9=""),"-",BB9-BA9) -> - | BD9: =IFERROR((BB9/BA9)-1,"-") -> - | BG9: =IF(AND(BE9="",BF9=""),"-",BF9-BE9) -> - | BH9: =IFERROR((BF9/BE9)-1,"-") -> - | BI9: =BE9+BA9+AW9+AS9+AO9+AK9+AG9+AC9+Y9+U9+Q9+M9 -> 0 | BJ9: =BF9+BB9+AX9+AT9+AP9+AL9+AH9+AD9+Z9+V9+R9+N9 -> 0 | BK9: =IF(AND(BI9="",BJ9=""),"-",BJ9-BI9) -> 0 | BL9: =IFERROR((BJ9/BI9)-1,"-") -> -
B10: 4 | C10: NOME DO PRODUTO/SERVIÇO | D10: 80 | E10: 0.1 | F10: 1000000 | G10: =F10/$F$3 -> 0.25380711 | H10: =G10+H9 -> 0.61928934 | J10: 6 | K10: NOME DO PRODUTO | L10: 100000 | O10: =IF(AND(M10="",N10=""),"-",N10-M10) -> - | P10: =IFERROR((N10/M10)-1,"-") -> - | S10: =IF(AND(Q10="",R10=""),"-",R10-Q10) -> - | T10: =IFERROR((R10/Q10)-1,"-") -> - | W10: =IF(AND(U10="",V10=""),"-",V10-U10) -> - | X10: =IFERROR((V10/U10)-1,"-") -> - | AA10: =IF(AND(Y10="",Z10=""),"-",Z10-Y10) -> - | AB10: =IFERROR((Z10/Y10)-1,"-") -> - | AE10: =IF(AND(AC10="",AD10=""),"-",AD10-AC10) -> - | AF10: =IFERROR((AD10/AC10)-1,"-") -> - | AI10: =IF(AND(AG10="",AH10=""),"-",AH10-AG10) -> - | AJ10: =IFERROR((AH10/AG10)-1,"-") -> - | AM10: =IF(AND(AK10="",AL10=""),"-",AL10-AK10) -> - | AN10: =IFERROR((AL10/AK10)-1,"-") -> - | AQ10: =IF(AND(AO10="",AP10=""),"-",AP10-AO10) -> - | AR10: =IFERROR((AP10/AO10)-1,"-") -> - | AU10: =IF(AND(AS10="",AT10=""),"-",AT10-AS10) -> - | AV10: =IFERROR((AT10/AS10)-1,"-") -> - | AY10: =IF(AND(AW10="",AX10=""),"-",AX10-AW10) -> - | AZ10: =IFERROR((AX10/AW10)-1,"-") -> - | BC10: =IF(AND(BA10="",BB10=""),"-",BB10-BA10) -> - | BD10: =IFERROR((BB10/BA10)-1,"-") -> - | BG10: =IF(AND(BE10="",BF10=""),"-",BF10-BE10) -> - | BH10: =IFERROR((BF10/BE10)-1,"-") -> - | BI10: =BE10+BA10+AW10+AS10+AO10+AK10+AG10+AC10+Y10+U10+Q10+M10 -> 0 | BJ10: =BF10+BB10+AX10+AT10+AP10+AL10+AH10+AD10+Z10+V10+R10+N10 -> 0 | BK10: =IF(AND(BI10="",BJ10=""),"-",BJ10-BI10) -> 0 | BL10: =IFERROR((BJ10/BI10)-1,"-") -> -
B11: 5 | C11: NOME DO PRODUTO/SERVIÇO | D11: 100 | E11: 0.15 | F11: 100000 | G11: =F11/$F$3 -> 0.025380711 | H11: =G11+H10 -> 0.64467005 | J11: 7 | K11: NOME DO PRODUTO | L11: 100000 | O11: =IF(AND(M11="",N11=""),"-",N11-M11) -> - | P11: =IFERROR((N11/M11)-1,"-") -> - | S11: =IF(AND(Q11="",R11=""),"-",R11-Q11) -> - | T11: =IFERROR((R11/Q11)-1,"-") -> - | W11: =IF(AND(U11="",V11=""),"-",V11-U11) -> - | X11: =IFERROR((V11/U11)-1,"-") -> - | AA11: =IF(AND(Y11="",Z11=""),"-",Z11-Y11) -> - | AB11: =IFERROR((Z11/Y11)-1,"-") -> - | AE11: =IF(AND(AC11="",AD11=""),"-",AD11-AC11) -> - | AF11: =IFERROR((AD11/AC11)-1,"-") -> - | AI11: =IF(AND(AG11="",AH11=""),"-",AH11-AG11) -> - | AJ11: =IFERROR((AH11/AG11)-1,"-") -> - | AM11: =IF(AND(AK11="",AL11=""),"-",AL11-AK11) -> - | AN11: =IFERROR((AL11/AK11)-1,"-") -> - | AQ11: =IF(AND(AO11="",AP11=""),"-",AP11-AO11) -> - | AR11: =IFERROR((AP11/AO11)-1,"-") -> - | AU11: =IF(AND(AS11="",AT11=""),"-",AT11-AS11) -> - | AV11: =IFERROR((AT11/AS11)-1,"-") -> - | AY11: =IF(AND(AW11="",AX11=""),"-",AX11-AW11) -> - | AZ11: =IFERROR((AX11/AW11)-1,"-") -> - | BC11: =IF(AND(BA11="",BB11=""),"-",BB11-BA11) -> - | BD11: =IFERROR((BB11/BA11)-1,"-") -> - | BG11: =IF(AND(BE11="",BF11=""),"-",BF11-BE11) -> - | BH11: =IFERROR((BF11/BE11)-1,"-") -> - | BI11: =BE11+BA11+AW11+AS11+AO11+AK11+AG11+AC11+Y11+U11+Q11+M11 -> 0 | BJ11: =BF11+BB11+AX11+AT11+AP11+AL11+AH11+AD11+Z11+V11+R11+N11 -> 0 | BK11: =IF(AND(BI11="",BJ11=""),"-",BJ11-BI11) -> 0 | BL11: =IFERROR((BJ11/BI11)-1,"-") -> -
B12: 7 | C12: NOME DO PRODUTO/SERVIÇO | D12: 60 | E12: 0.35 | F12: 100000 | G12: =F12/$F$3 -> 0.025380711 | H12: =G12+H11 -> 0.67005076 | J12: 8 | K12: NOME DO PRODUTO | L12: 100000 | O12: =IF(AND(M12="",N12=""),"-",N12-M12) -> - | P12: =IFERROR((N12/M12)-1,"-") -> - | S12: =IF(AND(Q12="",R12=""),"-",R12-Q12) -> - | T12: =IFERROR((R12/Q12)-1,"-") -> - | W12: =IF(AND(U12="",V12=""),"-",V12-U12) -> - | X12: =IFERROR((V12/U12)-1,"-") -> - | AA12: =IF(AND(Y12="",Z12=""),"-",Z12-Y12) -> - | AB12: =IFERROR((Z12/Y12)-1,"-") -> - | AE12: =IF(AND(AC12="",AD12=""),"-",AD12-AC12) -> - | AF12: =IFERROR((AD12/AC12)-1,"-") -> - | AI12: =IF(AND(AG12="",AH12=""),"-",AH12-AG12) -> - | AJ12: =IFERROR((AH12/AG12)-1,"-") -> - | AM12: =IF(AND(AK12="",AL12=""),"-",AL12-AK12) -> - | AN12: =IFERROR((AL12/AK12)-1,"-") -> - | AQ12: =IF(AND(AO12="",AP12=""),"-",AP12-AO12) -> - | AR12: =IFERROR((AP12/AO12)-1,"-") -> - | AU12: =IF(AND(AS12="",AT12=""),"-",AT12-AS12) -> - | AV12: =IFERROR((AT12/AS12)-1,"-") -> - | AY12: =IF(AND(AW12="",AX12=""),"-",AX12-AW12) -> - | AZ12: =IFERROR((AX12/AW12)-1,"-") -> - | BC12: =IF(AND(BA12="",BB12=""),"-",BB12-BA12) -> - | BD12: =IFERROR((BB12/BA12)-1,"-") -> - | BG12: =IF(AND(BE12="",BF12=""),"-",BF12-BE12) -> - | BH12: =IFERROR((BF12/BE12)-1,"-") -> - | BI12: =BE12+BA12+AW12+AS12+AO12+AK12+AG12+AC12+Y12+U12+Q12+M12 -> 0 | BJ12: =BF12+BB12+AX12+AT12+AP12+AL12+AH12+AD12+Z12+V12+R12+N12 -> 0 | BK12: =IF(AND(BI12="",BJ12=""),"-",BJ12-BI12) -> 0 | BL12: =IFERROR((BJ12/BI12)-1,"-") -> -
B13: 8 | C13: NOME DO PRODUTO/SERVIÇO | D13: 20 | E13: 0.01 | F13: 100000 | G13: =F13/$F$3 -> 0.025380711 | H13: =G13+H12 -> 0.69543147 | J13: 9 | K13: NOME DO PRODUTO | L13: 100000 | O13: =IF(AND(M13="",N13=""),"-",N13-M13) -> - | P13: =IFERROR((N13/M13)-1,"-") -> - | S13: =IF(AND(Q13="",R13=""),"-",R13-Q13) -> - | T13: =IFERROR((R13/Q13)-1,"-") -> - | W13: =IF(AND(U13="",V13=""),"-",V13-U13) -> - | X13: =IFERROR((V13/U13)-1,"-") -> - | AA13: =IF(AND(Y13="",Z13=""),"-",Z13-Y13) -> - | AB13: =IFERROR((Z13/Y13)-1,"-") -> - | AE13: =IF(AND(AC13="",AD13=""),"-",AD13-AC13) -> - | AF13: =IFERROR((AD13/AC13)-1,"-") -> - | AI13: =IF(AND(AG13="",AH13=""),"-",AH13-AG13) -> - | AJ13: =IFERROR((AH13/AG13)-1,"-") -> - | AM13: =IF(AND(AK13="",AL13=""),"-",AL13-AK13) -> - | AN13: =IFERROR((AL13/AK13)-1,"-") -> - | AQ13: =IF(AND(AO13="",AP13=""),"-",AP13-AO13) -> - | AR13: =IFERROR((AP13/AO13)-1,"-") -> - | AU13: =IF(AND(AS13="",AT13=""),"-",AT13-AS13) -> - | AV13: =IFERROR((AT13/AS13)-1,"-") -> - | AY13: =IF(AND(AW13="",AX13=""),"-",AX13-AW13) -> - | AZ13: =IFERROR((AX13/AW13)-1,"-") -> - | BC13: =IF(AND(BA13="",BB13=""),"-",BB13-BA13) -> - | BD13: =IFERROR((BB13/BA13)-1,"-") -> - | BG13: =IF(AND(BE13="",BF13=""),"-",BF13-BE13) -> - | BH13: =IFERROR((BF13/BE13)-1,"-") -> - | BI13: =BE13+BA13+AW13+AS13+AO13+AK13+AG13+AC13+Y13+U13+Q13+M13 -> 0 | BJ13: =BF13+BB13+AX13+AT13+AP13+AL13+AH13+AD13+Z13+V13+R13+N13 -> 0 | BK13: =IF(AND(BI13="",BJ13=""),"-",BJ13-BI13) -> 0 | BL13: =IFERROR((BJ13/BI13)-1,"-") -> -
B14: 9 | C14: NOME DO PRODUTO/SERVIÇO | D14: 90 | E14: 0.02 | F14: 100000 | G14: =F14/$F$3 -> 0.025380711 | H14: =G14+H13 -> 0.72081218 | J14: 10 | K14: NOME DO PRODUTO | L14: 100000 | O14: =IF(AND(M14="",N14=""),"-",N14-M14) -> - | P14: =IFERROR((N14/M14)-1,"-") -> - | S14: =IF(AND(Q14="",R14=""),"-",R14-Q14) -> - | T14: =IFERROR((R14/Q14)-1,"-") -> - | W14: =IF(AND(U14="",V14=""),"-",V14-U14) -> - | X14: =IFERROR((V14/U14)-1,"-") -> - | AA14: =IF(AND(Y14="",Z14=""),"-",Z14-Y14) -> - | AB14: =IFERROR((Z14/Y14)-1,"-") -> - | AE14: =IF(AND(AC14="",AD14=""),"-",AD14-AC14) -> - | AF14: =IFERROR((AD14/AC14)-1,"-") -> - | AI14: =IF(AND(AG14="",AH14=""),"-",AH14-AG14) -> - | AJ14: =IFERROR((AH14/AG14)-1,"-") -> - | AM14: =IF(AND(AK14="",AL14=""),"-",AL14-AK14) -> - | AN14: =IFERROR((AL14/AK14)-1,"-") -> - | AQ14: =IF(AND(AO14="",AP14=""),"-",AP14-AO14) -> - | AR14: =IFERROR((AP14/AO14)-1,"-") -> - | AU14: =IF(AND(AS14="",AT14=""),"-",AT14-AS14) -> - | AV14: =IFERROR((AT14/AS14)-1,"-") -> - | AY14: =IF(AND(AW14="",AX14=""),"-",AX14-AW14) -> - | AZ14: =IFERROR((AX14/AW14)-1,"-") -> - | BC14: =IF(AND(BA14="",BB14=""),"-",BB14-BA14) -> - | BD14: =IFERROR((BB14/BA14)-1,"-") -> - | BG14: =IF(AND(BE14="",BF14=""),"-",BF14-BE14) -> - | BH14: =IFERROR((BF14/BE14)-1,"-") -> - | BI14: =BE14+BA14+AW14+AS14+AO14+AK14+AG14+AC14+Y14+U14+Q14+M14 -> 0 | BJ14: =BF14+BB14+AX14+AT14+AP14+AL14+AH14+AD14+Z14+V14+R14+N14 -> 0 | BK14: =IF(AND(BI14="",BJ14=""),"-",BJ14-BI14) -> 0 | BL14: =IFERROR((BJ14/BI14)-1,"-") -> -
B15: 10 | C15: NOME DO PRODUTO/SERVIÇO | D15: 200 | E15: 0.03 | F15: 100000 | G15: =F15/$F$3 -> 0.025380711 | H15: =G15+H14 -> 0.74619289 | J15: 11 | K15: NOME DO PRODUTO | L15: 100000 | O15: =IF(AND(M15="",N15=""),"-",N15-M15) -> - | P15: =IFERROR((N15/M15)-1,"-") -> - | S15: =IF(AND(Q15="",R15=""),"-",R15-Q15) -> - | T15: =IFERROR((R15/Q15)-1,"-") -> - | W15: =IF(AND(U15="",V15=""),"-",V15-U15) -> - | X15: =IFERROR((V15/U15)-1,"-") -> - | AA15: =IF(AND(Y15="",Z15=""),"-",Z15-Y15) -> - | AB15: =IFERROR((Z15/Y15)-1,"-") -> - | AE15: =IF(AND(AC15="",AD15=""),"-",AD15-AC15) -> - | AF15: =IFERROR((AD15/AC15)-1,"-") -> - | AI15: =IF(AND(AG15="",AH15=""),"-",AH15-AG15) -> - | AJ15: =IFERROR((AH15/AG15)-1,"-") -> - | AM15: =IF(AND(AK15="",AL15=""),"-",AL15-AK15) -> - | AN15: =IFERROR((AL15/AK15)-1,"-") -> - | AQ15: =IF(AND(AO15="",AP15=""),"-",AP15-AO15) -> - | AR15: =IFERROR((AP15/AO15)-1,"-") -> - | AU15: =IF(AND(AS15="",AT15=""),"-",AT15-AS15) -> - | AV15: =IFERROR((AT15/AS15)-1,"-") -> - | AY15: =IF(AND(AW15="",AX15=""),"-",AX15-AW15) -> - | AZ15: =IFERROR((AX15/AW15)-1,"-") -> - | BC15: =IF(AND(BA15="",BB15=""),"-",BB15-BA15) -> - | BD15: =IFERROR((BB15/BA15)-1,"-") -> - | BG15: =IF(AND(BE15="",BF15=""),"-",BF15-BE15) -> - | BH15: =IFERROR((BF15/BE15)-1,"-") -> - | BI15: =BE15+BA15+AW15+AS15+AO15+AK15+AG15+AC15+Y15+U15+Q15+M15 -> 0 | BJ15: =BF15+BB15+AX15+AT15+AP15+AL15+AH15+AD15+Z15+V15+R15+N15 -> 0 | BK15: =IF(AND(BI15="",BJ15=""),"-",BJ15-BI15) -> 0 | BL15: =IFERROR((BJ15/BI15)-1,"-") -> -
B16: 11 | C16: NOME DO PRODUTO/SERVIÇO | D16: 20 | E16: 0.03 | F16: 100000 | G16: =F16/$F$3 -> 0.025380711 | H16: =G16+H15 -> 0.7715736 | J16: 12 | K16: NOME DO PRODUTO | L16: 100000 | O16: =IF(AND(M16="",N16=""),"-",N16-M16) -> - | P16: =IFERROR((N16/M16)-1,"-") -> - | S16: =IF(AND(Q16="",R16=""),"-",R16-Q16) -> - | T16: =IFERROR((R16/Q16)-1,"-") -> - | W16: =IF(AND(U16="",V16=""),"-",V16-U16) -> - | X16: =IFERROR((V16/U16)-1,"-") -> - | AA16: =IF(AND(Y16="",Z16=""),"-",Z16-Y16) -> - | AB16: =IFERROR((Z16/Y16)-1,"-") -> - | AE16: =IF(AND(AC16="",AD16=""),"-",AD16-AC16) -> - | AF16: =IFERROR((AD16/AC16)-1,"-") -> - | AI16: =IF(AND(AG16="",AH16=""),"-",AH16-AG16) -> - | AJ16: =IFERROR((AH16/AG16)-1,"-") -> - | AM16: =IF(AND(AK16="",AL16=""),"-",AL16-AK16) -> - | AN16: =IFERROR((AL16/AK16)-1,"-") -> - | AQ16: =IF(AND(AO16="",AP16=""),"-",AP16-AO16) -> - | AR16: =IFERROR((AP16/AO16)-1,"-") -> - | AU16: =IF(AND(AS16="",AT16=""),"-",AT16-AS16) -> - | AV16: =IFERROR((AT16/AS16)-1,"-") -> - | AY16: =IF(AND(AW16="",AX16=""),"-",AX16-AW16) -> - | AZ16: =IFERROR((AX16/AW16)-1,"-") -> - | BC16: =IF(AND(BA16="",BB16=""),"-",BB16-BA16) -> - | BD16: =IFERROR((BB16/BA16)-1,"-") -> - | BG16: =IF(AND(BE16="",BF16=""),"-",BF16-BE16) -> - | BH16: =IFERROR((BF16/BE16)-1,"-") -> - | BI16: =BE16+BA16+AW16+AS16+AO16+AK16+AG16+AC16+Y16+U16+Q16+M16 -> 0 | BJ16: =BF16+BB16+AX16+AT16+AP16+AL16+AH16+AD16+Z16+V16+R16+N16 -> 0 | BK16: =IF(AND(BI16="",BJ16=""),"-",BJ16-BI16) -> 0 | BL16: =IFERROR((BJ16/BI16)-1,"-") -> -
B17: 12 | C17: NOME DO PRODUTO/SERVIÇO | D17: 40 | E17: 0.04 | F17: 100000 | G17: =F17/$F$3 -> 0.025380711 | H17: =G17+H16 -> 0.79695431 | J17: 13 | K17: NOME DO PRODUTO | L17: 100000 | O17: =IF(AND(M17="",N17=""),"-",N17-M17) -> - | P17: =IFERROR((N17/M17)-1,"-") -> - | S17: =IF(AND(Q17="",R17=""),"-",R17-Q17) -> - | T17: =IFERROR((R17/Q17)-1,"-") -> - | W17: =IF(AND(U17="",V17=""),"-",V17-U17) -> - | X17: =IFERROR((V17/U17)-1,"-") -> - | AA17: =IF(AND(Y17="",Z17=""),"-",Z17-Y17) -> - | AB17: =IFERROR((Z17/Y17)-1,"-") -> - | AE17: =IF(AND(AC17="",AD17=""),"-",AD17-AC17) -> - | AF17: =IFERROR((AD17/AC17)-1,"-") -> - | AI17: =IF(AND(AG17="",AH17=""),"-",AH17-AG17) -> - | AJ17: =IFERROR((AH17/AG17)-1,"-") -> - | AM17: =IF(AND(AK17="",AL17=""),"-",AL17-AK17) -> - | AN17: =IFERROR((AL17/AK17)-1,"-") -> - | AQ17: =IF(AND(AO17="",AP17=""),"-",AP17-AO17) -> - | AR17: =IFERROR((AP17/AO17)-1,"-") -> - | AU17: =IF(AND(AS17="",AT17=""),"-",AT17-AS17) -> - | AV17: =IFERROR((AT17/AS17)-1,"-") -> - | AY17: =IF(AND(AW17="",AX17=""),"-",AX17-AW17) -> - | AZ17: =IFERROR((AX17/AW17)-1,"-") -> - | BC17: =IF(AND(BA17="",BB17=""),"-",BB17-BA17) -> - | BD17: =IFERROR((BB17/BA17)-1,"-") -> - | BG17: =IF(AND(BE17="",BF17=""),"-",BF17-BE17) -> - | BH17: =IFERROR((BF17/BE17)-1,"-") -> - | BI17: =BE17+BA17+AW17+AS17+AO17+AK17+AG17+AC17+Y17+U17+Q17+M17 -> 0 | BJ17: =BF17+BB17+AX17+AT17+AP17+AL17+AH17+AD17+Z17+V17+R17+N17 -> 0 | BK17: =IF(AND(BI17="",BJ17=""),"-",BJ17-BI17) -> 0 | BL17: =IFERROR((BJ17/BI17)-1,"-") -> -
B18: 13 | C18: NOME DO PRODUTO/SERVIÇO | D18: 60 | E18: 0.05 | F18: 100000 | G18: =F18/$F$3 -> 0.025380711 | H18: =G18+H17 -> 0.82233503 | J18: 14 | K18: NOME DO PRODUTO | O18: =IF(AND(M18="",N18=""),"-",N18-M18) -> - | P18: =IFERROR((N18/M18)-1,"-") -> - | S18: =IF(AND(Q18="",R18=""),"-",R18-Q18) -> - | T18: =IFERROR((R18/Q18)-1,"-") -> - | W18: =IF(AND(U18="",V18=""),"-",V18-U18) -> - | X18: =IFERROR((V18/U18)-1,"-") -> - | AA18: =IF(AND(Y18="",Z18=""),"-",Z18-Y18) -> - | AB18: =IFERROR((Z18/Y18)-1,"-") -> - | AE18: =IF(AND(AC18="",AD18=""),"-",AD18-AC18) -> - | AF18: =IFERROR((AD18/AC18)-1,"-") -> - | AI18: =IF(AND(AG18="",AH18=""),"-",AH18-AG18) -> - | AJ18: =IFERROR((AH18/AG18)-1,"-") -> - | AM18: =IF(AND(AK18="",AL18=""),"-",AL18-AK18) -> - | AN18: =IFERROR((AL18/AK18)-1,"-") -> - | AQ18: =IF(AND(AO18="",AP18=""),"-",AP18-AO18) -> - | AR18: =IFERROR((AP18/AO18)-1,"-") -> - | AU18: =IF(AND(AS18="",AT18=""),"-",AT18-AS18) -> - | AV18: =IFERROR((AT18/AS18)-1,"-") -> - | AY18: =IF(AND(AW18="",AX18=""),"-",AX18-AW18) -> - | AZ18: =IFERROR((AX18/AW18)-1,"-") -> - | BC18: =IF(AND(BA18="",BB18=""),"-",BB18-BA18) -> - | BD18: =IFERROR((BB18/BA18)-1,"-") -> - | BG18: =IF(AND(BE18="",BF18=""),"-",BF18-BE18) -> - | BH18: =IFERROR((BF18/BE18)-1,"-") -> - | BI18: =BE18+BA18+AW18+AS18+AO18+AK18+AG18+AC18+Y18+U18+Q18+M18 -> 0 | BJ18: =BF18+BB18+AX18+AT18+AP18+AL18+AH18+AD18+Z18+V18+R18+N18 -> 0 | BK18: =IF(AND(BI18="",BJ18=""),"-",BJ18-BI18) -> 0 | BL18: =IFERROR((BJ18/BI18)-1,"-") -> -
B19: 14 | C19: NOME DO PRODUTO/SERVIÇO | D19: 80 | E19: 0.06 | F19: 100000 | G19: =F19/$F$3 -> 0.025380711 | H19: =G19+H18 -> 0.84771574 | J19: 15 | K19: NOME DO PRODUTO | O19: =IF(AND(M19="",N19=""),"-",N19-M19) -> - | P19: =IFERROR((N19/M19)-1,"-") -> - | S19: =IF(AND(Q19="",R19=""),"-",R19-Q19) -> - | T19: =IFERROR((R19/Q19)-1,"-") -> - | W19: =IF(AND(U19="",V19=""),"-",V19-U19) -> - | X19: =IFERROR((V19/U19)-1,"-") -> - | AA19: =IF(AND(Y19="",Z19=""),"-",Z19-Y19) -> - | AB19: =IFERROR((Z19/Y19)-1,"-") -> - | AE19: =IF(AND(AC19="",AD19=""),"-",AD19-AC19) -> - | AF19: =IFERROR((AD19/AC19)-1,"-") -> - | AI19: =IF(AND(AG19="",AH19=""),"-",AH19-AG19) -> - | AJ19: =IFERROR((AH19/AG19)-1,"-") -> - | AM19: =IF(AND(AK19="",AL19=""),"-",AL19-AK19) -> - | AN19: =IFERROR((AL19/AK19)-1,"-") -> - | AQ19: =IF(AND(AO19="",AP19=""),"-",AP19-AO19) -> - | AR19: =IFERROR((AP19/AO19)-1,"-") -> - | AU19: =IF(AND(AS19="",AT19=""),"-",AT19-AS19) -> - | AV19: =IFERROR((AT19/AS19)-1,"-") -> - | AY19: =IF(AND(AW19="",AX19=""),"-",AX19-AW19) -> - | AZ19: =IFERROR((AX19/AW19)-1,"-") -> - | BC19: =IF(AND(BA19="",BB19=""),"-",BB19-BA19) -> - | BD19: =IFERROR((BB19/BA19)-1,"-") -> - | BG19: =IF(AND(BE19="",BF19=""),"-",BF19-BE19) -> - | BH19: =IFERROR((BF19/BE19)-1,"-") -> - | BI19: =BE19+BA19+AW19+AS19+AO19+AK19+AG19+AC19+Y19+U19+Q19+M19 -> 0 | BJ19: =BF19+BB19+AX19+AT19+AP19+AL19+AH19+AD19+Z19+V19+R19+N19 -> 0 | BK19: =IF(AND(BI19="",BJ19=""),"-",BJ19-BI19) -> 0 | BL19: =IFERROR((BJ19/BI19)-1,"-") -> -
B20: 15 | C20: NOME DO PRODUTO/SERVIÇO | D20: 100 | E20: 0.05 | F20: 100000 | G20: =F20/$F$3 -> 0.025380711 | H20: =G20+H19 -> 0.87309645 | J20: 16 | K20: NOME DO PRODUTO | O20: =IF(AND(M20="",N20=""),"-",N20-M20) -> - | P20: =IFERROR((N20/M20)-1,"-") -> - | S20: =IF(AND(Q20="",R20=""),"-",R20-Q20) -> - | T20: =IFERROR((R20/Q20)-1,"-") -> - | W20: =IF(AND(U20="",V20=""),"-",V20-U20) -> - | X20: =IFERROR((V20/U20)-1,"-") -> - | AA20: =IF(AND(Y20="",Z20=""),"-",Z20-Y20) -> - | AB20: =IFERROR((Z20/Y20)-1,"-") -> - | AE20: =IF(AND(AC20="",AD20=""),"-",AD20-AC20) -> - | AF20: =IFERROR((AD20/AC20)-1,"-") -> - | AI20: =IF(AND(AG20="",AH20=""),"-",AH20-AG20) -> - | AJ20: =IFERROR((AH20/AG20)-1,"-") -> - | AM20: =IF(AND(AK20="",AL20=""),"-",AL20-AK20) -> - | AN20: =IFERROR((AL20/AK20)-1,"-") -> - | AQ20: =IF(AND(AO20="",AP20=""),"-",AP20-AO20) -> - | AR20: =IFERROR((AP20/AO20)-1,"-") -> - | AU20: =IF(AND(AS20="",AT20=""),"-",AT20-AS20) -> - | AV20: =IFERROR((AT20/AS20)-1,"-") -> - | AY20: =IF(AND(AW20="",AX20=""),"-",AX20-AW20) -> - | AZ20: =IFERROR((AX20/AW20)-1,"-") -> - | BC20: =IF(AND(BA20="",BB20=""),"-",BB20-BA20) -> - | BD20: =IFERROR((BB20/BA20)-1,"-") -> - | BG20: =IF(AND(BE20="",BF20=""),"-",BF20-BE20) -> - | BH20: =IFERROR((BF20/BE20)-1,"-") -> - | BI20: =BE20+BA20+AW20+AS20+AO20+AK20+AG20+AC20+Y20+U20+Q20+M20 -> 0 | BJ20: =BF20+BB20+AX20+AT20+AP20+AL20+AH20+AD20+Z20+V20+R20+N20 -> 0 | BK20: =IF(AND(BI20="",BJ20=""),"-",BJ20-BI20) -> 0 | BL20: =IFERROR((BJ20/BI20)-1,"-") -> -
B21: 16 | C21: NOME DO PRODUTO/SERVIÇO | D21: 150 | E21: 0.05 | F21: 100000 | G21: =F21/$F$3 -> 0.025380711 | H21: =G21+H20 -> 0.89847716 | J21: 17 | K21: NOME DO PRODUTO | O21: =IF(AND(M21="",N21=""),"-",N21-M21) -> - | P21: =IFERROR((N21/M21)-1,"-") -> - | S21: =IF(AND(Q21="",R21=""),"-",R21-Q21) -> - | T21: =IFERROR((R21/Q21)-1,"-") -> - | W21: =IF(AND(U21="",V21=""),"-",V21-U21) -> - | X21: =IFERROR((V21/U21)-1,"-") -> - | AA21: =IF(AND(Y21="",Z21=""),"-",Z21-Y21) -> - | AB21: =IFERROR((Z21/Y21)-1,"-") -> - | AE21: =IF(AND(AC21="",AD21=""),"-",AD21-AC21) -> - | AF21: =IFERROR((AD21/AC21)-1,"-") -> - | AI21: =IF(AND(AG21="",AH21=""),"-",AH21-AG21) -> - | AJ21: =IFERROR((AH21/AG21)-1,"-") -> - | AM21: =IF(AND(AK21="",AL21=""),"-",AL21-AK21) -> - | AN21: =IFERROR((AL21/AK21)-1,"-") -> - | AQ21: =IF(AND(AO21="",AP21=""),"-",AP21-AO21) -> - | AR21: =IFERROR((AP21/AO21)-1,"-") -> - | AU21: =IF(AND(AS21="",AT21=""),"-",AT21-AS21) -> - | AV21: =IFERROR((AT21/AS21)-1,"-") -> - | AY21: =IF(AND(AW21="",AX21=""),"-",AX21-AW21) -> - | AZ21: =IFERROR((AX21/AW21)-1,"-") -> - | BC21: =IF(AND(BA21="",BB21=""),"-",BB21-BA21) -> - | BD21: =IFERROR((BB21/BA21)-1,"-") -> - | BG21: =IF(AND(BE21="",BF21=""),"-",BF21-BE21) -> - | BH21: =IFERROR((BF21/BE21)-1,"-") -> - | BI21: =BE21+BA21+AW21+AS21+AO21+AK21+AG21+AC21+Y21+U21+Q21+M21 -> 0 | BJ21: =BF21+BB21+AX21+AT21+AP21+AL21+AH21+AD21+Z21+V21+R21+N21 -> 0 | BK21: =IF(AND(BI21="",BJ21=""),"-",BJ21-BI21) -> 0 | BL21: =IFERROR((BJ21/BI21)-1,"-") -> -
B22: 17 | C22: NOME DO PRODUTO/SERVIÇO | D22: 60 | E22: 0.05 | F22: 100000 | G22: =F22/$F$3 -> 0.025380711 | H22: =G22+H21 -> 0.92385787 | J22: 18 | K22: NOME DO PRODUTO | O22: =IF(AND(M22="",N22=""),"-",N22-M22) -> - | P22: =IFERROR((N22/M22)-1,"-") -> - | S22: =IF(AND(Q22="",R22=""),"-",R22-Q22) -> - | T22: =IFERROR((R22/Q22)-1,"-") -> - | W22: =IF(AND(U22="",V22=""),"-",V22-U22) -> - | X22: =IFERROR((V22/U22)-1,"-") -> - | AA22: =IF(AND(Y22="",Z22=""),"-",Z22-Y22) -> - | AB22: =IFERROR((Z22/Y22)-1,"-") -> - | AE22: =IF(AND(AC22="",AD22=""),"-",AD22-AC22) -> - | AF22: =IFERROR((AD22/AC22)-1,"-") -> - | AI22: =IF(AND(AG22="",AH22=""),"-",AH22-AG22) -> - | AJ22: =IFERROR((AH22/AG22)-1,"-") -> - | AM22: =IF(AND(AK22="",AL22=""),"-",AL22-AK22) -> - | AN22: =IFERROR((AL22/AK22)-1,"-") -> - | AQ22: =IF(AND(AO22="",AP22=""),"-",AP22-AO22) -> - | AR22: =IFERROR((AP22/AO22)-1,"-") -> - | AU22: =IF(AND(AS22="",AT22=""),"-",AT22-AS22) -> - | AV22: =IFERROR((AT22/AS22)-1,"-") -> - | AY22: =IF(AND(AW22="",AX22=""),"-",AX22-AW22) -> - | AZ22: =IFERROR((AX22/AW22)-1,"-") -> - | BC22: =IF(AND(BA22="",BB22=""),"-",BB22-BA22) -> - | BD22: =IFERROR((BB22/BA22)-1,"-") -> - | BG22: =IF(AND(BE22="",BF22=""),"-",BF22-BE22) -> - | BH22: =IFERROR((BF22/BE22)-1,"-") -> - | BI22: =BE22+BA22+AW22+AS22+AO22+AK22+AG22+AC22+Y22+U22+Q22+M22 -> 0 | BJ22: =BF22+BB22+AX22+AT22+AP22+AL22+AH22+AD22+Z22+V22+R22+N22 -> 0 | BK22: =IF(AND(BI22="",BJ22=""),"-",BJ22-BI22) -> 0 | BL22: =IFERROR((BJ22/BI22)-1,"-") -> -
B23: 18 | C23: NOME DO PRODUTO/SERVIÇO | D23: 20 | E23: 0.05 | F23: 100000 | G23: =F23/$F$3 -> 0.025380711 | H23: =G23+H22 -> 0.94923858 | J23: 19 | K23: NOME DO PRODUTO | O23: =IF(AND(M23="",N23=""),"-",N23-M23) -> - | P23: =IFERROR((N23/M23)-1,"-") -> - | S23: =IF(AND(Q23="",R23=""),"-",R23-Q23) -> - | T23: =IFERROR((R23/Q23)-1,"-") -> - | W23: =IF(AND(U23="",V23=""),"-",V23-U23) -> - | X23: =IFERROR((V23/U23)-1,"-") -> - | AA23: =IF(AND(Y23="",Z23=""),"-",Z23-Y23) -> - | AB23: =IFERROR((Z23/Y23)-1,"-") -> - | AE23: =IF(AND(AC23="",AD23=""),"-",AD23-AC23) -> - | AF23: =IFERROR((AD23/AC23)-1,"-") -> - | AI23: =IF(AND(AG23="",AH23=""),"-",AH23-AG23) -> - | AJ23: =IFERROR((AH23/AG23)-1,"-") -> - | AM23: =IF(AND(AK23="",AL23=""),"-",AL23-AK23) -> - | AN23: =IFERROR((AL23/AK23)-1,"-") -> - | AQ23: =IF(AND(AO23="",AP23=""),"-",AP23-AO23) -> - | AR23: =IFERROR((AP23/AO23)-1,"-") -> - | AU23: =IF(AND(AS23="",AT23=""),"-",AT23-AS23) -> - | AV23: =IFERROR((AT23/AS23)-1,"-") -> - | AY23: =IF(AND(AW23="",AX23=""),"-",AX23-AW23) -> - | AZ23: =IFERROR((AX23/AW23)-1,"-") -> - | BC23: =IF(AND(BA23="",BB23=""),"-",BB23-BA23) -> - | BD23: =IFERROR((BB23/BA23)-1,"-") -> - | BG23: =IF(AND(BE23="",BF23=""),"-",BF23-BE23) -> - | BH23: =IFERROR((BF23/BE23)-1,"-") -> - | BI23: =BE23+BA23+AW23+AS23+AO23+AK23+AG23+AC23+Y23+U23+Q23+M23 -> 0 | BJ23: =BF23+BB23+AX23+AT23+AP23+AL23+AH23+AD23+Z23+V23+R23+N23 -> 0 | BK23: =IF(AND(BI23="",BJ23=""),"-",BJ23-BI23) -> 0 | BL23: =IFERROR((BJ23/BI23)-1,"-") -> -
B24: 19 | C24: NOME DO PRODUTO/SERVIÇO | D24: 90 | E24: 0.05 | F24: 100000 | G24: =F24/$F$3 -> 0.025380711 | H24: =G24+H23 -> 0.97461929 | J24: 20 | K24: NOME DO PRODUTO | O24: =IF(AND(M24="",N24=""),"-",N24-M24) -> - | P24: =IFERROR((N24/M24)-1,"-") -> - | S24: =IF(AND(Q24="",R24=""),"-",R24-Q24) -> - | T24: =IFERROR((R24/Q24)-1,"-") -> - | W24: =IF(AND(U24="",V24=""),"-",V24-U24) -> - | X24: =IFERROR((V24/U24)-1,"-") -> - | AA24: =IF(AND(Y24="",Z24=""),"-",Z24-Y24) -> - | AB24: =IFERROR((Z24/Y24)-1,"-") -> - | AE24: =IF(AND(AC24="",AD24=""),"-",AD24-AC24) -> - | AF24: =IFERROR((AD24/AC24)-1,"-") -> - | AI24: =IF(AND(AG24="",AH24=""),"-",AH24-AG24) -> - | AJ24: =IFERROR((AH24/AG24)-1,"-") -> - | AM24: =IF(AND(AK24="",AL24=""),"-",AL24-AK24) -> - | AN24: =IFERROR((AL24/AK24)-1,"-") -> - | AQ24: =IF(AND(AO24="",AP24=""),"-",AP24-AO24) -> - | AR24: =IFERROR((AP24/AO24)-1,"-") -> - | AU24: =IF(AND(AS24="",AT24=""),"-",AT24-AS24) -> - | AV24: =IFERROR((AT24/AS24)-1,"-") -> - | AY24: =IF(AND(AW24="",AX24=""),"-",AX24-AW24) -> - | AZ24: =IFERROR((AX24/AW24)-1,"-") -> - | BC24: =IF(AND(BA24="",BB24=""),"-",BB24-BA24) -> - | BD24: =IFERROR((BB24/BA24)-1,"-") -> - | BG24: =IF(AND(BE24="",BF24=""),"-",BF24-BE24) -> - | BH24: =IFERROR((BF24/BE24)-1,"-") -> - | BI24: =BE24+BA24+AW24+AS24+AO24+AK24+AG24+AC24+Y24+U24+Q24+M24 -> 0 | BJ24: =BF24+BB24+AX24+AT24+AP24+AL24+AH24+AD24+Z24+V24+R24+N24 -> 0 | BK24: =IF(AND(BI24="",BJ24=""),"-",BJ24-BI24) -> 0 | BL24: =IFERROR((BJ24/BI24)-1,"-") -> -
B25: 20 | C25: NOME DO PRODUTO/SERVIÇO | D25: 200 | E25: 0.05 | F25: 100000 | G25: =F25/$F$3 -> 0.025380711 | H25: =G25+H24 -> 1 | J25: 21 | K25: NOME DO PRODUTO | O25: =IF(AND(M25="",N25=""),"-",N25-M25) -> - | P25: =IFERROR((N25/M25)-1,"-") -> - | S25: =IF(AND(Q25="",R25=""),"-",R25-Q25) -> - | T25: =IFERROR((R25/Q25)-1,"-") -> - | W25: =IF(AND(U25="",V25=""),"-",V25-U25) -> - | X25: =IFERROR((V25/U25)-1,"-") -> - | AA25: =IF(AND(Y25="",Z25=""),"-",Z25-Y25) -> - | AB25: =IFERROR((Z25/Y25)-1,"-") -> - | AE25: =IF(AND(AC25="",AD25=""),"-",AD25-AC25) -> - | AF25: =IFERROR((AD25/AC25)-1,"-") -> - | AI25: =IF(AND(AG25="",AH25=""),"-",AH25-AG25) -> - | AJ25: =IFERROR((AH25/AG25)-1,"-") -> - | AM25: =IF(AND(AK25="",AL25=""),"-",AL25-AK25) -> - | AN25: =IFERROR((AL25/AK25)-1,"-") -> - | AQ25: =IF(AND(AO25="",AP25=""),"-",AP25-AO25) -> - | AR25: =IFERROR((AP25/AO25)-1,"-") -> - | AU25: =IF(AND(AS25="",AT25=""),"-",AT25-AS25) -> - | AV25: =IFERROR((AT25/AS25)-1,"-") -> - | AY25: =IF(AND(AW25="",AX25=""),"-",AX25-AW25) -> - | AZ25: =IFERROR((AX25/AW25)-1,"-") -> - | BC25: =IF(AND(BA25="",BB25=""),"-",BB25-BA25) -> - | BD25: =IFERROR((BB25/BA25)-1,"-") -> - | BG25: =IF(AND(BE25="",BF25=""),"-",BF25-BE25) -> - | BH25: =IFERROR((BF25/BE25)-1,"-") -> - | BI25: =BE25+BA25+AW25+AS25+AO25+AK25+AG25+AC25+Y25+U25+Q25+M25 -> 0 | BJ25: =BF25+BB25+AX25+AT25+AP25+AL25+AH25+AD25+Z25+V25+R25+N25 -> 0 | BK25: =IF(AND(BI25="",BJ25=""),"-",BJ25-BI25) -> 0 | BL25: =IFERROR((BJ25/BI25)-1,"-") -> -
K26: TOTAL GERAL | L26: =SUM(L5:L25) -> 1300000 | M26: =SUM(M5:M25) -> 250000 | N26: =SUM(N5:N25) -> 275000 | O26: =IF(AND(M26="",N26=""),"-",N26-M26) -> 25000 | P26: =IFERROR((N26/M26)-1,"-") -> 0.1 | Q26: =SUM(Q5:Q25) -> 0 | R26: =SUM(R5:R25) -> 0 | S26: =IF(AND(Q26="",R26=""),"-",R26-Q26) -> 0 | T26: =IFERROR((R26/Q26)-1,"-") -> - | U26: =SUM(U5:U25) -> 0 | V26: =SUM(V5:V25) -> 0 | W26: =IF(AND(U26="",V26=""),"-",V26-U26) -> 0 | X26: =IFERROR((V26/U26)-1,"-") -> - | Y26: =SUM(Y5:Y25) -> 0 | Z26: =SUM(Z5:Z25) -> 0 | AA26: =IF(AND(Y26="",Z26=""),"-",Z26-Y26) -> 0 | AB26: =IFERROR((Z26/Y26)-1,"-") -> - | AC26: =SUM(AC5:AC25) -> 0 | AD26: =SUM(AD5:AD25) -> 0 | AE26: =IF(AND(AC26="",AD26=""),"-",AD26-AC26) -> 0 | AF26: =IFERROR((AD26/AC26)-1,"-") -> - | AG26: =SUM(AG5:AG25) -> 0 | AH26: =SUM(AH5:AH25) -> 0 | AI26: =IF(AND(AG26="",AH26=""),"-",AH26-AG26) -> 0 | AJ26: =IFERROR((AH26/AG26)-1,"-") -> - | AK26: =SUM(AK5:AK25) -> 0 | AL26: =SUM(AL5:AL25) -> 0 | AM26: =IF(AND(AK26="",AL26=""),"-",AL26-AK26) -> 0 | AN26: =IFERROR((AL26/AK26)-1,"-") -> - | AO26: =SUM(AO5:AO25) -> 0 | AP26: =SUM(AP5:AP25) -> 0 | AQ26: =IF(AND(AO26="",AP26=""),"-",AP26-AO26) -> 0 | AR26: =IFERROR((AP26/AO26)-1,"-") -> - | AS26: =SUM(AS5:AS25) -> 0 | AT26: =SUM(AT5:AT25) -> 0 | AU26: =IF(AND(AS26="",AT26=""),"-",AT26-AS26) -> 0 | AV26: =IFERROR((AT26/AS26)-1,"-") -> - | AW26: =SUM(AW5:AW25) -> 0 | AX26: =SUM(AX5:AX25) -> 0 | AY26: =IF(AND(AW26="",AX26=""),"-",AX26-AW26) -> 0 | AZ26: =IFERROR((AX26/AW26)-1,"-") -> - | BA26: =SUM(BA5:BA25) -> 0 | BB26: =SUM(BB5:BB25) -> 0 | BC26: =IF(AND(BA26="",BB26=""),"-",BB26-BA26) -> 0 | BD26: =IFERROR((BB26/BA26)-1,"-") -> - | BE26: =SUM(BE5:BE25) -> 0 | BF26: =SUM(BF5:BF25) -> 0 | BG26: =IF(AND(BE26="",BF26=""),"-",BF26-BE26) -> 0 | BH26: =IFERROR((BF26/BE26)-1,"-") -> - | BI26: =SUM(BI5:BI25) -> 250000 | BJ26: =SUM(BJ5:BJ25) -> 275000 | BK26: =IF(AND(BI26="",BJ26=""),"-",BJ26-BI26) -> 25000 | BL26: =IFERROR((BJ26/BI26)-1,"-") -> 0.1

Sheet 5.3
C2: < CLIQUE AQUI E VOLTE AO PAINEL INICIAL | D2: GESTÃO DO FLUXO DE CAIXA
C4: Detalhamento das Entradas e Saídas | D4: Jan | F4: Fev | H4: Mar | J4: Abr | L4: Mai | N4: Jun | P4: Jul | R4: Ago | T4: Set | V4: Out | X4: Nov | Z4: Dez
D5: Meta | E5: Real | F5: Meta | G5: Real | H5: Meta | I5: Real | J5: Meta | K5: Real | L5: Meta | M5: Real | N5: Meta | O5: Real | P5: Meta | Q5: Real | R5: Meta | S5: Real | T5: Meta | U5: Real | V5: Meta | W5: Real | X5: Meta | Y5: Real | Z5: Meta | AA5: Real
C6: ENTRADAS / CRÉDITOS
C7: Vendas da Loja | D7: 200000 | E7: 200000
C8: Vendas Online | D8: 100000 | E8: 100000 | F8: 20000 | G8: 22000 | H8: 20000 | J8: 20000 | L8: 20000 | M8: 15000 | N8: 20000 | O8: 25000 | P8: 20000 | R8: 20000 | T8: 20000 | V8: 20000 | X8: 20000 | Z8: 20000
C9: Empréstimos | D9: 100000 | E9: 100000
C10: TOTAL DAS ENTRADAS | D10: =SUM(D7:D9) -> 400000 | E10: =SUM(E7:E9) -> 400000 | F10: =SUM(F7:F9) -> 20000 | G10: =SUM(G7:G9) -> 22000 | H10: =SUM(H7:H9) -> 20000 | I10: =SUM(I7:I9) -> 0 | J10: =SUM(J7:J9) -> 20000 | K10: =SUM(K7:K9) -> 0 | ... AA10: =SUM(AA7:AA9) -> 0
C11: SAÍDAS / DÉBITOS
C12: Folha de pagamento | D12: 200000 | E12: 250000 | F12: 200000 | H12: 200000 | J12: 200000 | L12: 200000 | N12: 200000 | P12: 200000 | R12: 230000 | T12: 230000 | V12: 230000 | X12: 230000 | Z12: 230000
C13: Alimentação | D13: 1500 | E13: 1500
C14: Aluguel | D14: 5000 | E14: 5000 | F14: 5000 | H14: 5000 | J14: 15000 | L14: 15000 | N14: 15000 | P14: 15000 | R14: 15000 | T14: 15000 | V14: 15000 | X14: 15000 | Z14: 15000
C15: Combustível | D15: 2500 | E15: 2500
C16: Contabilidade | D16: 1500 | E16: 1500
C17: Despesas financeiras | D17: 1000 | E17: 1000
C18: Empréstimos | D18: 3000 | E18: 3000
C19: Energia elétrica | D19: 900 | E19: 900
C20: Equipamentos e/ou Manutenção | D20: 2300 | E20: 2300
C21: Férias | D21: 3000 | E21: 3000
C22: 13º salário | D22: 2000 | E22: 2000
C23: Fornecedores | D23: 45000 | E23: 100000
C24: Impostos e Taxas | D24: 5000 | E24: 5000
C25: Telefone | D25: 1200 | E25: 1200
C26: Despesas diversas | D26: 2900 | E26: 2900
C27: Outros pagamentos | D27: 1200 | E27: 1200
C28: TOTAL DAS SAÍDAS | D28: =SUM(D12:D27) -> 278000 | E28: =SUM(E12:E27) -> 383000 | F28: =SUM(F12:F27) -> 205000 | G28: =SUM(G12:G27) -> 0 | H28: =SUM(H12:H27) -> 205000 | I28: =SUM(I12:I27) -> 0 | J28: =SUM(J12:J27) -> 215000 | K28: =SUM(K12:K27) -> 0 | ... AA28: =SUM(AA12:AA27) -> 0
C30: LUCRO/PREJUÍZO MENSAL | D30: Jan | F30: Fev | H30: Mar | J30: Abr | L30: Mai | N30: Jun | P30: Jul | R30: Ago | T30: Set | V30: Out | X30: Nov | Z30: Dez
D31: =E10-E28 -> 17000 | F31: =G10-G28 -> 22000 | H31: =I10-I28 -> 0 | J31: =K10-K28 -> 0 | L31: =M10-M28 -> 15000 | N31: =O10-O28 -> 25000 | P31: =Q10-Q28 -> 0 | R31: =S10-S28 -> 0 | T31: =U10-U28 -> 0 | V31: =W10-W28 -> 0 | X31: =Y10-Y28 -> 0 | Z31: =AA10-AA28 -> 0
